Workbook
Name ACTIVITE: REF!$L$5:$L$20
Name AGENCE: REF!$N$5:$N$20
Name ETAPE: [1]REF!$D$5:$D$19
Name ETAPE: REF!$D$5:$D$23
Name MOIS: [1]REF!$H$5:$H$23
Name MOIS: REF!$H$5:$H$20
Name PHASE: [1]REF!$B$5:$B$11
Name PHASE: REF!$B$5:$B$12
Name PROFIL: [1]REF!$F$5:$F$13
Name PROFIL: REF!$F$5:$F$22
Name TYPE_ACHAT: REF!$J$5:$J$13

Sheet FICHE PROJET
C1: Fiche projet
B3: Nom du client | F3: Auteur :
B4: Projet | F4: Date :
B5: Référence propale
B6: Contact client
B8: Agence
B9: Service line
B10: Directeur agence
B11: Responsable SL
B12: Commercial
B14: Type de contrat
B15: Période (jj/mm/aaaa au jj/mm/aaaa)
B16: Montant du contrat | C16: =SYNTHESE!D4 -> 94925
B17: dont CA back | C17: =SYNTHESE!D64
B18: Montant du contrat back | C18: =IFERROR(SYNTHESE!D68*SYNTHESE!D63,"")

Sheet SYNTHESE
C1: Synthèse
F2: Lot | G2: (Tous) | J2: Lot | K2: (Tous)
C4: Montant du projet (€) | D4: =D8+D25+D17 -> 94925 | F4: Phase | G4: Charge | H4: Valorisation | J4: Etapes | K4: Charge | L4: Valorisation
F5: CONCEPTION | G5: 8.5 | H5: 7075 | J5: Analyse de l’existant | K5: 3 | L5: 2550
F6: CONSTRUCTION | G6: 7.5 | H6: 5625 | J6: Conception fonctionnelle détaillée | K6: 4 | L6: 3300
C7: Nombre de jours produit (jh) | D7: =WORKLOAD!F3 -> 104 | F7: VALIDATION | G7: 56 | H7: 40550 | J7: Conception Générale | K7: 1.5 | L7: 1225
C8: Jours valorisés (€) | D8: =PROFIL!J13 -> 77425 | F8: FINALISATION | G8: 6 | H8: 4650 | J8: Développement et tests unitaires | K8: 7.5 | L8: 5625
C9: Coût du projet pour Exakis Nelite (€) | D9: =PROFIL!K13 -> 38120 | F9: (vide) | G9: 0 | H9: 0 | J9: Formation | K9: 48 | L9: 34700
C10: CJM de production | D10: =IFERROR(D9/D7,"") -> 366.53846 | F10: PROVISION | G10: 4 | H10: 3025 | J10: Livraison / installation / Mise en œuvre | K10: 6 | L10: 4350
C11: Marge brute Agence (%) | D11: =IFERROR((D8-PROFIL!L13)/SYNTHESE!D8,"") -> 0.50765257 | F11: PILOTAGE | G11: 22 | H11: 16500 | J11: Pilotage projet | K11: 22 | L11: 16500
C12: Marge brute Exakis Nelite (%) | D12: =IFERROR((D8-D9)/D8,"") -> 0.50765257 | F12: Total général | G12: 104 | H12: 77425 | J12: Provision pour risque | K12: 4 | L12: 3025
C13: TJM Client (€) | D13: =IFERROR(D8/D7,"") -> 744.47115 | J13: Support | K13: 6 | L13: 4650
J14: Tests d’intégration / Recette interne | K14: 2 | L14: 1500
J15: (vide) | K15: 0 | L15: 0
C16: Frais de déplacement (€) | D16: =FRAIS!D17 -> 17500 | J16: Total général | K16: 104 | L16: 77425
C17: Montant des frais à refacturer (€) | D17: =FRAIS!E17 -> 17500
C18: Frais non refacturés / jour produit | D18: =IFERROR((D16-D17)/D7,"") -> 0
C20: Provision pour Risque (JH) | D20: =SUMIF(WORKLOAD!C4:C96,"PROVISION",WORKLOAD!F4:F96) -> 4
C21: Provision pour Risque (€) | D21: =SUMIF(WORKLOAD!C4:C96,"PROVISION",WORKLOAD!G4:G96) -> 3025
C22: Provision pour Risque (%) | D22: =IFERROR(D21/D8,"") -> 0.039070068
C24: Montant des achats mat/log (€) | D24: =ACHAT!E17 -> 0
C25: Montant des achats à refacturer (€) | D25: =ACHAT!G17 -> 0
C26: Marge achats (€) | D26: =D25-D24 -> 0
C27: Marge des Achats/Reventes (%) | D27: =IF(D24<>0,(D25-D24)/D25,"")
C29: Marge Nette Exakis Nelite (€) | D29: =D8-D9+D26+D17-D16 -> 39305
C30: Marge Nette Exakis Nelite (%) | D30: =IFERROR(D29/D4,"") -> 0.41406373
C33: FO - Nombre de jours produit (jh) | D33: =IF(SUMIF(PROFIL!C6:C12,"FO",PROFIL!I6:I12)<>0,SUMIF(PROFIL!C6:C12,"FO",PROFIL!I6:I12),"") -> 104
C34: FO - Jours valorisés (€) | D34: =IF(SUMIF(PROFIL!C6:C12,"FO",PROFIL!J6:J12)<>0,SUMIF(PROFIL!C6:C12,"FO",PROFIL!J6:J12),"") -> 77425
C35: FO - TJM Client (€) | D35: =IFERROR(D34/D33,"") -> 744.47115
C36: FO - CJM Production (€) | D36: =IF(SUMIF(PROFIL!C6:C12,"FO",PROFIL!J6:J12)<>0,SUMIF(PROFIL!C6:C12,"FO",PROFIL!K6:K12)/(SUMIF(PROFIL!C6:C12,"FO",PROFIL!I6:I12)),"") -> 366.53846
C37: FO - Marge Exakis Nelite (%) | D37: =IF(SUMIF(PROFIL!C6:C12,"FO",PROFIL!J6:J12)<>0,(SUMIF(PROFIL!C6:C12,"FO",PROFIL!J6:J12)-SUMIF(PROFIL!C6:C12,"FO",PROFIL!K6:K12))/(SUMIF(PROFIL!C6:C12,"FO",PROFIL!J6:J12)),"") -> 0.50765257
C39: CESSION - Nombre de jours produit | D39: =IF(SUMIF(PROFIL!C6:C12,"CESSION",PROFIL!I6:I12)<>0,SUMIF(PROFIL!C6:C12,"CESSION",PROFIL!I6:I12),"")
C40: CESSION - Jours valorisés (€) | D40: =IF(SUMIF(PROFIL!C6:C12,"CESSION",PROFIL!J6:J12)<>0,SUMIF(PROFIL!C6:C12,"CESSION",PROFIL!J6:J12),"")
C41: CESSION - TJM Client (€) | D41: =IFERROR(D40/D39,"")
C42: CESSION - CJM Production (€) | D42: =IF(SUMIF(PROFIL!C3:C10,"CESSION",PROFIL!J3:J10)<>0,SUMIF(PROFIL!C3:C10,"CESSION",PROFIL!K3:K10)/(SUMIF(PROFIL!C3:C10,"CESSION",PROFIL!I3:I10)),"")
C43: CESSION - Marge Exakis Nelite (%) | D43: =IF(SUMIF(PROFIL!C3:C10,"CESSION",PROFIL!J3:J10)<>0,(SUMIF(PROFIL!C3:C10,"CESSION",PROFIL!J3:J10)-SUMIF(PROFIL!C3:C10,"CESSION",PROFIL!K3:K10))/(SUMIF(PROFIL!C3:C10,"CESSION",PROFIL!J3:J10)),"")
C44: CESSION - Taux de Cession Interne | D44: =IF(SUMIF(PROFIL!C6:C12,"CESSION",PROFIL!J6:J12)<>0,SUMIF(PROFIL!C6:C12,"CESSION",PROFIL!L6:L12)/(SUMIF(PROFIL!C6:C12,"CESSION",PROFIL!I6:I12)),"")
C45: CESSION - Marge AGENCE (%) | D45: =IF(SUMIF(PROFIL!C6:C12,"CESSION",PROFIL!J6:J12)<>0,(SUMIF(PROFIL!C6:C12,"CESSION",PROFIL!J6:J12)-SUMIF(PROFIL!C6:C12,"CESSION",PROFIL!L6:L12))/(SUMIF(PROFIL!C6:C12,"CESSION",PROFIL!J6:J12)),"")
C47: ACHAT - Nombre de jours produit | D47: =IF(SUMIF(PROFIL!C6:C12,"ACHAT",PROFIL!I6:I12)<>0,SUMIF(PROFIL!C6:C12,"ACHAT",PROFIL!I6:I12),"")
C48: ACHAT - Jours valorisés (€) | D48: =IF(SUMIF(PROFIL!C6:C12,"ACHAT",PROFIL!J6:J12)<>0,SUMIF(PROFIL!C6:C12,"ACHAT",PROFIL!J6:J12),"")
C49: ACHAT - TJM Client (€) | D49: =IFERROR(D48/D47,"")
C50: ACHAT - Coût d'achat Moyen / j (€) | D50: =IF(SUMIF(PROFIL!C6:C12,"ACHAT",PROFIL!J6:J12)<>0,SUMIF(PROFIL!C6:C12,"ACHAT",PROFIL!L6:L12)/(SUMIF(PROFIL!C6:C12,"ACHAT",PROFIL!I6:I12)),"")
C51: ACHAT - Marge AGENCE (%) | D51: =IF(SUMIF(PROFIL!C6:C12,"ACHAT",PROFIL!J6:J12)<>0,(SUMIF(PROFIL!C6:C12,"ACHAT",PROFIL!J6:J12)-SUMIF(PROFIL!C6:C12,"ACHAT",PROFIL!K6:K12))/(SUMIF(PROFIL!C6:C12,"ACHAT",PROFIL!J6:J12)),"")
C53: BO - Nombre de jours produit (jh) | D53: =IF(SUMIF(PROFIL!C6:C12,"BO",PROFIL!I6:I12)<>0,SUMIF(PROFIL!C6:C12,"BO",PROFIL!I6:I12),"")
C54: BO - Jours valorisés (€) | D54: =IF(SUMIF(PROFIL!C6:C12,"BO",PROFIL!J6:J12)<>0,SUMIF(PROFIL!C6:C12,"BO",PROFIL!J6:J12),"")
C55: BO - TJM Client (€) | D55: =IFERROR(D54/D53,"")
C56: BO - CJM Production (€) | D56: =IF(SUMIF(PROFIL!C6:C12,"BO",PROFIL!J6:J12)<>0,SUMIF(PROFIL!C6:C12,"BO",PROFIL!K6:K12)/(SUMIF(PROFIL!C6:C12,"BO",PROFIL!I6:I12)),"")
C57: BO - Marge Exakis Nelite (%) | D57: =IF(SUMIF(PROFIL!C6:C12,"BO",PROFIL!J6:J12)<>0,(SUMIF(PROFIL!C6:C12,"BO",PROFIL!J6:J12)-SUMIF(PROFIL!C6:C12,"BO",PROFIL!K6:K12))/(SUMIF(PROFIL!C6:C12,"BO",PROFIL!J6:J12)),"")
C58: ACHAT BO - Nombre de jours produit | D58: =IF(SUMIF(PROFIL!C6:C12,"ACHAT BO",PROFIL!I6:I12)<>0,SUMIF(PROFIL!C6:C12,"ACHAT BO",PROFIL!I6:I12),"")
C59: ACHAT BO - Jours valorisés (€) | D59: =IF(SUMIF(PROFIL!C6:C12,"ACHAT BO",PROFIL!J6:J12)<>0,SUMIF(PROFIL!C6:C12,"ACHAT BO",PROFIL!J6:J12),"")
C60: ACHAT BO - TJM Client (€) | D60: =IFERROR(D59/D58,"")
C61: ACHAT BO - CJM Production (€) | D61: =IF(SUMIF(PROFIL!C6:C12,"ACHAT BO",PROFIL!J6:J12)<>0,SUMIF(PROFIL!C6:C12,"ACHAT BO",PROFIL!K6:K12)/(SUMIF(PROFIL!C6:C12,"ACHAT BO",PROFIL!I6:I12)),"")
C62: ACHAT BO - Marge Exakis Nelite (%) | D62: =IF(SUMIF(PROFIL!C6:C12,"ACHAT BO",PROFIL!J6:J12)<>0,(SUMIF(PROFIL!C6:C12,"ACHAT BO",PROFIL!J6:J12)-SUMIF(PROFIL!C6:C12,"ACHAT BO",PROFIL!K6:K12))/(SUMIF(PROFIL!C6:C12,"ACHAT BO",PROFIL!J6:J12)),"")
C63: TOTAL BO - Nombre de jours produit | D63: =IF(OR(SUMIF(PROFIL!C6:C12,"BO",PROFIL!I6:I12)<>0, SUMIF(PROFIL!C6:C12,"ACHAT BO",PROFIL!I6:I12)<>0), SUMIF(PROFIL!C6:C12,"BO",PROFIL!I6:I12)+SUMIF(PROFIL!C6:C12,"ACHAT BO",PROFIL!I6:I12),"")
C64: TOTAL BO - Jours valorisés (€) | D64: =IF(OR(SUMIF(PROFIL!C6:C12,"BO",PROFIL!J6:J12)<>0,SUMIF(PROFIL!C6:C12,"ACHAT BO",PROFIL!J6:J12)<>0 ),SUMIF(PROFIL!C6:C12,"BO",PROFIL!J6:J12)+SUMIF(PROFIL!C6:C12,"ACHAT BO",PROFIL!J6:J12),"")
C65: TOTAL BO - TJM Client (€) | D65: =IFERROR(D64/D63,"")
C66: TOTAL BO - CJM Production (€) | D66: =IF(SUMIF(PROFIL!C6:C12,"BO",PROFIL!J6:J12)+SUMIF(PROFIL!C6:C12,"ACHAT BO",PROFIL!J6:J12)<>0,(SUMIF(PROFIL!C6:C12,"BO",PROFIL!K6:K12)+SUMIF(PROFIL!C6:C12,"ACHAT BO",PROFIL!K6:K12))/(SUMIF(PROFIL!C6:C12,"BO",PROFIL!I6:I12)+SUMIF(PROFIL!C6:C12,"ACHAT BO",PROFIL!I6:I12)),"")
C67: TOTAL BO - Marge Exakis Nelite (%) | D67: =IF(SUMIF(PROFIL!C6:C12,"BO",PROFIL!J6:J12)+SUMIF(PROFIL!C6:C12,"ACHAT BO",PROFIL!J6:J12)<>0,(SUMIF(PROFIL!C6:C12,"BO",PROFIL!J6:J12)+SUMIF(PROFIL!C6:C12,"ACHAT BO",PROFIL!J6:J12)-SUMIF(PROFIL!C6:C12,"BO",PROFIL!K6:K12)-SUMIF(PROFIL!C6:C12,"ACHAT BO",PROFIL!K6:K12))/(SUMIF(PROFIL!C6:C12,"BO",PROFIL!J6:J12)+SUMIF(PROFIL!C6:C12,"ACHAT BO",PROFIL!J6:J12)),"")
C68: PRCS Moyen du BACK | D68: =IF((SUMIF(PROFIL!C6:C12,"BO",PROFIL!I6:I12)+SUMIF(PROFIL!C6:C12,"ACHAT BO",PROFIL!I6:I12))<>0,(SUMIF(PROFIL!C6:C12,"BO",PROFIL!L6:L12)+SUMIF(PROFIL!C6:C12,"ACHAT BO",PROFIL!L6:L12))/(SUMIF(PROFIL!C6:C12,"BO",PROFIL!I6:I12)+SUMIF(PROFIL!C6:C12,"ACHAT BO",PROFIL!I6:I12)),"")
C69: Marge FRONT / BACK | D69: =IF(D65<>"",(D65-D68)/D65,"")

Sheet PROFIL
B1: Profil
A5: TJM remisés | B5: PROFIL | C5: Entité | D5: TJM | E5: CJM | F5: PRCS | G5: Frais Déplacement (si Cession) | H5: TCI / PRCS | I5: Charge | J5: CA (€) | K5: COUT Exakis Nelite (€) | L5: COUT AGENCE (€) | M5: %jh PROFIL | N5: %€ PROFIL | O5: Marge /Profil Exakis Nelite | P5: Marge /Profil AGENCE
A6: =IF(AND(D6<>"",$J$15<>""),D6*(1-$J$15),"") | B6: Chef de Projet | C6: FO | D6: 750 | E6: 400 | F6: =IF(OR( C6="BO",C6="ACHAT BO"), 450,"") | H6: =IFERROR(IF(C6="CESSION",(((D6-E6)/2)+E6)+((G6/2)/I6),IF(C6="ACHAT",E6,IF(OR( C6="BO",C6="ACHAT BO"), F6+G6/I6,""))),"") | I6: =WORKLOAD!H96 -> 21.5 | J6: =I6*D6*(1-$J$15) -> 16125 | K6: =E6*I6 -> 8600 | L6: =IFERROR(IF(C6="FO",E6*I6,H6*I6),0) -> 8600 | M6: =IF(I6<>0,I6/$I$13,"") -> 0.20673077 | N6: =IF(J6<>0,J6/$J$13,"") -> 0.20826606 | O6: =IF(J6<>0,(J6-K6)/J6,"") -> 0.46666667 | P6: =IF(J6<>0,(J6-L6)/J6,"") -> 0.46666667 | Q6: ETT
A7: =IF(AND(D7<>"",$J$15<>""),D7*(1-$J$15),"") | B7: Architecte | C7: FO | D7: 850 | E7: 420 | F7: =IF(OR( C7="BO",C7="ACHAT BO"), 450,"") | H7: =IFERROR(IF(C7="CESSION",(((D7-E7)/2)+E7)+((G7/2)/I7),IF(C7="ACHAT",E7,IF(OR( C7="BO",C7="ACHAT BO"), F7+G7/I7,""))),"") | I7: =WORKLOAD!I96 -> 10.5 | J7: =I7*D7*(1-$J$15) -> 8925 | K7: =E7*I7 -> 4410 | L7: =IFERROR(IF(C7="FO",E7*I7,H7*I7),0) -> 4410 | M7: =IF(I7<>0,I7/$I$13,"") -> 0.10096154 | N7: =IF(J7<>0,J7/$J$13,"") -> 0.11527284 | O7: =IF(J7<>0,(J7-K7)/J7,"") -> 0.50588235 | P7: =IF(J7<>0,(J7-L7)/J7,"") -> 0.50588235 | Q7: ???
A8: =IF(AND(D8<>"",$J$15<>""),D8*(1-$J$15),"") | B8: Consultant Technique | C8: FO | D8: 750 | E8: 380 | F8: =IF(OR( C8="BO",C8="ACHAT BO"), 450,"") | H8: =IFERROR(IF(C8="CESSION",(((D8-E8)/2)+E8)+((G8/2)/I8),IF(C8="ACHAT",E8,IF(OR( C8="BO",C8="ACHAT BO"), F8+G8/I8,""))),"") | I8: =WORKLOAD!J96 -> 29.5 | J8: =I8*D8*(1-$J$15) -> 22125 | K8: =E8*I8 -> 11210 | L8: =IFERROR(IF(C8="FO",E8*I8,H8*I8),0) -> 11210 | M8: =IF(I8<>0,I8/$I$13,"") -> 0.28365385 | N8: =IF(J8<>0,J8/$J$13,"") -> 0.28576041 | O8: =IF(J8<>0,(J8-K8)/J8,"") -> 0.49333333 | P8: =IF(J8<>0,(J8-L8)/J8,"") -> 0.49333333 | Q8: ??? / ADY (PlanB)
A9: =IF(AND(D9<>"",$J$15<>""),D9*(1-$J$15),"") | B9: Consultant Change | C9: FO | D9: 700 | E9: 320 | F9: =IF(OR( C9="BO",C9="ACHAT BO"), 450,"") | H9: =IFERROR(IF(C9="CESSION",(((D9-E9)/2)+E9)+((G9/2)/I9),IF(C9="ACHAT",E9,IF(OR( C9="BO",C9="ACHAT BO"), F9+G9/I9,""))),"") | I9: =WORKLOAD!K96 -> 37.5 | J9: =I9*D9*(1-$J$15) -> 26250 | K9: =E9*I9 -> 12000 | L9: =IFERROR(IF(C9="FO",E9*I9,H9*I9),0) -> 12000 | M9: =IF(I9<>0,I9/$I$13,"") -> 0.36057692 | N9: =IF(J9<>0,J9/$J$13,"") -> 0.33903778 | O9: =IF(J9<>0,(J9-K9)/J9,"") -> 0.54285714 | P9: =IF(J9<>0,(J9-L9)/J9,"") -> 0.54285714 | Q9: ETN
A10: =IF(AND(D10<>"",$J$15<>""),D10*(1-$J$15),"") | B10: Consultant Data | C10: FO | D10: 800 | E10: 380 | F10: =IF(OR( C10="BO",C10="ACHAT BO"), 450,"") | H10: =IFERROR(IF(C10="CESSION",(((D10-E10)/2)+E10)+((G10/2)/I10),IF(C10="ACHAT",E10,IF(OR( C10="BO",C10="ACHAT BO"), F10+G10/I10,""))),"") | I10: =WORKLOAD!L96 -> 5 | J10: =I10*D10*(1-$J$15) -> 4000 | K10: =E10*I10 -> 1900 | L10: =IFERROR(IF(C10="FO",E10*I10,H10*I10),0) -> 1900 | M10: =IF(I10<>0,I10/$I$13,"") -> 0.048076923 | N10: =IF(J10<>0,J10/$J$13,"") -> 0.0516629 | O10: =IF(J10<>0,(J10-K10)/J10,"") -> 0.525 | P10: =IF(J10<>0,(J10-L10)/J10,"") -> 0.525
A11: =IF(AND(D11<>"",$J$15<>""),D11*(1-$J$15),"") | F11: =IF(OR( C11="BO",C11="ACHAT BO"), 450,"") | H11: =IFERROR(IF(C11="CESSION",(((D11-E11)/2)+E11)+((G11/2)/I11),IF(C11="ACHAT",E11,IF(OR( C11="BO",C11="ACHAT BO"), F11+G11/I11,""))),"") | I11: =WORKLOAD!M96 -> 0 | J11: =I11*D11*(1-$J$15) -> 0 | K11: =E11*I11 -> 0 | L11: =IFERROR(IF(C11="FO",E11*I11,H11*I11),0) -> 0 | M11: =IF(I11<>0,I11/$I$13,"") | N11: =IF(J11<>0,J11/$J$13,"") | O11: =IF(J11<>0,(J11-K11)/J11,"") | P11: =IF(J11<>0,(J11-L11)/J11,"")
A12: =IF(AND(D12<>"",$J$15<>""),D12*(1-$J$15),"") | F12: =IF(OR( C12="BO",C12="ACHAT BO"), 450,"") | H12: =IFERROR(IF(C12="CESSION",(((D12-E12)/2)+E12)+((G12/2)/I12),IF(C12="ACHAT",E12,IF(OR( C12="BO",C12="ACHAT BO"), F12+G12/I12,""))),"") | I12: =WORKLOAD!N96 -> 0 | J12: =I12*D12*(1-$J$15) -> 0 | K12: =E12*I12 -> 0 | L12: =IFERROR(IF(C12="FO",E12*I12,H12*I12),0) -> 0 | M12: =IF(I12<>0,I12/$I$13,"") | N12: =IF(J12<>0,J12/$J$13,"") | O12: =IF(J12<>0,(J12-K12)/J12,"") | P12: =IF(J12<>0,(J12-L12)/J12,"")
B13: TOTAL | I13: =SUBTOTAL(9,I6:I12) -> 104 | J13: =SUBTOTAL(9,J6:J12) -> 77425 | K13: =SUBTOTAL(9,K6:K12) -> 38120 | L13: =SUBTOTAL(9,L6:L12) -> 38120 | O13: =IF(J13<>0,(J13-K13)/J13,"") -> 0.50765257 | P13: =IF(J13<>0,(J13-L13)/J13,"") -> 0.50765257
I14: CA initial
B15: Agences : TJM pour 40% de marge Exakis Nelite | I15: Remise
B16: Profils | D16: TJM Paris | E16: CJM Paris | F16: TJM Région | G16: CJM Région
B17: Consultant Junior | D17: 500 | E17: 300 | F17: 418.33333 | G17: 251
B18: Consultant | C18: 359 | D18: 575 | E18: 345 | F18: 458.33333 | G18: 275
B19: Consultant confirmé | C19: 359 | D19: 708.33333 | E19: 425 | F19: 558.33333 | G19: 335
B20: Expert | C20: 481 | D20: 733.33333 | E20: 440 | F20: 633.33333 | G20: 380
B21: Expert senior | C21: 359 | D21: 833.33333 | E21: 500 | F21: 733.33333 | G21: 440
B22: Architecte | D22: 816.66667 | E22: 490 | F22: 658.33333 | G22: 395
B23: Architecte Senior | C23: 481 | D23: 916.66667 | E23: 550 | F23: 766.66667 | G23: 460
B24: Chef de Projet | C24: 481 | D24: 733.33333 | E24: 440 | F24: 616.66667 | G24: 370
B25: Chef de Projet Senior | D25: 808.33333 | E25: 485 | F25: 683.33333 | G25: 410
B26: Directeur de projet | C26: 290 | D26: 966.66667 | E26: 580 | F26: 833.33333 | G26: 500
B27: Consultant Fonctionnel | C27: 359 | D27: 583.33333 | E27: 350 | F27: 491.66667 | G27: 295
B28: Consultant Fonctionnel Senior | D28: 650 | E28: 390 | F28: 575 | G28: 345
B29: Expert Fonctionnel | D29: 775 | E29: 465 | F29: 683.33333 | G29: 410
B30: Référent | D30: 1066.6667 | E30: 640 | F30: 766.66667 | G30: 460
B31: Manager | C31: 290 | D31: 1033.3333 | E31: 620 | F31: 816.66667 | G31: 490
B33: Rappel cf supra dans le Tableau PRCS à 450 €

Sheet ACHAT
A1: Achat
A4: Achat Matériel / Logiciel | B4: Type d'achat | C4: Coût unitaire | D4: Qté | E4: Montant HT | G4: Montant Revente | H4: Markup (%) | I4: Commentaire
E5: =IF(C5>0,C5*D5,"") | H5: =IFERROR((G5-E5)/G5,"")
E6: =IF(C6>0,C6*D6,"") | H6: =IFERROR((G6-E6)/G6,"")
E7: =IF(C7>0,C7*D7,"") | H7: =IFERROR((G7-E7)/G7,"")
E8: =IF(C8>0,C8*D8,"") | H8: =IFERROR((G8-E8)/G8,"")
E9: =IF(C9>0,C9*D9,"") | H9: =IFERROR((G9-E9)/G9,"")
E10: =IF(C10>0,C10*D10,"") | H10: =IFERROR((G10-E10)/G10,"")
E11: =IF(C11>0,C11*D11,"") | H11: =IFERROR((G11-E11)/G11,"")
E12: =IF(C12>0,C12*D12,"") | H12: =IFERROR((G12-E12)/G12,"")
E13: =IF(C13>0,C13*D13,"") | H13: =IFERROR((G13-E13)/G13,"")
E14: =IF(C14>0,C14*D14,"") | H14: =IFERROR((G14-E14)/G14,"")
E15: =IF(C15>0,C15*D15,"") | H15: =IFERROR((G15-E15)/G15,"")
E16: =IF(C16>0,C16*D16,"") | H16: =IFERROR((G16-E16)/G16,"")
A17: TOTAL | E17: =SUM(E5:E16) -> 0 | G17: =SUM(G5:G16) -> 0 | H17: =IFERROR((G17-E17)/G17,"")
A20: Achat Prestataires externes | B20: Société | C20: Coût jour | D20: Nbj | E20: Total Coût | F20: TJM | G20: Montant Revente | H20: Markup (%) | I20: Commentaire
E21: =IF(C21>0,C21*D21,"") | G21: =IF(F21>0,D21*F21,"") | H21: =IFERROR((G21-E21)/G21,"")
E22: =IF(C22>0,C22*D22,"") | G22: =IF(F22>0,D22*F22,"") | H22: =IFERROR((G22-E22)/G22,"")
E23: =IF(C23>0,C23*D23,"") | G23: =IF(F23>0,D23*F23,"") | H23: =IFERROR((G23-E23)/G23,"")
E24: =IF(C24>0,C24*D24,"") | G24: =IF(F24>0,D24*F24,"") | H24: =IFERROR((G24-E24)/G24,"")
E25: =IF(C25>0,C25*D25,"") | G25: =IF(F25>0,D25*F25,"") | H25: =IFERROR((G25-E25)/G25,"")
E26: =IF(C26>0,C26*D26,"") | G26: =IF(F26>0,D26*F26,"") | H26: =IFERROR((G26-E26)/G26,"")
E27: =IF(C27>0,C27*D27,"") | G27: =IF(F27>0,D27*F27,"") | H27: =IFERROR((G27-E27)/G27,"")
E28: =IF(C28>0,C28*D28,"") | G28: =IF(F28>0,D28*F28,"") | H28: =IFERROR((G28-E28)/G28,"")
E29: =IF(C29>0,C29*D29,"") | G29: =IF(F29>0,D29*F29,"") | H29: =IFERROR((G29-E29)/G29,"")
E30: =IF(C30>0,C30*D30,"") | G30: =IF(F30>0,D30*F30,"") | H30: =IFERROR((G30-E30)/G30,"")
E31: =IF(C31>0,C31*D31,"") | G31: =IF(F31>0,D31*F31,"") | H31: =IFERROR((G31-E31)/G31,"")
E32: =IF(C32>0,C32*D32,"") | G32: =IF(F32>0,D32*F32,"") | H32: =IFERROR((G32-E32)/G32,"")
A33: TOTAL | C33: =IFERROR(E33/D33,"") | D33: =SUM(D21:D32) -> 0 | E33: =SUM(E21:E32) -> 0 | F33: =IFERROR(G33/D33,"") | G33: =SUM(G21:G32) -> 0 | H33: =IFERROR((G33-E33)/G33,"")

Sheet FRAIS
A1: Frais
A4: Libellé Frais | B4: Coût unitaire | C4: Qté | D4: Montant | E4: Montant Refacturé | F4: Commentaire
A5: Lot 1 : Déploiement Sites Majeurs | B5: 500 | C5: 15 | D5: =IF(C5>0,B5*C5,"") -> 7500 | E5: 7500
A6: Lot 2: Déploiement Sites Secondaires | B6: 500 | C6: 20 | D6: =IF(C6>0,B6*C6,"") -> 10000 | E6: 10000
D7: =IF(C7>0,B7*C7,"")
D8: =IF(C8>0,B8*C8,"")
D9: =IF(C9>0,B9*C9,"")
D10: =IF(C10>0,B10*C10,"")
D11: =IF(C11>0,B11*C11,"")
D12: =IF(C12>0,B12*C12,"")
D13: =IF(C13>0,B13*C13,"")
D14: =IF(C14>0,B14*C14,"")
D15: =IF(C15>0,B15*C15,"")
D16: =IF(C16>0,B16*C16,"")
A17: TOTAL | D17: =SUM(D5:D16) -> 17500 | E17: =SUM(E5:E16) -> 17500

Sheet WORKLOAD
C1: Workload | G1: % pilotage projet | H1: =(H3*100)/F3 -> 20.673077 | I1: % provision | J1: =((F60+F61+F62+F63)/F3)*100 -> 3.8461538
E3: SOUS TOTAL | F3: =SUBTOTAL(9,F5:F95) -> 104 | G3: =SUBTOTAL(9,G5:G95) -> 77425 | H3: =SUBTOTAL(9,H5:H95) -> 21.5 | I3: =SUBTOTAL(9,I5:I95) -> 10.5 | J3: =SUBTOTAL(9,J5:J95) -> 29.5 | K3: =SUBTOTAL(9,K5:K95) -> 37.5 | L3: =SUBTOTAL(9,L5:L95) -> 5 | M3: =SUBTOTAL(9,M5:M95) -> 0 | N3: =SUBTOTAL(9,N5:N95) -> 0 | O3: Cout par profil
A4: ID | B4: Lot | C4: Phase | D4: Etape | E4: Tâche | F4: TOTAL Charge | G4: TOTAL Valorisation | H4: =PROFIL!B6 -> Chef de Projet | I4: =PROFIL!B7 -> Architecte | J4: =PROFIL!B8 -> Consultant Technique | K4: =PROFIL!B9 -> Consultant Change | L4: =PROFIL!B10 -> Consultant Data | M4: =PROFIL!B11 -> 0 | N4: =PROFIL!B12 -> 0 | O4: =PROFIL!B6 -> Chef de Projet | P4: =PROFIL!B7 -> Architecte | Q4: =PROFIL!B8 -> Consultant Technique | R4: =PROFIL!B9 -> Consultant Change | S4: =PROFIL!B10 -> Consultant Data | T4: =PROFIL!B11 -> 0 | U4: =PROFIL!B12 -> 0 | V4: Livrable | W4: Hypothèses/Commentaire
A5: 1 | B5: Gouvernance | C5: PILOTAGE | D5: Pilotage projet | E5: Kick-off projet et cadrage initial | F5: =IF((H5+I5+J5+K5+L5+M5+N5)=0,"-",(H5+I5+J5+K5+L5+M5+N5)) -> 1.5 | G5: =IF((O5+P5+Q5+R5+S5+T5+U5)=0,"-",(O5+P5+Q5+R5+S5+T5+U5)) -> 1175 | H5: 1 | I5: 0.5 | O5: =H5*(IF(PROFIL!$J$15<>"",PROFIL!$D$6*(1-PROFIL!$J$15),PROFIL!$D$6)) -> 750 | P5: =I5*(IF(PROFIL!$J$15<>"",PROFIL!$D$7*(1-PROFIL!$J$15),PROFIL!$D$7)) -> 425 | Q5: =J5*(IF(PROFIL!$J$15<>"",PROFIL!$D$8*(1-PROFIL!$J$15),PROFIL!$D$8)) -> 0 | R5: =K5*(IF(PROFIL!$J$15<>"",PROFIL!$D$9*(1-PROFIL!$J$15),PROFIL!$D$9)) -> 0 | S5: =L5*(IF(PROFIL!$J$15<>"",PROFIL!$D$10*(1-PROFIL!$J$15),PROFIL!$D$10)) -> 0 | T5: =M5*(IF(PROFIL!$J$15<>"",PROFIL!$D$11*(1-PROFIL!$J$15),PROFIL!$D$11)) -> 0 | U5: =N5*(IF(PROFIL!$J$15<>"",PROFIL!$D$12*(1-PROFIL!$J$15),PROFIL!$D$12)) -> 0 | V5: oui | W5: Réunion de lancement formelle
F6: =IF((H6+I6+J6+K6+L6+M6+N6)=0,"-",(H6+I6+J6+K6+L6+M6+N6)) -> - | G6: =IF((O6+P6+Q6+R6+S6+T6+U6)=0,"-",(O6+P6+Q6+R6+S6+T6+U6)) -> - | O6: =H6*(IF(PROFIL!$J$15<>"",PROFIL!$D$6*(1-PROFIL!$J$15),PROFIL!$D$6)) -> 0 | P6: =I6*(IF(PROFIL!$J$15<>"",PROFIL!$D$7*(1-PROFIL!$J$15),PROFIL!$D$7)) -> 0 | Q6: =J6*(IF(PROFIL!$J$15<>"",PROFIL!$D$8*(1-PROFIL!$J$15),PROFIL!$D$8)) -> 0 | R6: =K6*(IF(PROFIL!$J$15<>"",PROFIL!$D$9*(1-PROFIL!$J$15),PROFIL!$D$9)) -> 0 | S6: =L6*(IF(PROFIL!$J$15<>"",PROFIL!$D$10*(1-PROFIL!$J$15),PROFIL!$D$10)) -> 0 | T6: =M6*(IF(PROFIL!$J$15<>"",PROFIL!$D$11*(1-PROFIL!$J$15),PROFIL!$D$11)) -> 0 | U6: =N6*(IF(PROFIL!$J$15<>"",PROFIL!$D$12*(1-PROFIL!$J$15),PROFIL!$D$12)) -> 0
A7: 1 | B7: Gouvernance | C7: PILOTAGE | D7: Pilotage projet | E7: Suivi hebdomadaire projet | F7: =IF((H7+I7+J7+K7+L7+M7+N7)=0,"-",(H7+I7+J7+K7+L7+M7+N7)) -> 2 | G7: =IF((O7+P7+Q7+R7+S7+T7+U7)=0,"-",(O7+P7+Q7+R7+S7+T7+U7)) -> 1500 | H7: 2 | O7: =H7*(IF(PROFIL!$J$15<>"",PROFIL!$D$6*(1-PROFIL!$J$15),PROFIL!$D$6)) -> 1500 | P7: =I7*(IF(PROFIL!$J$15<>"",PROFIL!$D$7*(1-PROFIL!$J$15),PROFIL!$D$7)) -> 0 | Q7: =J7*(IF(PROFIL!$J$15<>"",PROFIL!$D$8*(1-PROFIL!$J$15),PROFIL!$D$8)) -> 0 | R7: =K7*(IF(PROFIL!$J$15<>"",PROFIL!$D$9*(1-PROFIL!$J$15),PROFIL!$D$9)) -> 0 | S7: =L7*(IF(PROFIL!$J$15<>"",PROFIL!$D$10*(1-PROFIL!$J$15),PROFIL!$D$10)) -> 0 | T7: =M7*(IF(PROFIL!$J$15<>"",PROFIL!$D$11*(1-PROFIL!$J$15),PROFIL!$D$11)) -> 0 | U7: =N7*(IF(PROFIL!$J$15<>"",PROFIL!$D$12*(1-PROFIL!$J$15),PROFIL!$D$12)) -> 0 | V7: non | W7: COMOP
A8: 1 | B8: Gouvernance | C8: PILOTAGE | D8: Pilotage projet | E8: COPIL mensuels et reporting | F8: =IF((H8+I8+J8+K8+L8+M8+N8)=0,"-",(H8+I8+J8+K8+L8+M8+N8)) -> 3 | G8: =IF((O8+P8+Q8+R8+S8+T8+U8)=0,"-",(O8+P8+Q8+R8+S8+T8+U8)) -> 2200 | H8: 2 | K8: 1 | O8: =H8*(IF(PROFIL!$J$15<>"",PROFIL!$D$6*(1-PROFIL!$J$15),PROFIL!$D$6)) -> 1500 | P8: =I8*(IF(PROFIL!$J$15<>"",PROFIL!$D$7*(1-PROFIL!$J$15),PROFIL!$D$7)) -> 0 | Q8: =J8*(IF(PROFIL!$J$15<>"",PROFIL!$D$8*(1-PROFIL!$J$15),PROFIL!$D$8)) -> 0 | R8: =K8*(IF(PROFIL!$J$15<>"",PROFIL!$D$9*(1-PROFIL!$J$15),PROFIL!$D$9)) -> 700 | S8: =L8*(IF(PROFIL!$J$15<>"",PROFIL!$D$10*(1-PROFIL!$J$15),PROFIL!$D$10)) -> 0 | T8: =M8*(IF(PROFIL!$J$15<>"",PROFIL!$D$11*(1-PROFIL!$J$15),PROFIL!$D$11)) -> 0 | U8: =N8*(IF(PROFIL!$J$15<>"",PROFIL!$D$12*(1-PROFIL!$J$15),PROFIL!$D$12)) -> 0 | V8: non | W8: Pilotage décisionnel
F9: =IF((H9+I9+J9+K9+L9+M9+N9)=0,"-",(H9+I9+J9+K9+L9+M9+N9)) -> - | G9: =IF((O9+P9+Q9+R9+S9+T9+U9)=0,"-",(O9+P9+Q9+R9+S9+T9+U9)) -> - | O9: =H9*(IF(PROFIL!$J$15<>"",PROFIL!$D$6*(1-PROFIL!$J$15),PROFIL!$D$6)) -> 0 | P9: =I9*(IF(PROFIL!$J$15<>"",PROFIL!$D$7*(1-PROFIL!$J$15),PROFIL!$D$7)) -> 0 | Q9: =J9*(IF(PROFIL!$J$15<>"",PROFIL!$D$8*(1-PROFIL!$J$15),PROFIL!$D$8)) -> 0 | R9: =K9*(IF(PROFIL!$J$15<>"",PROFIL!$D$9*(1-PROFIL!$J$15),PROFIL!$D$9)) -> 0 | S9: =L9*(IF(PROFIL!$J$15<>"",PROFIL!$D$10*(1-PROFIL!$J$15),PROFIL!$D$10)) -> 0 | T9: =M9*(IF(PROFIL!$J$15<>"",PROFIL!$D$11*(1-PROFIL!$J$15),PROFIL!$D$11)) -> 0 | U9: =N9*(IF(PROFIL!$J$15<>"",PROFIL!$D$12*(1-PROFIL!$J$15),PROFIL!$D$12)) -> 0
A10: 2 | B10: Tech | C10: PILOTAGE | D10: Pilotage projet | E10: Pilotage Tech | F10: =IF((H10+I10+J10+K10+L10+M10+N10)=0,"-",(H10+I10+J10+K10+L10+M10+N10)) -> 2 | G10: =IF((O10+P10+Q10+R10+S10+T10+U10)=0,"-",(O10+P10+Q10+R10+S10+T10+U10)) -> 1500 | H10: 2 | O10: =H10*(IF(PROFIL!$J$15<>"",PROFIL!$D$6*(1-PROFIL!$J$15),PROFIL!$D$6)) -> 1500 | P10: =I10*(IF(PROFIL!$J$15<>"",PROFIL!$D$7*(1-PROFIL!$J$15),PROFIL!$D$7)) -> 0 | Q10: =J10*(IF(PROFIL!$J$15<>"",PROFIL!$D$8*(1-PROFIL!$J$15),PROFIL!$D$8)) -> 0 | R10: =K10*(IF(PROFIL!$J$15<>"",PROFIL!$D$9*(1-PROFIL!$J$15),PROFIL!$D$9)) -> 0 | S10: =L10*(IF(PROFIL!$J$15<>"",PROFIL!$D$10*(1-PROFIL!$J$15),PROFIL!$D$10)) -> 0 | T10: =M10*(IF(PROFIL!$J$15<>"",PROFIL!$D$11*(1-PROFIL!$J$15),PROFIL!$D$11)) -> 0 | U10: =N10*(IF(PROFIL!$J$15<>"",PROFIL!$D$12*(1-PROFIL!$J$15),PROFIL!$D$12)) -> 0
A11: 2 | B11: Tech | C11: CONCEPTION | D11: Analyse de l’existant | E11: Analyse tenant Entra ID | F11: =IF((H11+I11+J11+K11+L11+M11+N11)=0,"-",(H11+I11+J11+K11+L11+M11+N11)) -> 1 | G11: =IF((O11+P11+Q11+R11+S11+T11+U11)=0,"-",(O11+P11+Q11+R11+S11+T11+U11)) -> 850 | I11: 1 | O11: =H11*(IF(PROFIL!$J$15<>"",PROFIL!$D$6*(1-PROFIL!$J$15),PROFIL!$D$6)) -> 0 | P11: =I11*(IF(PROFIL!$J$15<>"",PROFIL!$D$7*(1-PROFIL!$J$15),PROFIL!$D$7)) -> 850 | Q11: =J11*(IF(PROFIL!$J$15<>"",PROFIL!$D$8*(1-PROFIL!$J$15),PROFIL!$D$8)) -> 0 | R11: =K11*(IF(PROFIL!$J$15<>"",PROFIL!$D$9*(1-PROFIL!$J$15),PROFIL!$D$9)) -> 0 | S11: =L11*(IF(PROFIL!$J$15<>"",PROFIL!$D$10*(1-PROFIL!$J$15),PROFIL!$D$10)) -> 0 | T11: =M11*(IF(PROFIL!$J$15<>"",PROFIL!$D$11*(1-PROFIL!$J$15),PROFIL!$D$11)) -> 0 | U11: =N11*(IF(PROFIL!$J$15<>"",PROFIL!$D$12*(1-PROFIL!$J$15),PROFIL!$D$12)) -> 0 | V11: oui | W11: Contraintes existantes
A12: 2 | B12: Tech | C12: CONCEPTION | D12: Analyse de l’existant | E12: Analyse Intune / WHfB existant | F12: =IF((H12+I12+J12+K12+L12+M12+N12)=0,"-",(H12+I12+J12+K12+L12+M12+N12)) -> 1 | G12: =IF((O12+P12+Q12+R12+S12+T12+U12)=0,"-",(O12+P12+Q12+R12+S12+T12+U12)) -> 850 | I12: 1 | O12: =H12*(IF(PROFIL!$J$15<>"",PROFIL!$D$6*(1-PROFIL!$J$15),PROFIL!$D$6)) -> 0 | P12: =I12*(IF(PROFIL!$J$15<>"",PROFIL!$D$7*(1-PROFIL!$J$15),PROFIL!$D$7)) -> 850 | Q12: =J12*(IF(PROFIL!$J$15<>"",PROFIL!$D$8*(1-PROFIL!$J$15),PROFIL!$D$8)) -> 0 | R12: =K12*(IF(PROFIL!$J$15<>"",PROFIL!$D$9*(1-PROFIL!$J$15),PROFIL!$D$9)) -> 0 | S12: =L12*(IF(PROFIL!$J$15<>"",PROFIL!$D$10*(1-PROFIL!$J$15),PROFIL!$D$10)) -> 0 | T12: =M12*(IF(PROFIL!$J$15<>"",PROFIL!$D$11*(1-PROFIL!$J$15),PROFIL!$D$11)) -> 0 | U12: =N12*(IF(PROFIL!$J$15<>"",PROFIL!$D$12*(1-PROFIL!$J$15),PROFIL!$D$12)) -> 0 | V12: oui | W12: Basé POC
A13: 2 | B13: Tech | C13: CONCEPTION | D13: Analyse de l’existant | E13: Analyse VPN F5 & PingAM | F13: =IF((H13+I13+J13+K13+L13+M13+N13)=0,"-",(H13+I13+J13+K13+L13+M13+N13)) -> 1 | G13: =IF((O13+P13+Q13+R13+S13+T13+U13)=0,"-",(O13+P13+Q13+R13+S13+T13+U13)) -> 850 | I13: 1 | O13: =H13*(IF(PROFIL!$J$15<>"",PROFIL!$D$6*(1-PROFIL!$J$15),PROFIL!$D$6)) -> 0 | P13: =I13*(IF(PROFIL!$J$15<>"",PROFIL!$D$7*(1-PROFIL!$J$15),PROFIL!$D$7)) -> 850 | Q13: =J13*(IF(PROFIL!$J$15<>"",PROFIL!$D$8*(1-PROFIL!$J$15),PROFIL!$D$8)) -> 0 | R13: =K13*(IF(PROFIL!$J$15<>"",PROFIL!$D$9*(1-PROFIL!$J$15),PROFIL!$D$9)) -> 0 | S13: =L13*(IF(PROFIL!$J$15<>"",PROFIL!$D$10*(1-PROFIL!$J$15),PROFIL!$D$10)) -> 0 | T13: =M13*(IF(PROFIL!$J$15<>"",PROFIL!$D$11*(1-PROFIL!$J$15),PROFIL!$D$11)) -> 0 | U13: =N13*(IF(PROFIL!$J$15<>"",PROFIL!$D$12*(1-PROFIL!$J$15),PROFIL!$D$12)) -> 0 | V13: oui | W13: Dépendances critiques
A14: 3 | B14: Tech | C14: CONCEPTION | D14: Conception Générale | E14: Définition architecture cible globale | F14: =IF((H14+I14+J14+K14+L14+M14+N14)=0,"-",(H14+I14+J14+K14+L14+M14+N14)) -> - | G14: =IF((O14+P14+Q14+R14+S14+T14+U14)=0,"-",(O14+P14+Q14+R14+S14+T14+U14)) -> - | O14: =H14*(IF(PROFIL!$J$15<>"",PROFIL!$D$6*(1-PROFIL!$J$15),PROFIL!$D$6)) -> 0 | P14: =I14*(IF(PROFIL!$J$15<>"",PROFIL!$D$7*(1-PROFIL!$J$15),PROFIL!$D$7)) -> 0 | Q14: =J14*(IF(PROFIL!$J$15<>"",PROFIL!$D$8*(1-PROFIL!$J$15),PROFIL!$D$8)) -> 0 | R14: =K14*(IF(PROFIL!$J$15<>"",PROFIL!$D$9*(1-PROFIL!$J$15),PROFIL!$D$9)) -> 0 | S14: =L14*(IF(PROFIL!$J$15<>"",PROFIL!$D$10*(1-PROFIL!$J$15),PROFIL!$D$10)) -> 0 | T14: =M14*(IF(PROFIL!$J$15<>"",PROFIL!$D$11*(1-PROFIL!$J$15),PROFIL!$D$11)) -> 0 | U14: =N14*(IF(PROFIL!$J$15<>"",PROFIL!$D$12*(1-PROFIL!$J$15),PROFIL!$D$12)) -> 0 | V14: oui | W14: Implémentation déja réalisée
A15: 3 | B15: Tech | C15: CONCEPTION | D15: Conception Générale | E15: Définition scénarios d’usage | F15: =IF((H15+I15+J15+K15+L15+M15+N15)=0,"-",(H15+I15+J15+K15+L15+M15+N15)) -> 1.5 | G15: =IF((O15+P15+Q15+R15+S15+T15+U15)=0,"-",(O15+P15+Q15+R15+S15+T15+U15)) -> 1225 | I15: 1 | J15: 0.5 | O15: =H15*(IF(PROFIL!$J$15<>"",PROFIL!$D$6*(1-PROFIL!$J$15),PROFIL!$D$6)) -> 0 | P15: =I15*(IF(PROFIL!$J$15<>"",PROFIL!$D$7*(1-PROFIL!$J$15),PROFIL!$D$7)) -> 850 | Q15: =J15*(IF(PROFIL!$J$15<>"",PROFIL!$D$8*(1-PROFIL!$J$15),PROFIL!$D$8)) -> 375 | R15: =K15*(IF(PROFIL!$J$15<>"",PROFIL!$D$9*(1-PROFIL!$J$15),PROFIL!$D$9)) -> 0 | S15: =L15*(IF(PROFIL!$J$15<>"",PROFIL!$D$10*(1-PROFIL!$J$15),PROFIL!$D$10)) -> 0 | T15: =M15*(IF(PROFIL!$J$15<>"",PROFIL!$D$11*(1-PROFIL!$J$15),PROFIL!$D$11)) -> 0 | U15: =N15*(IF(PROFIL!$J$15<>"",PROFIL!$D$12*(1-PROFIL!$J$15),PROFIL!$D$12)) -> 0 | V15: oui | W15: Nominal / fallback
A16: 3 | B16: Tech | C16: CONCEPTION | D16: Conception fonctionnelle détaillée | E16: Conception accès conditionnel | F16: =IF((H16+I16+J16+K16+L16+M16+N16)=0,"-",(H16+I16+J16+K16+L16+M16+N16)) -> 2.5 | G16: =IF((O16+P16+Q16+R16+S16+T16+U16)=0,"-",(O16+P16+Q16+R16+S16+T16+U16)) -> 2075 | I16: 2 | J16: 0.5 | O16: =H16*(IF(PROFIL!$J$15<>"",PROFIL!$D$6*(1-PROFIL!$J$15),PROFIL!$D$6)) -> 0 | P16: =I16*(IF(PROFIL!$J$15<>"",PROFIL!$D$7*(1-PROFIL!$J$15),PROFIL!$D$7)) -> 1700 | Q16: =J16*(IF(PROFIL!$J$15<>"",PROFIL!$D$8*(1-PROFIL!$J$15),PROFIL!$D$8)) -> 375 | R16: =K16*(IF(PROFIL!$J$15<>"",PROFIL!$D$9*(1-PROFIL!$J$15),PROFIL!$D$9)) -> 0 | S16: =L16*(IF(PROFIL!$J$15<>"",PROFIL!$D$10*(1-PROFIL!$J$15),PROFIL!$D$10)) -> 0 | T16: =M16*(IF(PROFIL!$J$15<>"",PROFIL!$D$11*(1-PROFIL!$J$15),PROFIL!$D$11)) -> 0 | U16: =N16*(IF(PROFIL!$J$15<>"",PROFIL!$D$12*(1-PROFIL!$J$15),PROFIL!$D$12)) -> 0 | V16: oui | W16: Point dur du projet
A17: 3 | B17: Tech | C17: CONCEPTION | D17: Conception fonctionnelle détaillée | E17: Gestion des cas dégradés | F17: =IF((H17+I17+J17+K17+L17+M17+N17)=0,"-",(H17+I17+J17+K17+L17+M17+N17)) -> 1.5 | G17: =IF((O17+P17+Q17+R17+S17+T17+U17)=0,"-",(O17+P17+Q17+R17+S17+T17+U17)) -> 1225 | I17: 1 | J17: 0.5 | O17: =H17*(IF(PROFIL!$J$15<>"",PROFIL!$D$6*(1-PROFIL!$J$15),PROFIL!$D$6)) -> 0 | P17: =I17*(IF(PROFIL!$J$15<>"",PROFIL!$D$7*(1-PROFIL!$J$15),PROFIL!$D$7)) -> 850 | Q17: =J17*(IF(PROFIL!$J$15<>"",PROFIL!$D$8*(1-PROFIL!$J$15),PROFIL!$D$8)) -> 375 | R17: =K17*(IF(PROFIL!$J$15<>"",PROFIL!$D$9*(1-PROFIL!$J$15),PROFIL!$D$9)) -> 0 | S17: =L17*(IF(PROFIL!$J$15<>"",PROFIL!$D$10*(1-PROFIL!$J$15),PROFIL!$D$10)) -> 0 | T17: =M17*(IF(PROFIL!$J$15<>"",PROFIL!$D$11*(1-PROFIL!$J$15),PROFIL!$D$11)) -> 0 | U17: =N17*(IF(PROFIL!$J$15<>"",PROFIL!$D$12*(1-PROFIL!$J$15),PROFIL!$D$12)) -> 0 | V17: oui | W17: Sécurité + UX
A18: 2 | B18: Tech | C18: PILOTAGE | D18: Pilotage projet | E18: Pilotage Tech | F18: =IF((H18+I18+J18+K18+L18+M18+N18)=0,"-",(H18+I18+J18+K18+L18+M18+N18)) -> 5 | G18: =IF((O18+P18+Q18+R18+S18+T18+U18)=0,"-",(O18+P18+Q18+R18+S18+T18+U18)) -> 3750 | H18: 5 | O18: =H18*(IF(PROFIL!$J$15<>"",PROFIL!$D$6*(1-PROFIL!$J$15),PROFIL!$D$6)) -> 3750 | P18: =I18*(IF(PROFIL!$J$15<>"",PROFIL!$D$7*(1-PROFIL!$J$15),PROFIL!$D$7)) -> 0 | Q18: =J18*(IF(PROFIL!$J$15<>"",PROFIL!$D$8*(1-PROFIL!$J$15),PROFIL!$D$8)) -> 0 | R18: =K18*(IF(PROFIL!$J$15<>"",PROFIL!$D$9*(1-PROFIL!$J$15),PROFIL!$D$9)) -> 0 | S18: =L18*(IF(PROFIL!$J$15<>"",PROFIL!$D$10*(1-PROFIL!$J$15),PROFIL!$D$10)) -> 0 | T18: =M18*(IF(PROFIL!$J$15<>"",PROFIL!$D$11*(1-PROFIL!$J$15),PROFIL!$D$11)) -> 0 | U18: =N18*(IF(PROFIL!$J$15<>"",PROFIL!$D$12*(1-PROFIL!$J$15),PROFIL!$D$12)) -> 0
A19: 4 | B19: Tech | C19: CONSTRUCTION | D19: Développement et tests unitaires | E19: Configuration Entra ID | F19: =IF((H19+I19+J19+K19+L19+M19+N19)=0,"-",(H19+I19+J19+K19+L19+M19+N19)) -> - | G19: =IF((O19+P19+Q19+R19+S19+T19+U19)=0,"-",(O19+P19+Q19+R19+S19+T19+U19)) -> - | O19: =H19*(IF(PROFIL!$J$15<>"",PROFIL!$D$6*(1-PROFIL!$J$15),PROFIL!$D$6)) -> 0 | P19: =I19*(IF(PROFIL!$J$15<>"",PROFIL!$D$7*(1-PROFIL!$J$15),PROFIL!$D$7)) -> 0 | Q19: =J19*(IF(PROFIL!$J$15<>"",PROFIL!$D$8*(1-PROFIL!$J$15),PROFIL!$D$8)) -> 0 | R19: =K19*(IF(PROFIL!$J$15<>"",PROFIL!$D$9*(1-PROFIL!$J$15),PROFIL!$D$9)) -> 0 | S19: =L19*(IF(PROFIL!$J$15<>"",PROFIL!$D$10*(1-PROFIL!$J$15),PROFIL!$D$10)) -> 0 | T19: =M19*(IF(PROFIL!$J$15<>"",PROFIL!$D$11*(1-PROFIL!$J$15),PROFIL!$D$11)) -> 0 | U19: =N19*(IF(PROFIL!$J$15<>"",PROFIL!$D$12*(1-PROFIL!$J$15),PROFIL!$D$12)) -> 0 | V19: non
A20: 4 | B20: Tech | C20: CONSTRUCTION | D20: Développement et tests unitaires | E20: Configuration WHfB | F20: =IF((H20+I20+J20+K20+L20+M20+N20)=0,"-",(H20+I20+J20+K20+L20+M20+N20)) -> 1.5 | G20: =IF((O20+P20+Q20+R20+S20+T20+U20)=0,"-",(O20+P20+Q20+R20+S20+T20+U20)) -> 1125 | J20: 1.5 | O20: =H20*(IF(PROFIL!$J$15<>"",PROFIL!$D$6*(1-PROFIL!$J$15),PROFIL!$D$6)) -> 0 | P20: =I20*(IF(PROFIL!$J$15<>"",PROFIL!$D$7*(1-PROFIL!$J$15),PROFIL!$D$7)) -> 0 | Q20: =J20*(IF(PROFIL!$J$15<>"",PROFIL!$D$8*(1-PROFIL!$J$15),PROFIL!$D$8)) -> 1125 | R20: =K20*(IF(PROFIL!$J$15<>"",PROFIL!$D$9*(1-PROFIL!$J$15),PROFIL!$D$9)) -> 0 | S20: =L20*(IF(PROFIL!$J$15<>"",PROFIL!$D$10*(1-PROFIL!$J$15),PROFIL!$D$10)) -> 0 | T20: =M20*(IF(PROFIL!$J$15<>"",PROFIL!$D$11*(1-PROFIL!$J$15),PROFIL!$D$11)) -> 0 | U20: =N20*(IF(PROFIL!$J$15<>"",PROFIL!$D$12*(1-PROFIL!$J$15),PROFIL!$D$12)) -> 0 | V20: non | W20: Implémentation déja réalisée
A21: 4 | B21: Tech | C21: CONSTRUCTION | D21: Développement et tests unitaires | E21: Paramétrage accès conditionnel | F21: =IF((H21+I21+J21+K21+L21+M21+N21)=0,"-",(H21+I21+J21+K21+L21+M21+N21)) -> 4 | G21: =IF((O21+P21+Q21+R21+S21+T21+U21)=0,"-",(O21+P21+Q21+R21+S21+T21+U21)) -> 3000 | J21: 4 | O21: =H21*(IF(PROFIL!$J$15<>"",PROFIL!$D$6*(1-PROFIL!$J$15),PROFIL!$D$6)) -> 0 | P21: =I21*(IF(PROFIL!$J$15<>"",PROFIL!$D$7*(1-PROFIL!$J$15),PROFIL!$D$7)) -> 0 | Q21: =J21*(IF(PROFIL!$J$15<>"",PROFIL!$D$8*(1-PROFIL!$J$15),PROFIL!$D$8)) -> 3000 | R21: =K21*(IF(PROFIL!$J$15<>"",PROFIL!$D$9*(1-PROFIL!$J$15),PROFIL!$D$9)) -> 0 | S21: =L21*(IF(PROFIL!$J$15<>"",PROFIL!$D$10*(1-PROFIL!$J$15),PROFIL!$D$10)) -> 0 | T21: =M21*(IF(PROFIL!$J$15<>"",PROFIL!$D$11*(1-PROFIL!$J$15),PROFIL!$D$11)) -> 0 | U21: =N21*(IF(PROFIL!$J$15<>"",PROFIL!$D$12*(1-PROFIL!$J$15),PROFIL!$D$12)) -> 0 | V21: non
A22: 4 | B22: Tech | C22: CONSTRUCTION | D22: Développement et tests unitaires | E22: Intégration VPN F5 | F22: =IF((H22+I22+J22+K22+L22+M22+N22)=0,"-",(H22+I22+J22+K22+L22+M22+N22)) -> 1 | G22: =IF((O22+P22+Q22+R22+S22+T22+U22)=0,"-",(O22+P22+Q22+R22+S22+T22+U22)) -> 750 | J22: 1 | O22: =H22*(IF(PROFIL!$J$15<>"",PROFIL!$D$6*(1-PROFIL!$J$15),PROFIL!$D$6)) -> 0 | P22: =I22*(IF(PROFIL!$J$15<>"",PROFIL!$D$7*(1-PROFIL!$J$15),PROFIL!$D$7)) -> 0 | Q22: =J22*(IF(PROFIL!$J$15<>"",PROFIL!$D$8*(1-PROFIL!$J$15),PROFIL!$D$8)) -> 750 | R22: =K22*(IF(PROFIL!$J$15<>"",PROFIL!$D$9*(1-PROFIL!$J$15),PROFIL!$D$9)) -> 0 | S22: =L22*(IF(PROFIL!$J$15<>"",PROFIL!$D$10*(1-PROFIL!$J$15),PROFIL!$D$10)) -> 0 | T22: =M22*(IF(PROFIL!$J$15<>"",PROFIL!$D$11*(1-PROFIL!$J$15),PROFIL!$D$11)) -> 0 | U22: =N22*(IF(PROFIL!$J$15<>"",PROFIL!$D$12*(1-PROFIL!$J$15),PROFIL!$D$12)) -> 0 | V22: non | W22: Coordination F5
A23: 4 | B23: Tech | C23: CONSTRUCTION | D23: Développement et tests unitaires | E23: Intégration PingAM | F23: =IF((H23+I23+J23+K23+L23+M23+N23)=0,"-",(H23+I23+J23+K23+L23+M23+N23)) -> 1 | G23: =IF((O23+P23+Q23+R23+S23+T23+U23)=0,"-",(O23+P23+Q23+R23+S23+T23+U23)) -> 750 | J23: 1 | O23: =H23*(IF(PROFIL!$J$15<>"",PROFIL!$D$6*(1-PROFIL!$J$15),PROFIL!$D$6)) -> 0 | P23: =I23*(IF(PROFIL!$J$15<>"",PROFIL!$D$7*(1-PROFIL!$J$15),PROFIL!$D$7)) -> 0 | Q23: =J23*(IF(PROFIL!$J$15<>"",PROFIL!$D$8*(1-PROFIL!$J$15),PROFIL!$D$8)) -> 750 | R23: =K23*(IF(PROFIL!$J$15<>"",PROFIL!$D$9*(1-PROFIL!$J$15),PROFIL!$D$9)) -> 0 | S23: =L23*(IF(PROFIL!$J$15<>"",PROFIL!$D$10*(1-PROFIL!$J$15),PROFIL!$D$10)) -> 0 | T23: =M23*(IF(PROFIL!$J$15<>"",PROFIL!$D$11*(1-PROFIL!$J$15),PROFIL!$D$11)) -> 0 | U23: =N23*(IF(PROFIL!$J$15<>"",PROFIL!$D$12*(1-PROFIL!$J$15),PROFIL!$D$12)) -> 0 | V23: non | W23: Dépendance IDP
A24: 5 | B24: Tech | C24: VALIDATION | D24: Tests d’intégration / Recette interne | E24: Tests & Recette | F24: =IF((H24+I24+J24+K24+L24+M24+N24)=0,"-",(H24+I24+J24+K24+L24+M24+N24)) -> 1 | G24: =IF((O24+P24+Q24+R24+S24+T24+U24)=0,"-",(O24+P24+Q24+R24+S24+T24+U24)) -> 750 | J24: 1 | O24: =H24*(IF(PROFIL!$J$15<>"",PROFIL!$D$6*(1-PROFIL!$J$15),PROFIL!$D$6)) -> 0 | P24: =I24*(IF(PROFIL!$J$15<>"",PROFIL!$D$7*(1-PROFIL!$J$15),PROFIL!$D$7)) -> 0 | Q24: =J24*(IF(PROFIL!$J$15<>"",PROFIL!$D$8*(1-PROFIL!$J$15),PROFIL!$D$8)) -> 750 | R24: =K24*(IF(PROFIL!$J$15<>"",PROFIL!$D$9*(1-PROFIL!$J$15),PROFIL!$D$9)) -> 0 | S24: =L24*(IF(PROFIL!$J$15<>"",PROFIL!$D$10*(1-PROFIL!$J$15),PROFIL!$D$10)) -> 0 | T24: =M24*(IF(PROFIL!$J$15<>"",PROFIL!$D$11*(1-PROFIL!$J$15),PROFIL!$D$11)) -> 0 | U24: =N24*(IF(PROFIL!$J$15<>"",PROFIL!$D$12*(1-PROFIL!$J$15),PROFIL!$D$12)) -> 0 | V24: oui | W24: Cahier de Recette
A25: 5 | B25: Tech | C25: VALIDATION | D25: Tests d’intégration / Recette interne | E25: Corrections et ajustements | F25: =IF((H25+I25+J25+K25+L25+M25+N25)=0,"-",(H25+I25+J25+K25+L25+M25+N25)) -> 1 | G25: =IF((O25+P25+Q25+R25+S25+T25+U25)=0,"-",(O25+P25+Q25+R25+S25+T25+U25)) -> 750 | J25: 1 | O25: =H25*(IF(PROFIL!$J$15<>"",PROFIL!$D$6*(1-PROFIL!$J$15),PROFIL!$D$6)) -> 0 | P25: =I25*(IF(PROFIL!$J$15<>"",PROFIL!$D$7*(1-PROFIL!$J$15),PROFIL!$D$7)) -> 0 | Q25: =J25*(IF(PROFIL!$J$15<>"",PROFIL!$D$8*(1-PROFIL!$J$15),PROFIL!$D$8)) -> 750 | R25: =K25*(IF(PROFIL!$J$15<>"",PROFIL!$D$9*(1-PROFIL!$J$15),PROFIL!$D$9)) -> 0 | S25: =L25*(IF(PROFIL!$J$15<>"",PROFIL!$D$10*(1-PROFIL!$J$15),PROFIL!$D$10)) -> 0 | T25: =M25*(IF(PROFIL!$J$15<>"",PROFIL!$D$11*(1-PROFIL!$J$15),PROFIL!$D$11)) -> 0 | U25: =N25*(IF(PROFIL!$J$15<>"",PROFIL!$D$12*(1-PROFIL!$J$15),PROFIL!$D$12)) -> 0 | V25: non
A26: 6 | B26: Tech | C26: VALIDATION | D26: Livraison / installation / Mise en œuvre | E26: Préparation phase pilote | F26: =IF((H26+I26+J26+K26+L26+M26+N26)=0,"-",(H26+I26+J26+K26+L26+M26+N26)) -> 2 | G26: =IF((O26+P26+Q26+R26+S26+T26+U26)=0,"-",(O26+P26+Q26+R26+S26+T26+U26)) -> 1450 | J26: 1 | K26: 1 | O26: =H26*(IF(PROFIL!$J$15<>"",PROFIL!$D$6*(1-PROFIL!$J$15),PROFIL!$D$6)) -> 0 | P26: =I26*(IF(PROFIL!$J$15<>"",PROFIL!$D$7*(1-PROFIL!$J$15),PROFIL!$D$7)) -> 0 | Q26: =J26*(IF(PROFIL!$J$15<>"",PROFIL!$D$8*(1-PROFIL!$J$15),PROFIL!$D$8)) -> 750 | R26: =K26*(IF(PROFIL!$J$15<>"",PROFIL!$D$9*(1-PROFIL!$J$15),PROFIL!$D$9)) -> 700 | S26: =L26*(IF(PROFIL!$J$15<>"",PROFIL!$D$10*(1-PROFIL!$J$15),PROFIL!$D$10)) -> 0 | T26: =M26*(IF(PROFIL!$J$15<>"",PROFIL!$D$11*(1-PROFIL!$J$15),PROFIL!$D$11)) -> 0 | U26: =N26*(IF(PROFIL!$J$15<>"",PROFIL!$D$12*(1-PROFIL!$J$15),PROFIL!$D$12)) -> 0 | V26: non
A27: 6 | B27: Tech | C27: VALIDATION | D27: Livraison / installation / Mise en œuvre | E27: Accompagnement pilote | F27: =IF((H27+I27+J27+K27+L27+M27+N27)=0,"-",(H27+I27+J27+K27+L27+M27+N27)) -> 2 | G27: =IF((O27+P27+Q27+R27+S27+T27+U27)=0,"-",(O27+P27+Q27+R27+S27+T27+U27)) -> 1450 | J27: 1 | K27: 1 | O27: =H27*(IF(PROFIL!$J$15<>"",PROFIL!$D$6*(1-PROFIL!$J$15),PROFIL!$D$6)) -> 0 | P27: =I27*(IF(PROFIL!$J$15<>"",PROFIL!$D$7*(1-PROFIL!$J$15),PROFIL!$D$7)) -> 0 | Q27: =J27*(IF(PROFIL!$J$15<>"",PROFIL!$D$8*(1-PROFIL!$J$15),PROFIL!$D$8)) -> 750 | R27: =K27*(IF(PROFIL!$J$15<>"",PROFIL!$D$9*(1-PROFIL!$J$15),PROFIL!$D$9)) -> 700 | S27: =L27*(IF(PROFIL!$J$15<>"",PROFIL!$D$10*(1-PROFIL!$J$15),PROFIL!$D$10)) -> 0 | T27: =M27*(IF(PROFIL!$J$15<>"",PROFIL!$D$11*(1-PROFIL!$J$15),PROFIL!$D$11)) -> 0 | U27: =N27*(IF(PROFIL!$J$15<>"",PROFIL!$D$12*(1-PROFIL!$J$15),PROFIL!$D$12)) -> 0 | V27: non | W27: Forte sollicitation
A28: 6 | B28: Tech | C28: VALIDATION | D28: Livraison / installation / Mise en œuvre | E28: Ajustements post-pilote | F28: =IF((H28+I28+J28+K28+L28+M28+N28)=0,"-",(H28+I28+J28+K28+L28+M28+N28)) -> 2 | G28: =IF((O28+P28+Q28+R28+S28+T28+U28)=0,"-",(O28+P28+Q28+R28+S28+T28+U28)) -> 1450 | J28: 1 | K28: 1 | O28: =H28*(IF(PROFIL!$J$15<>"",PROFIL!$D$6*(1-PROFIL!$J$15),PROFIL!$D$6)) -> 0 | P28: =I28*(IF(PROFIL!$J$15<>"",PROFIL!$D$7*(1-PROFIL!$J$15),PROFIL!$D$7)) -> 0 | Q28: =J28*(IF(PROFIL!$J$15<>"",PROFIL!$D$8*(1-PROFIL!$J$15),PROFIL!$D$8)) -> 750 | R28: =K28*(IF(PROFIL!$J$15<>"",PROFIL!$D$9*(1-PROFIL!$J$15),PROFIL!$D$9)) -> 700 | S28: =L28*(IF(PROFIL!$J$15<>"",PROFIL!$D$10*(1-PROFIL!$J$15),PROFIL!$D$10)) -> 0 | T28: =M28*(IF(PROFIL!$J$15<>"",PROFIL!$D$11*(1-PROFIL!$J$15),PROFIL!$D$11)) -> 0 | U28: =N28*(IF(PROFIL!$J$15<>"",PROFIL!$D$12*(1-PROFIL!$J$15),PROFIL!$D$12)) -> 0 | V28: non
A29: 8 | B29: Tech | C29: FINALISATION | D29: Support | E29: Rédaction DAT + DEX final | F29: =IF((H29+I29+J29+K29+L29+M29+N29)=0,"-",(H29+I29+J29+K29+L29+M29+N29)) -> 3 | G29: =IF((O29+P29+Q29+R29+S29+T29+U29)=0,"-",(O29+P29+Q29+R29+S29+T29+U29)) -> 2450 | I29: 2 | J29: 1 | O29: =H29*(IF(PROFIL!$J$15<>"",PROFIL!$D$6*(1-PROFIL!$J$15),PROFIL!$D$6)) -> 0 | P29: =I29*(IF(PROFIL!$J$15<>"",PROFIL!$D$7*(1-PROFIL!$J$15),PROFIL!$D$7)) -> 1700 | Q29: =J29*(IF(PROFIL!$J$15<>"",PROFIL!$D$8*(1-PROFIL!$J$15),PROFIL!$D$8)) -> 750 | R29: =K29*(IF(PROFIL!$J$15<>"",PROFIL!$D$9*(1-PROFIL!$J$15),PROFIL!$D$9)) -> 0 | S29: =L29*(IF(PROFIL!$J$15<>"",PROFIL!$D$10*(1-PROFIL!$J$15),PROFIL!$D$10)) -> 0 | T29: =M29*(IF(PROFIL!$J$15<>"",PROFIL!$D$11*(1-PROFIL!$J$15),PROFIL!$D$11)) -> 0 | U29: =N29*(IF(PROFIL!$J$15<>"",PROFIL!$D$12*(1-PROFIL!$J$15),PROFIL!$D$12)) -> 0 | V29: oui
A30: 8 | B30: Tech | C30: FINALISATION | D30: Support | E30: Transfert de compétences | F30: =IF((H30+I30+J30+K30+L30+M30+N30)=0,"-",(H30+I30+J30+K30+L30+M30+N30)) -> 3 | G30: =IF((O30+P30+Q30+R30+S30+T30+U30)=0,"-",(O30+P30+Q30+R30+S30+T30+U30)) -> 2200 | J30: 2 | K30: 1 | O30: =H30*(IF(PROFIL!$J$15<>"",PROFIL!$D$6*(1-PROFIL!$J$15),PROFIL!$D$6)) -> 0 | P30: =I30*(IF(PROFIL!$J$15<>"",PROFIL!$D$7*(1-PROFIL!$J$15),PROFIL!$D$7)) -> 0 | Q30: =J30*(IF(PROFIL!$J$15<>"",PROFIL!$D$8*(1-PROFIL!$J$15),PROFIL!$D$8)) -> 1500 | R30: =K30*(IF(PROFIL!$J$15<>"",PROFIL!$D$9*(1-PROFIL!$J$15),PROFIL!$D$9)) -> 700 | S30: =L30*(IF(PROFIL!$J$15<>"",PROFIL!$D$10*(1-PROFIL!$J$15),PROFIL!$D$10)) -> 0 | T30: =M30*(IF(PROFIL!$J$15<>"",PROFIL!$D$11*(1-PROFIL!$J$15),PROFIL!$D$11)) -> 0 | U30: =N30*(IF(PROFIL!$J$15<>"",PROFIL!$D$12*(1-PROFIL!$J$15),PROFIL!$D$12)) -> 0 | V30: oui
A31: 7 | B31: Change | C31: PILOTAGE | D31: Pilotage projet | E31: Pilotage chantier Change hors Option | F31: =IF((H31+I31+J31+K31+L31+M31+N31)=0,"-",(H31+I31+J31+K31+L31+M31+N31)) -> 7 | G31: =IF((O31+P31+Q31+R31+S31+T31+U31)=0,"-",(O31+P31+Q31+R31+S31+T31+U31)) -> 5250 | H31: 7 | O31: =H31*(IF(PROFIL!$J$15<>"",PROFIL!$D$6*(1-PROFIL!$J$15),PROFIL!$D$6)) -> 5250 | P31: =I31*(IF(PROFIL!$J$15<>"",PROFIL!$D$7*(1-PROFIL!$J$15),PROFIL!$D$7)) -> 0 | Q31: =J31*(IF(PROFIL!$J$15<>"",PROFIL!$D$8*(1-PROFIL!$J$15),PROFIL!$D$8)) -> 0 | R31: =K31*(IF(PROFIL!$J$15<>"",PROFIL!$D$9*(1-PROFIL!$J$15),PROFIL!$D$9)) -> 0 | S31: =L31*(IF(PROFIL!$J$15<>"",PROFIL!$D$10*(1-PROFIL!$J$15),PROFIL!$D$10)) -> 0 | T31: =M31*(IF(PROFIL!$J$15<>"",PROFIL!$D$11*(1-PROFIL!$J$15),PROFIL!$D$11)) -> 0 | U31: =N31*(IF(PROFIL!$J$15<>"",PROFIL!$D$12*(1-PROFIL!$J$15),PROFIL!$D$12)) -> 0 | V31: oui
A32: 7 | B32: Change | C32: VALIDATION | D32: Formation | E32: Atelier - Cadrage populations et stratégie d'accompagnement | F32: =IF((H32+I32+J32+K32+L32+M32+N32)=0,"-",(H32+I32+J32+K32+L32+M32+N32)) -> 1 | G32: =IF((O32+P32+Q32+R32+S32+T32+U32)=0,"-",(O32+P32+Q32+R32+S32+T32+U32)) -> 700 | K32: 1 | O32: =H32*(IF(PROFIL!$J$15<>"",PROFIL!$D$6*(1-PROFIL!$J$15),PROFIL!$D$6)) -> 0 | P32: =I32*(IF(PROFIL!$J$15<>"",PROFIL!$D$7*(1-PROFIL!$J$15),PROFIL!$D$7)) -> 0 | Q32: =J32*(IF(PROFIL!$J$15<>"",PROFIL!$D$8*(1-PROFIL!$J$15),PROFIL!$D$8)) -> 0 | R32: =K32*(IF(PROFIL!$J$15<>"",PROFIL!$D$9*(1-PROFIL!$J$15),PROFIL!$D$9)) -> 700 | S32: =L32*(IF(PROFIL!$J$15<>"",PROFIL!$D$10*(1-PROFIL!$J$15),PROFIL!$D$10)) -> 0 | T32: =M32*(IF(PROFIL!$J$15<>"",PROFIL!$D$11*(1-PROFIL!$J$15),PROFIL!$D$11)) -> 0 | U32: =N32*(IF(PROFIL!$J$15<>"",PROFIL!$D$12*(1-PROFIL!$J$15),PROFIL!$D$12)) -> 0 | V32: oui
A33: 7 | B33: Change | C33: VALIDATION | D33: Formation | E33: Atelier Cadrage stratégie Change | F33: =IF((H33+I33+J33+K33+L33+M33+N33)=0,"-",(H33+I33+J33+K33+L33+M33+N33)) -> 1 | G33: =IF((O33+P33+Q33+R33+S33+T33+U33)=0,"-",(O33+P33+Q33+R33+S33+T33+U33)) -> 700 | K33: 1 | O33: =H33*(IF(PROFIL!$J$15<>"",PROFIL!$D$6*(1-PROFIL!$J$15),PROFIL!$D$6)) -> 0 | P33: =I33*(IF(PROFIL!$J$15<>"",PROFIL!$D$7*(1-PROFIL!$J$15),PROFIL!$D$7)) -> 0 | Q33: =J33*(IF(PROFIL!$J$15<>"",PROFIL!$D$8*(1-PROFIL!$J$15),PROFIL!$D$8)) -> 0 | R33: =K33*(IF(PROFIL!$J$15<>"",PROFIL!$D$9*(1-PROFIL!$J$15),PROFIL!$D$9)) -> 700 | S33: =L33*(IF(PROFIL!$J$15<>"",PROFIL!$D$10*(1-PROFIL!$J$15),PROFIL!$D$10)) -> 0 | T33: =M33*(IF(PROFIL!$J$15<>"",PROFIL!$D$11*(1-PROFIL!$J$15),PROFIL!$D$11)) -> 0 | U33: =N33*(IF(PROFIL!$J$15<>"",PROFIL!$D$12*(1-PROFIL!$J$15),PROFIL!$D$12)) -> 0 | V33: oui
A34: 7 | B34: Change | C34: VALIDATION | D34: Formation | E34: Livrable - Plan d'accompagnement au changement | F34: =IF((H34+I34+J34+K34+L34+M34+N34)=0,"-",(H34+I34+J34+K34+L34+M34+N34)) -> 1.5 | G34: =IF((O34+P34+Q34+R34+S34+T34+U34)=0,"-",(O34+P34+Q34+R34+S34+T34+U34)) -> 1050 | K34: 1.5 | O34: =H34*(IF(PROFIL!$J$15<>"",PROFIL!$D$6*(1-PROFIL!$J$15),PROFIL!$D$6)) -> 0 | P34: =I34*(IF(PROFIL!$J$15<>"",PROFIL!$D$7*(1-PROFIL!$J$15),PROFIL!$D$7)) -> 0 | Q34: =J34*(IF(PROFIL!$J$15<>"",PROFIL!$D$8*(1-PROFIL!$J$15),PROFIL!$D$8)) -> 0 | R34: =K34*(IF(PROFIL!$J$15<>"",PROFIL!$D$9*(1-PROFIL!$J$15),PROFIL!$D$9)) -> 1050 | S34: =L34*(IF(PROFIL!$J$15<>"",PROFIL!$D$10*(1-PROFIL!$J$15),PROFIL!$D$10)) -> 0 | T34: =M34*(IF(PROFIL!$J$15<>"",PROFIL!$D$11*(1-PROFIL!$J$15),PROFIL!$D$11)) -> 0 | U34: =N34*(IF(PROFIL!$J$15<>"",PROFIL!$D$12*(1-PROFIL!$J$15),PROFIL!$D$12)) -> 0 | V34: oui
A35: 7 | B35: Change | C35: VALIDATION | D35: Formation | E35: Livrable - 1 vidéo teasing | F35: =IF((H35+I35+J35+K35+L35+M35+N35)=0,"-",(H35+I35+J35+K35+L35+M35+N35)) -> 3 | G35: =IF((O35+P35+Q35+R35+S35+T35+U35)=0,"-",(O35+P35+Q35+R35+S35+T35+U35)) -> 2100 | K35: 3 | O35: =H35*(IF(PROFIL!$J$15<>"",PROFIL!$D$6*(1-PROFIL!$J$15),PROFIL!$D$6)) -> 0 | P35: =I35*(IF(PROFIL!$J$15<>"",PROFIL!$D$7*(1-PROFIL!$J$15),PROFIL!$D$7)) -> 0 | Q35: =J35*(IF(PROFIL!$J$15<>"",PROFIL!$D$8*(1-PROFIL!$J$15),PROFIL!$D$8)) -> 0 | R35: =K35*(IF(PROFIL!$J$15<>"",PROFIL!$D$9*(1-PROFIL!$J$15),PROFIL!$D$9)) -> 2100 | S35: =L35*(IF(PROFIL!$J$15<>"",PROFIL!$D$10*(1-PROFIL!$J$15),PROFIL!$D$10)) -> 0 | T35: =M35*(IF(PROFIL!$J$15<>"",PROFIL!$D$11*(1-PROFIL!$J$15),PROFIL!$D$11)) -> 0 | U35: =N35*(IF(PROFIL!$J$15<>"",PROFIL!$D$12*(1-PROFIL!$J$15),PROFIL!$D$12)) -> 0 | V35: oui
F36: =IF((H36+I36+J36+K36+L36+M36+N36)=0,"-",(H36+I36+J36+K36+L36+M36+N36)) -> - | G36: =IF((O36+P36+Q36+R36+S36+T36+U36)=0,"-",(O36+P36+Q36+R36+S36+T36+U36)) -> - | O36: =H36*(IF(PROFIL!$J$15<>"",PROFIL!$D$6*(1-PROFIL!$J$15),PROFIL!$D$6)) -> 0 | P36: =I36*(IF(PROFIL!$J$15<>"",PROFIL!$D$7*(1-PROFIL!$J$15),PROFIL!$D$7)) -> 0 | Q36: =J36*(IF(PROFIL!$J$15<>"",PROFIL!$D$8*(1-PROFIL!$J$15),PROFIL!$D$8)) -> 0 | R36: =K36*(IF(PROFIL!$J$15<>"",PROFIL!$D$9*(1-PROFIL!$J$15),PROFIL!$D$9)) -> 0 | S36: =L36*(IF(PROFIL!$J$15<>"",PROFIL!$D$10*(1-PROFIL!$J$15),PROFIL!$D$10)) -> 0 | T36: =M36*(IF(PROFIL!$J$15<>"",PROFIL!$D$11*(1-PROFIL!$J$15),PROFIL!$D$11)) -> 0 | U36: =N36*(IF(PROFIL!$J$15<>"",PROFIL!$D$12*(1-PROFIL!$J$15),PROFIL!$D$12)) -> 0
A37: 7 | B37: Change | C37: VALIDATION | D37: Formation | E37: Livrable - 3 Mails de communication | F37: =IF((H37+I37+J37+K37+L37+M37+N37)=0,"-",(H37+I37+J37+K37+L37+M37+N37)) -> 1.5 | G37: =IF((O37+P37+Q37+R37+S37+T37+U37)=0,"-",(O37+P37+Q37+R37+S37+T37+U37)) -> 1050 | K37: 1.5 | O37: =H37*(IF(PROFIL!$J$15<>"",PROFIL!$D$6*(1-PROFIL!$J$15),PROFIL!$D$6)) -> 0 | P37: =I37*(IF(PROFIL!$J$15<>"",PROFIL!$D$7*(1-PROFIL!$J$15),PROFIL!$D$7)) -> 0 | Q37: =J37*(IF(PROFIL!$J$15<>"",PROFIL!$D$8*(1-PROFIL!$J$15),PROFIL!$D$8)) -> 0 | R37: =K37*(IF(PROFIL!$J$15<>"",PROFIL!$D$9*(1-PROFIL!$J$15),PROFIL!$D$9)) -> 1050 | S37: =L37*(IF(PROFIL!$J$15<>"",PROFIL!$D$10*(1-PROFIL!$J$15),PROFIL!$D$10)) -> 0 | T37: =M37*(IF(PROFIL!$J$15<>"",PROFIL!$D$11*(1-PROFIL!$J$15),PROFIL!$D$11)) -> 0 | U37: =N37*(IF(PROFIL!$J$15<>"",PROFIL!$D$12*(1-PROFIL!$J$15),PROFIL!$D$12)) -> 0 | V37: oui
A38: 7 | B38: Change | C38: VALIDATION | D38: Formation | E38: Livrable - Kit Champions | F38: =IF((H38+I38+J38+K38+L38+M38+N38)=0,"-",(H38+I38+J38+K38+L38+M38+N38)) -> 2 | G38: =IF((O38+P38+Q38+R38+S38+T38+U38)=0,"-",(O38+P38+Q38+R38+S38+T38+U38)) -> 1400 | K38: 2 | O38: =H38*(IF(PROFIL!$J$15<>"",PROFIL!$D$6*(1-PROFIL!$J$15),PROFIL!$D$6)) -> 0 | P38: =I38*(IF(PROFIL!$J$15<>"",PROFIL!$D$7*(1-PROFIL!$J$15),PROFIL!$D$7)) -> 0 | Q38: =J38*(IF(PROFIL!$J$15<>"",PROFIL!$D$8*(1-PROFIL!$J$15),PROFIL!$D$8)) -> 0 | R38: =K38*(IF(PROFIL!$J$15<>"",PROFIL!$D$9*(1-PROFIL!$J$15),PROFIL!$D$9)) -> 1400 | S38: =L38*(IF(PROFIL!$J$15<>"",PROFIL!$D$10*(1-PROFIL!$J$15),PROFIL!$D$10)) -> 0 | T38: =M38*(IF(PROFIL!$J$15<>"",PROFIL!$D$11*(1-PROFIL!$J$15),PROFIL!$D$11)) -> 0 | U38: =N38*(IF(PROFIL!$J$15<>"",PROFIL!$D$12*(1-PROFIL!$J$15),PROFIL!$D$12)) -> 0 | V38: oui
A39: 7 | B39: Change | C39: VALIDATION | D39: Formation | E39: Session Mobilisation Champions | F39: =IF((H39+I39+J39+K39+L39+M39+N39)=0,"-",(H39+I39+J39+K39+L39+M39+N39)) -> 0.5 | G39: =IF((O39+P39+Q39+R39+S39+T39+U39)=0,"-",(O39+P39+Q39+R39+S39+T39+U39)) -> 350 | K39: 0.5 | O39: =H39*(IF(PROFIL!$J$15<>"",PROFIL!$D$6*(1-PROFIL!$J$15),PROFIL!$D$6)) -> 0 | P39: =I39*(IF(PROFIL!$J$15<>"",PROFIL!$D$7*(1-PROFIL!$J$15),PROFIL!$D$7)) -> 0 | Q39: =J39*(IF(PROFIL!$J$15<>"",PROFIL!$D$8*(1-PROFIL!$J$15),PROFIL!$D$8)) -> 0 | R39: =K39*(IF(PROFIL!$J$15<>"",PROFIL!$D$9*(1-PROFIL!$J$15),PROFIL!$D$9)) -> 350 | S39: =L39*(IF(PROFIL!$J$15<>"",PROFIL!$D$10*(1-PROFIL!$J$15),PROFIL!$D$10)) -> 0 | T39: =M39*(IF(PROFIL!$J$15<>"",PROFIL!$D$11*(1-PROFIL!$J$15),PROFIL!$D$11)) -> 0 | U39: =N39*(IF(PROFIL!$J$15<>"",PROFIL!$D$12*(1-PROFIL!$J$15),PROFIL!$D$12)) -> 0 | V39: oui
A40: 7 | B40: Change | C40: VALIDATION | D40: Formation | E40: Session Sponsoring Managers | F40: =IF((H40+I40+J40+K40+L40+M40+N40)=0,"-",(H40+I40+J40+K40+L40+M40+N40)) -> 0.5 | G40: =IF((O40+P40+Q40+R40+S40+T40+U40)=0,"-",(O40+P40+Q40+R40+S40+T40+U40)) -> 350 | K40: 0.5 | O40: =H40*(IF(PROFIL!$J$15<>"",PROFIL!$D$6*(1-PROFIL!$J$15),PROFIL!$D$6)) -> 0 | P40: =I40*(IF(PROFIL!$J$15<>"",PROFIL!$D$7*(1-PROFIL!$J$15),PROFIL!$D$7)) -> 0 | Q40: =J40*(IF(PROFIL!$J$15<>"",PROFIL!$D$8*(1-PROFIL!$J$15),PROFIL!$D$8)) -> 0 | R40: =K40*(IF(PROFIL!$J$15<>"",PROFIL!$D$9*(1-PROFIL!$J$15),PROFIL!$D$9)) -> 350 | S40: =L40*(IF(PROFIL!$J$15<>"",PROFIL!$D$10*(1-PROFIL!$J$15),PROFIL!$D$10)) -> 0 | T40: =M40*(IF(PROFIL!$J$15<>"",PROFIL!$D$11*(1-PROFIL!$J$15),PROFIL!$D$11)) -> 0 | U40: =N40*(IF(PROFIL!$J$15<>"",PROFIL!$D$12*(1-PROFIL!$J$15),PROFIL!$D$12)) -> 0 | V40: oui
A41: 7 | B41: Change | C41: VALIDATION | D41: Formation | E41: Livrable - 1 Modop utilisateurs | F41: =IF((H41+I41+J41+K41+L41+M41+N41)=0,"-",(H41+I41+J41+K41+L41+M41+N41)) -> 2 | G41: =IF((O41+P41+Q41+R41+S41+T41+U41)=0,"-",(O41+P41+Q41+R41+S41+T41+U41)) -> 1400 | K41: 2 | O41: =H41*(IF(PROFIL!$J$15<>"",PROFIL!$D$6*(1-PROFIL!$J$15),PROFIL!$D$6)) -> 0 | P41: =I41*(IF(PROFIL!$J$15<>"",PROFIL!$D$7*(1-PROFIL!$J$15),PROFIL!$D$7)) -> 0 | Q41: =J41*(IF(PROFIL!$J$15<>"",PROFIL!$D$8*(1-PROFIL!$J$15),PROFIL!$D$8)) -> 0 | R41: =K41*(IF(PROFIL!$J$15<>"",PROFIL!$D$9*(1-PROFIL!$J$15),PROFIL!$D$9)) -> 1400 | S41: =L41*(IF(PROFIL!$J$15<>"",PROFIL!$D$10*(1-PROFIL!$J$15),PROFIL!$D$10)) -> 0 | T41: =M41*(IF(PROFIL!$J$15<>"",PROFIL!$D$11*(1-PROFIL!$J$15),PROFIL!$D$11)) -> 0 | U41: =N41*(IF(PROFIL!$J$15<>"",PROFIL!$D$12*(1-PROFIL!$J$15),PROFIL!$D$12)) -> 0 | V41: oui
A42: 7 | B42: Change | C42: VALIDATION | D42: Formation | E42: Livrable - 1 Guide N1 / N2 | F42: =IF((H42+I42+J42+K42+L42+M42+N42)=0,"-",(H42+I42+J42+K42+L42+M42+N42)) -> 3 | G42: =IF((O42+P42+Q42+R42+S42+T42+U42)=0,"-",(O42+P42+Q42+R42+S42+T42+U42)) -> 2150 | J42: 1 | K42: 2 | O42: =H42*(IF(PROFIL!$J$15<>"",PROFIL!$D$6*(1-PROFIL!$J$15),PROFIL!$D$6)) -> 0 | P42: =I42*(IF(PROFIL!$J$15<>"",PROFIL!$D$7*(1-PROFIL!$J$15),PROFIL!$D$7)) -> 0 | Q42: =J42*(IF(PROFIL!$J$15<>"",PROFIL!$D$8*(1-PROFIL!$J$15),PROFIL!$D$8)) -> 750 | R42: =K42*(IF(PROFIL!$J$15<>"",PROFIL!$D$9*(1-PROFIL!$J$15),PROFIL!$D$9)) -> 1400 | S42: =L42*(IF(PROFIL!$J$15<>"",PROFIL!$D$10*(1-PROFIL!$J$15),PROFIL!$D$10)) -> 0 | T42: =M42*(IF(PROFIL!$J$15<>"",PROFIL!$D$11*(1-PROFIL!$J$15),PROFIL!$D$11)) -> 0 | U42: =N42*(IF(PROFIL!$J$15<>"",PROFIL!$D$12*(1-PROFIL!$J$15),PROFIL!$D$12)) -> 0 | V42: oui
A43: 7 | B43: Change | C43: VALIDATION | D43: Formation | E43: Session - 3 Webinars utilisateurs | F43: =IF((H43+I43+J43+K43+L43+M43+N43)=0,"-",(H43+I43+J43+K43+L43+M43+N43)) -> 3 | G43: =IF((O43+P43+Q43+R43+S43+T43+U43)=0,"-",(O43+P43+Q43+R43+S43+T43+U43)) -> 2100 | K43: 3 | O43: =H43*(IF(PROFIL!$J$15<>"",PROFIL!$D$6*(1-PROFIL!$J$15),PROFIL!$D$6)) -> 0 | P43: =I43*(IF(PROFIL!$J$15<>"",PROFIL!$D$7*(1-PROFIL!$J$15),PROFIL!$D$7)) -> 0 | Q43: =J43*(IF(PROFIL!$J$15<>"",PROFIL!$D$8*(1-PROFIL!$J$15),PROFIL!$D$8)) -> 0 | R43: =K43*(IF(PROFIL!$J$15<>"",PROFIL!$D$9*(1-PROFIL!$J$15),PROFIL!$D$9)) -> 2100 | S43: =L43*(IF(PROFIL!$J$15<>"",PROFIL!$D$10*(1-PROFIL!$J$15),PROFIL!$D$10)) -> 0 | T43: =M43*(IF(PROFIL!$J$15<>"",PROFIL!$D$11*(1-PROFIL!$J$15),PROFIL!$D$11)) -> 0 | U43: =N43*(IF(PROFIL!$J$15<>"",PROFIL!$D$12*(1-PROFIL!$J$15),PROFIL!$D$12)) -> 0 | V43: non
A44: 7 | B44: Change | C44: VALIDATION | D44: Formation | F44: =IF((H44+I44+J44+K44+L44+M44+N44)=0,"-",(H44+I44+J44+K44+L44+M44+N44)) -> - | G44: =IF((O44+P44+Q44+R44+S44+T44+U44)=0,"-",(O44+P44+Q44+R44+S44+T44+U44)) -> - | O44: =H44*(IF(PROFIL!$J$15<>"",PROFIL!$D$6*(1-PROFIL!$J$15),PROFIL!$D$6)) -> 0 | P44: =I44*(IF(PROFIL!$J$15<>"",PROFIL!$D$7*(1-PROFIL!$J$15),PROFIL!$D$7)) -> 0 | Q44: =J44*(IF(PROFIL!$J$15<>"",PROFIL!$D$8*(1-PROFIL!$J$15),PROFIL!$D$8)) -> 0 | R44: =K44*(IF(PROFIL!$J$15<>"",PROFIL!$D$9*(1-PROFIL!$J$15),PROFIL!$D$9)) -> 0 | S44: =L44*(IF(PROFIL!$J$15<>"",PROFIL!$D$10*(1-PROFIL!$J$15),PROFIL!$D$10)) -> 0 | T44: =M44*(IF(PROFIL!$J$15<>"",PROFIL!$D$11*(1-PROFIL!$J$15),PROFIL!$D$11)) -> 0 | U44: =N44*(IF(PROFIL!$J$15<>"",PROFIL!$D$12*(1-PROFIL!$J$15),PROFIL!$D$12)) -> 0 | V44: non
A45: 7 | B45: Change | C45: VALIDATION | D45: Formation | E45: Livrable - 1 Tuto vidéo Windows Hello en 3 étapes | F45: =IF((H45+I45+J45+K45+L45+M45+N45)=0,"-",(H45+I45+J45+K45+L45+M45+N45)) -> 2 | G45: =IF((O45+P45+Q45+R45+S45+T45+U45)=0,"-",(O45+P45+Q45+R45+S45+T45+U45)) -> 1400 | K45: 2 | O45: =H45*(IF(PROFIL!$J$15<>"",PROFIL!$D$6*(1-PROFIL!$J$15),PROFIL!$D$6)) -> 0 | P45: =I45*(IF(PROFIL!$J$15<>"",PROFIL!$D$7*(1-PROFIL!$J$15),PROFIL!$D$7)) -> 0 | Q45: =J45*(IF(PROFIL!$J$15<>"",PROFIL!$D$8*(1-PROFIL!$J$15),PROFIL!$D$8)) -> 0 | R45: =K45*(IF(PROFIL!$J$15<>"",PROFIL!$D$9*(1-PROFIL!$J$15),PROFIL!$D$9)) -> 1400 | S45: =L45*(IF(PROFIL!$J$15<>"",PROFIL!$D$10*(1-PROFIL!$J$15),PROFIL!$D$10)) -> 0 | T45: =M45*(IF(PROFIL!$J$15<>"",PROFIL!$D$11*(1-PROFIL!$J$15),PROFIL!$D$11)) -> 0 | U45: =N45*(IF(PROFIL!$J$15<>"",PROFIL!$D$12*(1-PROFIL!$J$15),PROFIL!$D$12)) -> 0 | V45: non
A46: 7 | B46: Change | C46: VALIDATION | D46: Formation | E46: Livrable - FAQ | F46: =IF((H46+I46+J46+K46+L46+M46+N46)=0,"-",(H46+I46+J46+K46+L46+M46+N46)) -> 1 | G46: =IF((O46+P46+Q46+R46+S46+T46+U46)=0,"-",(O46+P46+Q46+R46+S46+T46+U46)) -> 700 | K46: 1 | O46: =H46*(IF(PROFIL!$J$15<>"",PROFIL!$D$6*(1-PROFIL!$J$15),PROFIL!$D$6)) -> 0 | P46: =I46*(IF(PROFIL!$J$15<>"",PROFIL!$D$7*(1-PROFIL!$J$15),PROFIL!$D$7)) -> 0 | Q46: =J46*(IF(PROFIL!$J$15<>"",PROFIL!$D$8*(1-PROFIL!$J$15),PROFIL!$D$8)) -> 0 | R46: =K46*(IF(PROFIL!$J$15<>"",PROFIL!$D$9*(1-PROFIL!$J$15),PROFIL!$D$9)) -> 700 | S46: =L46*(IF(PROFIL!$J$15<>"",PROFIL!$D$10*(1-PROFIL!$J$15),PROFIL!$D$10)) -> 0 | T46: =M46*(IF(PROFIL!$J$15<>"",PROFIL!$D$11*(1-PROFIL!$J$15),PROFIL!$D$11)) -> 0 | U46: =N46*(IF(PROFIL!$J$15<>"",PROFIL!$D$12*(1-PROFIL!$J$15),PROFIL!$D$12)) -> 0 | V46: non
A47: 7 | B47: Change | C47: VALIDATION | D47: Formation | E47: Accompagnement des 13 Sites Principaux (Distanciel) | F47: =IF((H47+I47+J47+K47+L47+M47+N47)=0,"-",(H47+I47+J47+K47+L47+M47+N47)) -> - | G47: =IF((O47+P47+Q47+R47+S47+T47+U47)=0,"-",(O47+P47+Q47+R47+S47+T47+U47)) -> - | O47: =H47*(IF(PROFIL!$J$15<>"",PROFIL!$D$6*(1-PROFIL!$J$15),PROFIL!$D$6)) -> 0 | P47: =I47*(IF(PROFIL!$J$15<>"",PROFIL!$D$7*(1-PROFIL!$J$15),PROFIL!$D$7)) -> 0 | Q47: =J47*(IF(PROFIL!$J$15<>"",PROFIL!$D$8*(1-PROFIL!$J$15),PROFIL!$D$8)) -> 0 | R47: =K47*(IF(PROFIL!$J$15<>"",PROFIL!$D$9*(1-PROFIL!$J$15),PROFIL!$D$9)) -> 0 | S47: =L47*(IF(PROFIL!$J$15<>"",PROFIL!$D$10*(1-PROFIL!$J$15),PROFIL!$D$10)) -> 0 | T47: =M47*(IF(PROFIL!$J$15<>"",PROFIL!$D$11*(1-PROFIL!$J$15),PROFIL!$D$11)) -> 0 | U47: =N47*(IF(PROFIL!$J$15<>"",PROFIL!$D$12*(1-PROFIL!$J$15),PROFIL!$D$12)) -> 0 | V47: non
A48: 7 | B48: Change | C48: VALIDATION | D48: Formation | E48: OPTION 1 : Accompagnement des 13 Sites principaux (Ditanciels) + 4 jours pour les vagues des grands sites | F48: =IF((H48+I48+J48+K48+L48+M48+N48)=0,"-",(H48+I48+J48+K48+L48+M48+N48)) -> 20 | G48: =IF((O48+P48+Q48+R48+S48+T48+U48)=0,"-",(O48+P48+Q48+R48+S48+T48+U48)) -> 14500 | J48: 10 | K48: 10 | O48: =H48*(IF(PROFIL!$J$15<>"",PROFIL!$D$6*(1-PROFIL!$J$15),PROFIL!$D$6)) -> 0 | P48: =I48*(IF(PROFIL!$J$15<>"",PROFIL!$D$7*(1-PROFIL!$J$15),PROFIL!$D$7)) -> 0 | Q48: =J48*(IF(PROFIL!$J$15<>"",PROFIL!$D$8*(1-PROFIL!$J$15),PROFIL!$D$8)) -> 7500 | R48: =K48*(IF(PROFIL!$J$15<>"",PROFIL!$D$9*(1-PROFIL!$J$15),PROFIL!$D$9)) -> 7000 | S48: =L48*(IF(PROFIL!$J$15<>"",PROFIL!$D$10*(1-PROFIL!$J$15),PROFIL!$D$10)) -> 0 | T48: =M48*(IF(PROFIL!$J$15<>"",PROFIL!$D$11*(1-PROFIL!$J$15),PROFIL!$D$11)) -> 0 | U48: =N48*(IF(PROFIL!$J$15<>"",PROFIL!$D$12*(1-PROFIL!$J$15),PROFIL!$D$12)) -> 0 | V48: non | W48: Affiché en moitié moitié afin d'afficher un TJM Moyen. Indenpendemment on peut amener le consultant Change ou Identité sur les journées de bascule des Sites
A49: 7 | B49: Change | C49: PILOTAGE | D49: Pilotage projet | E49: Pilotage Option Change 15 sites | F49: =IF((H49+I49+J49+K49+L49+M49+N49)=0,"-",(H49+I49+J49+K49+L49+M49+N49)) -> 1.5 | G49: =IF((O49+P49+Q49+R49+S49+T49+U49)=0,"-",(O49+P49+Q49+R49+S49+T49+U49)) -> 1125 | H49: 1.5 | O49: =H49*(IF(PROFIL!$J$15<>"",PROFIL!$D$6*(1-PROFIL!$J$15),PROFIL!$D$6)) -> 1125 | P49: =I49*(IF(PROFIL!$J$15<>"",PROFIL!$D$7*(1-PROFIL!$J$15),PROFIL!$D$7)) -> 0 | Q49: =J49*(IF(PROFIL!$J$15<>"",PROFIL!$D$8*(1-PROFIL!$J$15),PROFIL!$D$8)) -> 0 | R49: =K49*(IF(PROFIL!$J$15<>"",PROFIL!$D$9*(1-PROFIL!$J$15),PROFIL!$D$9)) -> 0 | S49: =L49*(IF(PROFIL!$J$15<>"",PROFIL!$D$10*(1-PROFIL!$J$15),PROFIL!$D$10)) -> 0 | T49: =M49*(IF(PROFIL!$J$15<>"",PROFIL!$D$11*(1-PROFIL!$J$15),PROFIL!$D$11)) -> 0 | U49: =N49*(IF(PROFIL!$J$15<>"",PROFIL!$D$12*(1-PROFIL!$J$15),PROFIL!$D$12)) -> 0 | V49: non
A50: 7 | B50: Change | C50: VALIDATION | D50: Formation | E50: OPTION 2 : Dashboard Complet PowerBI | F50: =IF((H50+I50+J50+K50+L50+M50+N50)=0,"-",(H50+I50+J50+K50+L50+M50+N50)) -> 6 | G50: =IF((O50+P50+Q50+R50+S50+T50+U50)=0,"-",(O50+P50+Q50+R50+S50+T50+U50)) -> 4750 | H50: 0.5 | J50: 0.5 | L50: 5 | O50: =H50*(IF(PROFIL!$J$15<>"",PROFIL!$D$6*(1-PROFIL!$J$15),PROFIL!$D$6)) -> 375 | P50: =I50*(IF(PROFIL!$J$15<>"",PROFIL!$D$7*(1-PROFIL!$J$15),PROFIL!$D$7)) -> 0 | Q50: =J50*(IF(PROFIL!$J$15<>"",PROFIL!$D$8*(1-PROFIL!$J$15),PROFIL!$D$8)) -> 375 | R50: =K50*(IF(PROFIL!$J$15<>"",PROFIL!$D$9*(1-PROFIL!$J$15),PROFIL!$D$9)) -> 0 | S50: =L50*(IF(PROFIL!$J$15<>"",PROFIL!$D$10*(1-PROFIL!$J$15),PROFIL!$D$10)) -> 4000 | T50: =M50*(IF(PROFIL!$J$15<>"",PROFIL!$D$11*(1-PROFIL!$J$15),PROFIL!$D$11)) -> 0 | U50: =N50*(IF(PROFIL!$J$15<>"",PROFIL!$D$12*(1-PROFIL!$J$15),PROFIL!$D$12)) -> 0 | V50: oui | W50: PowerBI suivi déploiement
F51: =IF((H51+I51+J51+K51+L51+M51+N51)=0,"-",(H51+I51+J51+K51+L51+M51+N51)) -> - | G51: =IF((O51+P51+Q51+R51+S51+T51+U51)=0,"-",(O51+P51+Q51+R51+S51+T51+U51)) -> - | O51: =H51*(IF(PROFIL!$J$15<>"",PROFIL!$D$6*(1-PROFIL!$J$15),PROFIL!$D$6)) -> 0 | P51: =I51*(IF(PROFIL!$J$15<>"",PROFIL!$D$7*(1-PROFIL!$J$15),PROFIL!$D$7)) -> 0 | Q51: =J51*(IF(PROFIL!$J$15<>"",PROFIL!$D$8*(1-PROFIL!$J$15),PROFIL!$D$8)) -> 0 | R51: =K51*(IF(PROFIL!$J$15<>"",PROFIL!$D$9*(1-PROFIL!$J$15),PROFIL!$D$9)) -> 0 | S51: =L51*(IF(PROFIL!$J$15<>"",PROFIL!$D$10*(1-PROFIL!$J$15),PROFIL!$D$10)) -> 0 | T51: =M51*(IF(PROFIL!$J$15<>"",PROFIL!$D$11*(1-PROFIL!$J$15),PROFIL!$D$11)) -> 0 | U51: =N51*(IF(PROFIL!$J$15<>"",PROFIL!$D$12*(1-PROFIL!$J$15),PROFIL!$D$12)) -> 0
F52: =IF((H52+I52+J52+K52+L52+M52+N52)=0,"-",(H52+I52+J52+K52+L52+M52+N52)) -> - | G52: =IF((O52+P52+Q52+R52+S52+T52+U52)=0,"-",(O52+P52+Q52+R52+S52+T52+U52)) -> - | O52: =H52*(IF(PROFIL!$J$15<>"",PROFIL!$D$6*(1-PROFIL!$J$15),PROFIL!$D$6)) -> 0 | P52: =I52*(IF(PROFIL!$J$15<>"",PROFIL!$D$7*(1-PROFIL!$J$15),PROFIL!$D$7)) -> 0 | Q52: =J52*(IF(PROFIL!$J$15<>"",PROFIL!$D$8*(1-PROFIL!$J$15),PROFIL!$D$8)) -> 0 | R52: =K52*(IF(PROFIL!$J$15<>"",PROFIL!$D$9*(1-PROFIL!$J$15),PROFIL!$D$9)) -> 0 | S52: =L52*(IF(PROFIL!$J$15<>"",PROFIL!$D$10*(1-PROFIL!$J$15),PROFIL!$D$10)) -> 0 | T52: =M52*(IF(PROFIL!$J$15<>"",PROFIL!$D$11*(1-PROFIL!$J$15),PROFIL!$D$11)) -> 0 | U52: =N52*(IF(PROFIL!$J$15<>"",PROFIL!$D$12*(1-PROFIL!$J$15),PROFIL!$D$12)) -> 0
F53: =IF((H53+I53+J53+K53+L53+M53+N53)=0,"-",(H53+I53+J53+K53+L53+M53+N53)) -> - | G53: =IF((O53+P53+Q53+R53+S53+T53+U53)=0,"-",(O53+P53+Q53+R53+S53+T53+U53)) -> - | O53: =H53*(IF(PROFIL!$J$15<>"",PROFIL!$D$6*(1-PROFIL!$J$15),PROFIL!$D$6)) -> 0 | P53: =I53*(IF(PROFIL!$J$15<>"",PROFIL!$D$7*(1-PROFIL!$J$15),PROFIL!$D$7)) -> 0 | Q53: =J53*(IF(PROFIL!$J$15<>"",PROFIL!$D$8*(1-PROFIL!$J$15),PROFIL!$D$8)) -> 0 | R53: =K53*(IF(PROFIL!$J$15<>"",PROFIL!$D$9*(1-PROFIL!$J$15),PROFIL!$D$9)) -> 0 | S53: =L53*(IF(PROFIL!$J$15<>"",PROFIL!$D$10*(1-PROFIL!$J$15),PROFIL!$D$10)) -> 0 | T53: =M53*(IF(PROFIL!$J$15<>"",PROFIL!$D$11*(1-PROFIL!$J$15),PROFIL!$D$11)) -> 0 | U53: =N53*(IF(PROFIL!$J$15<>"",PROFIL!$D$12*(1-PROFIL!$J$15),PROFIL!$D$12)) -> 0
F54: =IF((H54+I54+J54+K54+L54+M54+N54)=0,"-",(H54+I54+J54+K54+L54+M54+N54)) -> - | G54: =IF((O54+P54+Q54+R54+S54+T54+U54)=0,"-",(O54+P54+Q54+R54+S54+T54+U54)) -> -
F55: =IF((H55+I55+J55+K55+L55+M55+N55)=0,"-",(H55+I55+J55+K55+L55+M55+N55)) -> - | G55: =IF((O55+P55+Q55+R55+S55+T55+U55)=0,"-",(O55+P55+Q55+R55+S55+T55+U55)) -> - | O55: =H55*(IF(PROFIL!$J$15<>"",PROFIL!$D$6*(1-PROFIL!$J$15),PROFIL!$D$6)) -> 0 | P55: =I55*(IF(PROFIL!$J$15<>"",PROFIL!$D$7*(1-PROFIL!$J$15),PROFIL!$D$7)) -> 0 | Q55: =J55*(IF(PROFIL!$J$15<>"",PROFIL!$D$8*(1-PROFIL!$J$15),PROFIL!$D$8)) -> 0 | R55: =K55*(IF(PROFIL!$J$15<>"",PROFIL!$D$9*(1-PROFIL!$J$15),PROFIL!$D$9)) -> 0 | S55: =L55*(IF(PROFIL!$J$15<>"",PROFIL!$D$10*(1-PROFIL!$J$15),PROFIL!$D$10)) -> 0 | T55: =M55*(IF(PROFIL!$J$15<>"",PROFIL!$D$11*(1-PROFIL!$J$15),PROFIL!$D$11)) -> 0 | U55: =N55*(IF(PROFIL!$J$15<>"",PROFIL!$D$12*(1-PROFIL!$J$15),PROFIL!$D$12)) -> 0
F56: =IF((H56+I56+J56+K56+L56+M56+N56)=0,"-",(H56+I56+J56+K56+L56+M56+N56)) -> - | G56: =IF((O56+P56+Q56+R56+S56+T56+U56)=0,"-",(O56+P56+Q56+R56+S56+T56+U56)) -> - | O56: =H56*(IF(PROFIL!$J$15<>"",PROFIL!$D$6*(1-PROFIL!$J$15),PROFIL!$D$6)) -> 0 | P56: =I56*(IF(PROFIL!$J$15<>"",PROFIL!$D$7*(1-PROFIL!$J$15),PROFIL!$D$7)) -> 0 | Q56: =J56*(IF(PROFIL!$J$15<>"",PROFIL!$D$8*(1-PROFIL!$J$15),PROFIL!$D$8)) -> 0 | R56: =K56*(IF(PROFIL!$J$15<>"",PROFIL!$D$9*(1-PROFIL!$J$15),PROFIL!$D$9)) -> 0 | S56: =L56*(IF(PROFIL!$J$15<>"",PROFIL!$D$10*(1-PROFIL!$J$15),PROFIL!$D$10)) -> 0 | T56: =M56*(IF(PROFIL!$J$15<>"",PROFIL!$D$11*(1-PROFIL!$J$15),PROFIL!$D$11)) -> 0 | U56: =N56*(IF(PROFIL!$J$15<>"",PROFIL!$D$12*(1-PROFIL!$J$15),PROFIL!$D$12)) -> 0
F57: =IF((H57+I57+J57+K57+L57+M57+N57)=0,"-",(H57+I57+J57+K57+L57+M57+N57)) -> - | G57: =IF((O57+P57+Q57+R57+S57+T57+U57)=0,"-",(O57+P57+Q57+R57+S57+T57+U57)) -> - | O57: =H57*(IF(PROFIL!$J$15<>"",PROFIL!$D$6*(1-PROFIL!$J$15),PROFIL!$D$6)) -> 0 | P57: =I57*(IF(PROFIL!$J$15<>"",PROFIL!$D$7*(1-PROFIL!$J$15),PROFIL!$D$7)) -> 0 | Q57: =J57*(IF(PROFIL!$J$15<>"",PROFIL!$D$8*(1-PROFIL!$J$15),PROFIL!$D$8)) -> 0 | R57: =K57*(IF(PROFIL!$J$15<>"",PROFIL!$D$9*(1-PROFIL!$J$15),PROFIL!$D$9)) -> 0 | S57: =L57*(IF(PROFIL!$J$15<>"",PROFIL!$D$10*(1-PROFIL!$J$15),PROFIL!$D$10)) -> 0 | T57: =M57*(IF(PROFIL!$J$15<>"",PROFIL!$D$11*(1-PROFIL!$J$15),PROFIL!$D$11)) -> 0 | U57: =N57*(IF(PROFIL!$J$15<>"",PROFIL!$D$12*(1-PROFIL!$J$15),PROFIL!$D$12)) -> 0
F58: =IF((H58+I58+J58+K58+L58+M58+N58)=0,"-",(H58+I58+J58+K58+L58+M58+N58)) -> - | G58: =IF((O58+P58+Q58+R58+S58+T58+U58)=0,"-",(O58+P58+Q58+R58+S58+T58+U58)) -> - | O58: =H58*(IF(PROFIL!$J$15<>"",PROFIL!$D$6*(1-PROFIL!$J$15),PROFIL!$D$6)) -> 0 | P58: =I58*(IF(PROFIL!$J$15<>"",PROFIL!$D$7*(1-PROFIL!$J$15),PROFIL!$D$7)) -> 0 | Q58: =J58*(IF(PROFIL!$J$15<>"",PROFIL!$D$8*(1-PROFIL!$J$15),PROFIL!$D$8)) -> 0 | R58: =K58*(IF(PROFIL!$J$15<>"",PROFIL!$D$9*(1-PROFIL!$J$15),PROFIL!$D$9)) -> 0 | S58: =L58*(IF(PROFIL!$J$15<>"",PROFIL!$D$10*(1-PROFIL!$J$15),PROFIL!$D$10)) -> 0 | T58: =M58*(IF(PROFIL!$J$15<>"",PROFIL!$D$11*(1-PROFIL!$J$15),PROFIL!$D$11)) -> 0 | U58: =N58*(IF(PROFIL!$J$15<>"",PROFIL!$D$12*(1-PROFIL!$J$15),PROFIL!$D$12)) -> 0
F59: =IF((H59+I59+J59+K59+L59+M59+N59)=0,"-",(H59+I59+J59+K59+L59+M59+N59)) -> - | G59: =IF((O59+P59+Q59+R59+S59+T59+U59)=0,"-",(O59+P59+Q59+R59+S59+T59+U59)) -> - | O59: =H59*(IF(PROFIL!$J$15<>"",PROFIL!$D$6*(1-PROFIL!$J$15),PROFIL!$D$6)) -> 0 | P59: =I59*(IF(PROFIL!$J$15<>"",PROFIL!$D$7*(1-PROFIL!$J$15),PROFIL!$D$7)) -> 0 | Q59: =J59*(IF(PROFIL!$J$15<>"",PROFIL!$D$8*(1-PROFIL!$J$15),PROFIL!$D$8)) -> 0 | R59: =K59*(IF(PROFIL!$J$15<>"",PROFIL!$D$9*(1-PROFIL!$J$15),PROFIL!$D$9)) -> 0 | S59: =L59*(IF(PROFIL!$J$15<>"",PROFIL!$D$10*(1-PROFIL!$J$15),PROFIL!$D$10)) -> 0 | T59: =M59*(IF(PROFIL!$J$15<>"",PROFIL!$D$11*(1-PROFIL!$J$15),PROFIL!$D$11)) -> 0 | U59: =N59*(IF(PROFIL!$J$15<>"",PROFIL!$D$12*(1-PROFIL!$J$15),PROFIL!$D$12)) -> 0
A60: 9 | B60: Risques | C60: PROVISION | D60: Provision pour risque | E60: Aléas accès conditionnel | F60: =IF((H60+I60+J60+K60+L60+M60+N60)=0,"-",(H60+I60+J60+K60+L60+M60+N60)) -> 1 | G60: =IF((O60+P60+Q60+R60+S60+T60+U60)=0,"-",(O60+P60+Q60+R60+S60+T60+U60)) -> 800 | I60: 0.5 | J60: 0.5 | O60: =H60*(IF(PROFIL!$J$15<>"",PROFIL!$D$6*(1-PROFIL!$J$15),PROFIL!$D$6)) -> 0 | P60: =I60*(IF(PROFIL!$J$15<>"",PROFIL!$D$7*(1-PROFIL!$J$15),PROFIL!$D$7)) -> 425 | Q60: =J60*(IF(PROFIL!$J$15<>"",PROFIL!$D$8*(1-PROFIL!$J$15),PROFIL!$D$8)) -> 375 | R60: =K60*(IF(PROFIL!$J$15<>"",PROFIL!$D$9*(1-PROFIL!$J$15),PROFIL!$D$9)) -> 0 | S60: =L60*(IF(PROFIL!$J$15<>"",PROFIL!$D$10*(1-PROFIL!$J$15),PROFIL!$D$10)) -> 0 | T60: =M60*(IF(PROFIL!$J$15<>"",PROFIL!$D$11*(1-PROFIL!$J$15),PROFIL!$D$11)) -> 0 | U60: =N60*(IF(PROFIL!$J$15<>"",PROFIL!$D$12*(1-PROFIL!$J$15),PROFIL!$D$12)) -> 0 | V60: NON
A61: 9 | B61: Risques | C61: PROVISION | D61: Provision pour risque | E61: Aléas déploiement | F61: =IF((H61+I61+J61+K61+L61+M61+N61)=0,"-",(H61+I61+J61+K61+L61+M61+N61)) -> 1.5 | G61: =IF((O61+P61+Q61+R61+S61+T61+U61)=0,"-",(O61+P61+Q61+R61+S61+T61+U61)) -> 1150 | I61: 0.5 | J61: 0.5 | K61: 0.5 | O61: =H61*(IF(PROFIL!$J$15<>"",PROFIL!$D$6*(1-PROFIL!$J$15),PROFIL!$D$6)) -> 0 | P61: =I61*(IF(PROFIL!$J$15<>"",PROFIL!$D$7*(1-PROFIL!$J$15),PROFIL!$D$7)) -> 425 | Q61: =J61*(IF(PROFIL!$J$15<>"",PROFIL!$D$8*(1-PROFIL!$J$15),PROFIL!$D$8)) -> 375 | R61: =K61*(IF(PROFIL!$J$15<>"",PROFIL!$D$9*(1-PROFIL!$J$15),PROFIL!$D$9)) -> 350 | S61: =L61*(IF(PROFIL!$J$15<>"",PROFIL!$D$10*(1-PROFIL!$J$15),PROFIL!$D$10)) -> 0 | T61: =M61*(IF(PROFIL!$J$15<>"",PROFIL!$D$11*(1-PROFIL!$J$15),PROFIL!$D$11)) -> 0 | U61: =N61*(IF(PROFIL!$J$15<>"",PROFIL!$D$12*(1-PROFIL!$J$15),PROFIL!$D$12)) -> 0 | V61: NON
A62: 9 | B62: Risques | C62: PROVISION | D62: Provision pour risque | E62: Aléas adoption utilisateurs | F62: =IF((H62+I62+J62+K62+L62+M62+N62)=0,"-",(H62+I62+J62+K62+L62+M62+N62)) -> 1 | G62: =IF((O62+P62+Q62+R62+S62+T62+U62)=0,"-",(O62+P62+Q62+R62+S62+T62+U62)) -> 700 | K62: 1 | O62: =H62*(IF(PROFIL!$J$15<>"",PROFIL!$D$6*(1-PROFIL!$J$15),PROFIL!$D$6)) -> 0 | P62: =I62*(IF(PROFIL!$J$15<>"",PROFIL!$D$7*(1-PROFIL!$J$15),PROFIL!$D$7)) -> 0 | Q62: =J62*(IF(PROFIL!$J$15<>"",PROFIL!$D$8*(1-PROFIL!$J$15),PROFIL!$D$8)) -> 0 | R62: =K62*(IF(PROFIL!$J$15<>"",PROFIL!$D$9*(1-PROFIL!$J$15),PROFIL!$D$9)) -> 700 | S62: =L62*(IF(PROFIL!$J$15<>"",PROFIL!$D$10*(1-PROFIL!$J$15),PROFIL!$D$10)) -> 0 | T62: =M62*(IF(PROFIL!$J$15<>"",PROFIL!$D$11*(1-PROFIL!$J$15),PROFIL!$D$11)) -> 0 | U62: =N62*(IF(PROFIL!$J$15<>"",PROFIL!$D$12*(1-PROFIL!$J$15),PROFIL!$D$12)) -> 0 | V62: NON
A63: 9 | B63: Risques | C63: PROVISION | D63: Provision pour risque | E63: Aléas planning / dépendances | F63: =IF((H63+I63+J63+K63+L63+M63+N63)=0,"-",(H63+I63+J63+K63+L63+M63+N63)) -> 0.5 | G63: =IF((O63+P63+Q63+R63+S63+T63+U63)=0,"-",(O63+P63+Q63+R63+S63+T63+U63)) -> 375 | H63: 0.5 | O63: =H63*(IF(PROFIL!$J$15<>"",PROFIL!$D$6*(1-PROFIL!$J$15),PROFIL!$D$6)) -> 375 | P63: =I63*(IF(PROFIL!$J$15<>"",PROFIL!$D$7*(1-PROFIL!$J$15),PROFIL!$D$7)) -> 0 | Q63: =J63*(IF(PROFIL!$J$15<>"",PROFIL!$D$8*(1-PROFIL!$J$15),PROFIL!$D$8)) -> 0 | R63: =K63*(IF(PROFIL!$J$15<>"",PROFIL!$D$9*(1-PROFIL!$J$15),PROFIL!$D$9)) -> 0 | S63: =L63*(IF(PROFIL!$J$15<>"",PROFIL!$D$10*(1-PROFIL!$J$15),PROFIL!$D$10)) -> 0 | T63: =M63*(IF(PROFIL!$J$15<>"",PROFIL!$D$11*(1-PROFIL!$J$15),PROFIL!$D$11)) -> 0 | U63: =N63*(IF(PROFIL!$J$15<>"",PROFIL!$D$12*(1-PROFIL!$J$15),PROFIL!$D$12)) -> 0 | V63: NON
F64: =IF((H64+I64+J64+K64+L64+M64+N64)=0,"-",(H64+I64+J64+K64+L64+M64+N64)) -> - | G64: =IF((O64+P64+Q64+R64+S64+T64+U64)=0,"-",(O64+P64+Q64+R64+S64+T64+U64)) -> - | O64: =H64*(IF(PROFIL!$J$15<>"",PROFIL!$D$6*(1-PROFIL!$J$15),PROFIL!$D$6)) -> 0 | P64: =I64*(IF(PROFIL!$J$15<>"",PROFIL!$D$7*(1-PROFIL!$J$15),PROFIL!$D$7)) -> 0 | Q64: =J64*(IF(PROFIL!$J$15<>"",PROFIL!$D$8*(1-PROFIL!$J$15),PROFIL!$D$8)) -> 0 | R64: =K64*(IF(PROFIL!$J$15<>"",PROFIL!$D$9*(1-PROFIL!$J$15),PROFIL!$D$9)) -> 0 | S64: =L64*(IF(PROFIL!$J$15<>"",PROFIL!$D$10*(1-PROFIL!$J$15),PROFIL!$D$10)) -> 0 | T64: =M64*(IF(PROFIL!$J$15<>"",PROFIL!$D$11*(1-PROFIL!$J$15),PROFIL!$D$11)) -> 0 | U64: =N64*(IF(PROFIL!$J$15<>"",PROFIL!$D$12*(1-PROFIL!$J$15),PROFIL!$D$12)) -> 0
F65: =IF((H65+I65+J65+K65+L65+M65+N65)=0,"-",(H65+I65+J65+K65+L65+M65+N65)) -> - | G65: =IF((O65+P65+Q65+R65+S65+T65+U65)=0,"-",(O65+P65+Q65+R65+S65+T65+U65)) -> - | O65: =H65*(IF(PROFIL!$J$15<>"",PROFIL!$D$6*(1-PROFIL!$J$15),PROFIL!$D$6)) -> 0 | P65: =I65*(IF(PROFIL!$J$15<>"",PROFIL!$D$7*(1-PROFIL!$J$15),PROFIL!$D$7)) -> 0 | Q65: =J65*(IF(PROFIL!$J$15<>"",PROFIL!$D$8*(1-PROFIL!$J$15),PROFIL!$D$8)) -> 0 | R65: =K65*(IF(PROFIL!$J$15<>"",PROFIL!$D$9*(1-PROFIL!$J$15),PROFIL!$D$9)) -> 0 | S65: =L65*(IF(PROFIL!$J$15<>"",PROFIL!$D$10*(1-PROFIL!$J$15),PROFIL!$D$10)) -> 0 | T65: =M65*(IF(PROFIL!$J$15<>"",PROFIL!$D$11*(1-PROFIL!$J$15),PROFIL!$D$11)) -> 0 | U65: =N65*(IF(PROFIL!$J$15<>"",PROFIL!$D$12*(1-PROFIL!$J$15),PROFIL!$D$12)) -> 0
F66: =IF((H66+I66+J66+K66+L66+M66+N66)=0,"-",(H66+I66+J66+K66+L66+M66+N66)) -> - | G66: =IF((O66+P66+Q66+R66+S66+T66+U66)=0,"-",(O66+P66+Q66+R66+S66+T66+U66)) -> - | O66: =H66*(IF(PROFIL!$J$15<>"",PROFIL!$D$6*(1-PROFIL!$J$15),PROFIL!$D$6)) -> 0 | P66: =I66*(IF(PROFIL!$J$15<>"",PROFIL!$D$7*(1-PROFIL!$J$15),PROFIL!$D$7)) -> 0 | Q66: =J66*(IF(PROFIL!$J$15<>"",PROFIL!$D$8*(1-PROFIL!$J$15),PROFIL!$D$8)) -> 0 | R66: =K66*(IF(PROFIL!$J$15<>"",PROFIL!$D$9*(1-PROFIL!$J$15),PROFIL!$D$9)) -> 0 | S66: =L66*(IF(PROFIL!$J$15<>"",PROFIL!$D$10*(1-PROFIL!$J$15),PROFIL!$D$10)) -> 0 | T66: =M66*(IF(PROFIL!$J$15<>"",PROFIL!$D$11*(1-PROFIL!$J$15),PROFIL!$D$11)) -> 0 | U66: =N66*(IF(PROFIL!$J$15<>"",PROFIL!$D$12*(1-PROFIL!$J$15),PROFIL!$D$12)) -> 0
F67: =IF((H67+I67+J67+K67+L67+M67+N67)=0,"-",(H67+I67+J67+K67+L67+M67+N67)) -> - | G67: =IF((O67+P67+Q67+R67+S67+T67+U67)=0,"-",(O67+P67+Q67+R67+S67+T67+U67)) -> - | O67: =H67*(IF(PROFIL!$J$15<>"",PROFIL!$D$6*(1-PROFIL!$J$15),PROFIL!$D$6)) -> 0 | P67: =I67*(IF(PROFIL!$J$15<>"",PROFIL!$D$7*(1-PROFIL!$J$15),PROFIL!$D$7)) -> 0 | Q67: =J67*(IF(PROFIL!$J$15<>"",PROFIL!$D$8*(1-PROFIL!$J$15),PROFIL!$D$8)) -> 0 | R67: =K67*(IF(PROFIL!$J$15<>"",PROFIL!$D$9*(1-PROFIL!$J$15),PROFIL!$D$9)) -> 0 | S67: =L67*(IF(PROFIL!$J$15<>"",PROFIL!$D$10*(1-PROFIL!$J$15),PROFIL!$D$10)) -> 0 | T67: =M67*(IF(PROFIL!$J$15<>"",PROFIL!$D$11*(1-PROFIL!$J$15),PROFIL!$D$11)) -> 0 | U67: =N67*(IF(PROFIL!$J$15<>"",PROFIL!$D$12*(1-PROFIL!$J$15),PROFIL!$D$12)) -> 0
F68: =IF((H68+I68+J68+K68+L68+M68+N68)=0,"-",(H68+I68+J68+K68+L68+M68+N68)) -> - | G68: =IF((O68+P68+Q68+R68+S68+T68+U68)=0,"-",(O68+P68+Q68+R68+S68+T68+U68)) -> - | O68: =H68*(IF(PROFIL!$J$15<>"",PROFIL!$D$6*(1-PROFIL!$J$15),PROFIL!$D$6)) -> 0 | P68: =I68*(IF(PROFIL!$J$15<>"",PROFIL!$D$7*(1-PROFIL!$J$15),PROFIL!$D$7)) -> 0 | Q68: =J68*(IF(PROFIL!$J$15<>"",PROFIL!$D$8*(1-PROFIL!$J$15),PROFIL!$D$8)) -> 0 | R68: =K68*(IF(PROFIL!$J$15<>"",PROFIL!$D$9*(1-PROFIL!$J$15),PROFIL!$D$9)) -> 0 | S68: =L68*(IF(PROFIL!$J$15<>"",PROFIL!$D$10*(1-PROFIL!$J$15),PROFIL!$D$10)) -> 0 | T68: =M68*(IF(PROFIL!$J$15<>"",PROFIL!$D$11*(1-PROFIL!$J$15),PROFIL!$D$11)) -> 0 | U68: =N68*(IF(PROFIL!$J$15<>"",PROFIL!$D$12*(1-PROFIL!$J$15),PROFIL!$D$12)) -> 0
F69: =IF((H69+I69+J69+K69+L69+M69+N69)=0,"-",(H69+I69+J69+K69+L69+M69+N69)) -> - | G69: =IF((O69+P69+Q69+R69+S69+T69+U69)=0,"-",(O69+P69+Q69+R69+S69+T69+U69)) -> - | O69: =H69*(IF(PROFIL!$J$15<>"",PROFIL!$D$6*(1-PROFIL!$J$15),PROFIL!$D$6)) -> 0 | P69: =I69*(IF(PROFIL!$J$15<>"",PROFIL!$D$7*(1-PROFIL!$J$15),PROFIL!$D$7)) -> 0 | Q69: =J69*(IF(PROFIL!$J$15<>"",PROFIL!$D$8*(1-PROFIL!$J$15),PROFIL!$D$8)) -> 0 | R69: =K69*(IF(PROFIL!$J$15<>"",PROFIL!$D$9*(1-PROFIL!$J$15),PROFIL!$D$9)) -> 0 | S69: =L69*(IF(PROFIL!$J$15<>"",PROFIL!$D$10*(1-PROFIL!$J$15),PROFIL!$D$10)) -> 0 | T69: =M69*(IF(PROFIL!$J$15<>"",PROFIL!$D$11*(1-PROFIL!$J$15),PROFIL!$D$11)) -> 0 | U69: =N69*(IF(PROFIL!$J$15<>"",PROFIL!$D$12*(1-PROFIL!$J$15),PROFIL!$D$12)) -> 0
F70: =IF((H70+I70+J70+K70+L70+M70+N70)=0,"-",(H70+I70+J70+K70+L70+M70+N70)) -> - | G70: =IF((O70+P70+Q70+R70+S70+T70+U70)=0,"-",(O70+P70+Q70+R70+S70+T70+U70)) -> - | O70: =H70*(IF(PROFIL!$J$15<>"",PROFIL!$D$6*(1-PROFIL!$J$15),PROFIL!$D$6)) -> 0 | P70: =I70*(IF(PROFIL!$J$15<>"",PROFIL!$D$7*(1-PROFIL!$J$15),PROFIL!$D$7)) -> 0 | Q70: =J70*(IF(PROFIL!$J$15<>"",PROFIL!$D$8*(1-PROFIL!$J$15),PROFIL!$D$8)) -> 0 | R70: =K70*(IF(PROFIL!$J$15<>"",PROFIL!$D$9*(1-PROFIL!$J$15),PROFIL!$D$9)) -> 0 | S70: =L70*(IF(PROFIL!$J$15<>"",PROFIL!$D$10*(1-PROFIL!$J$15),PROFIL!$D$10)) -> 0 | T70: =M70*(IF(PROFIL!$J$15<>"",PROFIL!$D$11*(1-PROFIL!$J$15),PROFIL!$D$11)) -> 0 | U70: =N70*(IF(PROFIL!$J$15<>"",PROFIL!$D$12*(1-PROFIL!$J$15),PROFIL!$D$12)) -> 0
F71: =IF((H71+I71+J71+K71+L71+M71+N71)=0,"-",(H71+I71+J71+K71+L71+M71+N71)) -> - | G71: =IF((O71+P71+Q71+R71+S71+T71+U71)=0,"-",(O71+P71+Q71+R71+S71+T71+U71)) -> - | O71: =H71*(IF(PROFIL!$J$15<>"",PROFIL!$D$6*(1-PROFIL!$J$15),PROFIL!$D$6)) -> 0 | P71: =I71*(IF(PROFIL!$J$15<>"",PROFIL!$D$7*(1-PROFIL!$J$15),PROFIL!$D$7)) -> 0 | Q71: =J71*(IF(PROFIL!$J$15<>"",PROFIL!$D$8*(1-PROFIL!$J$15),PROFIL!$D$8)) -> 0 | R71: =K71*(IF(PROFIL!$J$15<>"",PROFIL!$D$9*(1-PROFIL!$J$15),PROFIL!$D$9)) -> 0 | S71: =L71*(IF(PROFIL!$J$15<>"",PROFIL!$D$10*(1-PROFIL!$J$15),PROFIL!$D$10)) -> 0 | T71: =M71*(IF(PROFIL!$J$15<>"",PROFIL!$D$11*(1-PROFIL!$J$15),PROFIL!$D$11)) -> 0 | U71: =N71*(IF(PROFIL!$J$15<>"",PROFIL!$D$12*(1-PROFIL!$J$15),PROFIL!$D$12)) -> 0
F72: =IF((H72+I72+J72+K72+L72+M72+N72)=0,"-",(H72+I72+J72+K72+L72+M72+N72)) -> - | G72: =IF((O72+P72+Q72+R72+S72+T72+U72)=0,"-",(O72+P72+Q72+R72+S72+T72+U72)) -> - | O72: =H72*(IF(PROFIL!$J$15<>"",PROFIL!$D$6*(1-PROFIL!$J$15),PROFIL!$D$6)) -> 0 | P72: =I72*(IF(PROFIL!$J$15<>"",PROFIL!$D$7*(1-PROFIL!$J$15),PROFIL!$D$7)) -> 0 | Q72: =J72*(IF(PROFIL!$J$15<>"",PROFIL!$D$8*(1-PROFIL!$J$15),PROFIL!$D$8)) -> 0 | R72: =K72*(IF(PROFIL!$J$15<>"",PROFIL!$D$9*(1-PROFIL!$J$15),PROFIL!$D$9)) -> 0 | S72: =L72*(IF(PROFIL!$J$15<>"",PROFIL!$D$10*(1-PROFIL!$J$15),PROFIL!$D$10)) -> 0 | T72: =M72*(IF(PROFIL!$J$15<>"",PROFIL!$D$11*(1-PROFIL!$J$15),PROFIL!$D$11)) -> 0 | U72: =N72*(IF(PROFIL!$J$15<>"",PROFIL!$D$12*(1-PROFIL!$J$15),PROFIL!$D$12)) -> 0
F73: =IF((H73+I73+J73+K73+L73+M73+N73)=0,"-",(H73+I73+J73+K73+L73+M73+N73)) -> - | G73: =IF((O73+P73+Q73+R73+S73+T73+U73)=0,"-",(O73+P73+Q73+R73+S73+T73+U73)) -> - | O73: =H73*(IF(PROFIL!$J$15<>"",PROFIL!$D$6*(1-PROFIL!$J$15),PROFIL!$D$6)) -> 0 | P73: =I73*(IF(PROFIL!$J$15<>"",PROFIL!$D$7*(1-PROFIL!$J$15),PROFIL!$D$7)) -> 0 | Q73: =J73*(IF(PROFIL!$J$15<>"",PROFIL!$D$8*(1-PROFIL!$J$15),PROFIL!$D$8)) -> 0 | R73: =K73*(IF(PROFIL!$J$15<>"",PROFIL!$D$9*(1-PROFIL!$J$15),PROFIL!$D$9)) -> 0 | S73: =L73*(IF(PROFIL!$J$15<>"",PROFIL!$D$10*(1-PROFIL!$J$15),PROFIL!$D$10)) -> 0 | T73: =M73*(IF(PROFIL!$J$15<>"",PROFIL!$D$11*(1-PROFIL!$J$15),PROFIL!$D$11)) -> 0 | U73: =N73*(IF(PROFIL!$J$15<>"",PROFIL!$D$12*(1-PROFIL!$J$15),PROFIL!$D$12)) -> 0
F74: =IF((H74+I74+J74+K74+L74+M74+N74)=0,"-",(H74+I74+J74+K74+L74+M74+N74)) -> - | G74: =IF((O74+P74+Q74+R74+S74+T74+U74)=0,"-",(O74+P74+Q74+R74+S74+T74+U74)) -> - | O74: =H74*(IF(PROFIL!$J$15<>"",PROFIL!$D$6*(1-PROFIL!$J$15),PROFIL!$D$6)) -> 0 | P74: =I74*(IF(PROFIL!$J$15<>"",PROFIL!$D$7*(1-PROFIL!$J$15),PROFIL!$D$7)) -> 0 | Q74: =J74*(IF(PROFIL!$J$15<>"",PROFIL!$D$8*(1-PROFIL!$J$15),PROFIL!$D$8)) -> 0 | R74: =K74*(IF(PROFIL!$J$15<>"",PROFIL!$D$9*(1-PROFIL!$J$15),PROFIL!$D$9)) -> 0 | S74: =L74*(IF(PROFIL!$J$15<>"",PROFIL!$D$10*(1-PROFIL!$J$15),PROFIL!$D$10)) -> 0 | T74: =M74*(IF(PROFIL!$J$15<>"",PROFIL!$D$11*(1-PROFIL!$J$15),PROFIL!$D$11)) -> 0 | U74: =N74*(IF(PROFIL!$J$15<>"",PROFIL!$D$12*(1-PROFIL!$J$15),PROFIL!$D$12)) -> 0
F75: =IF((H75+I75+J75+K75+L75+M75+N75)=0,"-",(H75+I75+J75+K75+L75+M75+N75)) -> - | G75: =IF((O75+P75+Q75+R75+S75+T75+U75)=0,"-",(O75+P75+Q75+R75+S75+T75+U75)) -> - | O75: =H75*(IF(PROFIL!$J$15<>"",PROFIL!$D$6*(1-PROFIL!$J$15),PROFIL!$D$6)) -> 0 | P75: =I75*(IF(PROFIL!$J$15<>"",PROFIL!$D$7*(1-PROFIL!$J$15),PROFIL!$D$7)) -> 0 | Q75: =J75*(IF(PROFIL!$J$15<>"",PROFIL!$D$8*(1-PROFIL!$J$15),PROFIL!$D$8)) -> 0 | R75: =K75*(IF(PROFIL!$J$15<>"",PROFIL!$D$9*(1-PROFIL!$J$15),PROFIL!$D$9)) -> 0 | S75: =L75*(IF(PROFIL!$J$15<>"",PROFIL!$D$10*(1-PROFIL!$J$15),PROFIL!$D$10)) -> 0 | T75: =M75*(IF(PROFIL!$J$15<>"",PROFIL!$D$11*(1-PROFIL!$J$15),PROFIL!$D$11)) -> 0 | U75: =N75*(IF(PROFIL!$J$15<>"",PROFIL!$D$12*(1-PROFIL!$J$15),PROFIL!$D$12)) -> 0
... F95: =IF((H95+I95+J95+K95+L95+M95+N95)=0,"-",(H95+I95+J95+K95+L95+M95+N95)) -> - | G95: =IF((O95+P95+Q95+R95+S95+T95+U95)=0,"-",(O95+P95+Q95+R95+S95+T95+U95)) -> - | O95: =H95*(IF(PROFIL!$J$15<>"",PROFIL!$D$6*(1-PROFIL!$J$15),PROFIL!$D$6)) -> 0 | P95: =I95*(IF(PROFIL!$J$15<>"",PROFIL!$D$7*(1-PROFIL!$J$15),PROFIL!$D$7)) -> 0 | Q95: =J95*(IF(PROFIL!$J$15<>"",PROFIL!$D$8*(1-PROFIL!$J$15),PROFIL!$D$8)) -> 0 | R95: =K95*(IF(PROFIL!$J$15<>"",PROFIL!$D$9*(1-PROFIL!$J$15),PROFIL!$D$9)) -> 0 | S95: =L95*(IF(PROFIL!$J$15<>"",PROFIL!$D$10*(1-PROFIL!$J$15),PROFIL!$D$10)) -> 0 | T95: =M95*(IF(PROFIL!$J$15<>"",PROFIL!$D$11*(1-PROFIL!$J$15),PROFIL!$D$11)) -> 0 | U95: =N95*(IF(PROFIL!$J$15<>"",PROFIL!$D$12*(1-PROFIL!$J$15),PROFIL!$D$12)) -> 0
F96: =SUBTOTAL(9,F5:F95) -> 104 | G96: =SUBTOTAL(9,G5:G95) -> 77425 | H96: =SUBTOTAL(9,H5:H95) -> 21.5 | I96: =SUBTOTAL(9,I5:I95) -> 10.5 | J96: =SUBTOTAL(9,J5:J95) -> 29.5 | K96: =SUBTOTAL(9,K5:K95) -> 37.5 | L96: =SUBTOTAL(9,L5:L95) -> 5 | M96: =SUBTOTAL(9,M5:M95) -> 0 | ... U96: =SUBTOTAL(9,U5:U95) -> 0

Sheet METRIQUE
B1: Métrique
B4: Etape | C4: % Théorique | D4: Charge Théorique | E4: Charge Propale | F4: % Projet | H4: Ecart (%) Projet /Théorique
B5: Pilotage projet | C5: 0.2 | D5: =$D$10*C5 -> 1.5 | E5: =SUMIF(WORKLOAD!$D$5:$D$95,B5,WORKLOAD!$F$5:$F$95) -> 22 | F5: =IFERROR(E5/$E$10,"") -> 2.9333333 | H5: =IFERROR(F5-C5,"") -> 2.7333333
B6: Conception générale | C6: 0.05 | D6: =$D$10*C6 -> 0.375 | E6: =SUMIF(WORKLOAD!$D$5:$D$95,B6,WORKLOAD!$F$5:$F$95) -> 1.5 | F6: =IFERROR(E6/$E$10,"") -> 0.2 | H6: =IFERROR(F6-C6,"") -> 0.15
B7: Conception fonctionnelle détaillée | C7: 0.25 | D7: =$D$10*C7 -> 1.875 | E7: =SUMIF(WORKLOAD!$D$5:$D$95,B7,WORKLOAD!$F$5:$F$95) -> 4 | F7: =IFERROR(E7/$E$10,"") -> 0.53333333 | H7: =IFERROR(F7-C7,"") -> 0.28333333
B8: Conception technique détaillée | C8: 0.2 | D8: =$D$10*C8 -> 1.5 | E8: =SUMIF(WORKLOAD!$D$5:$D$95,B8,WORKLOAD!$F$5:$F$95) -> 0 | F8: =IFERROR(E8/$E$10,"") -> 0 | H8: =IFERROR(F8-C8,"") -> -0.2
B9: Cahier de recette | C9: 0.15 | D9: =$D$10*C9 -> 1.125 | E9: =SUMIF(WORKLOAD!$D$5:$D$95,B9,WORKLOAD!$F$5:$F$95) -> 0 | F9: =IFERROR(E9/$E$10,"") -> 0 | H9: =IFERROR(F9-C9,"") -> -0.15
B10: Développement et tests unitaires | C10: 1 | D10: =E10 -> 7.5 | E10: =SUMIF(WORKLOAD!$D$5:$D$95,B10,WORKLOAD!$F$5:$F$95) -> 7.5 | F10: 1 | H10: =F10-C10 -> 0
B11: Tests d'intégration / Recette interne | C11: 0.2 | D11: =$D$10*C11 -> 1.5 | E11: =SUMIF(WORKLOAD!$D$5:$D$95,B11,WORKLOAD!$F$5:$F$95) -> 0 | F11: =IFERROR(E11/$E$10,"") -> 0 | H11: =IFERROR(F11-C11,"") -> -0.2
B12: Livraison / installation / Mise en œuvre | C12: 0.1 | D12: =$D$10*C12 -> 0.75 | E12: =SUMIF(WORKLOAD!$D$5:$D$95,B12,WORKLOAD!$F$5:$F$95) -> 6 | F12: =IFERROR(E12/$E$10,"") -> 0.8 | H12: =IFERROR(F12-C12,"") -> 0.7
B13: Assistance recette | C13: 0.1 | D13: =$D$10*C13 -> 0.75 | E13: =SUMIF(WORKLOAD!$D$5:$D$95,B13,WORKLOAD!$F$5:$F$95) -> 0 | F13: =IFERROR(E13/$E$10,"") -> 0 | H13: =IFERROR(F13-C13,"") -> -0.1
B14: Garantie (suite recette - 3 mois) | C14: 0.06 | D14: =$D$10*C14 -> 0.45 | E14: =SUMIF(WORKLOAD!$D$5:$D$95,B14,WORKLOAD!$F$5:$F$95) -> 0 | F14: =IFERROR(E14/$E$10,"") -> 0 | H14: =IFERROR(F14-C14,"") -> -0.06
B16: TOTAL | C16: =SUM(C5:C14) -> 2.31 | D16: =SUM(D5:D14) -> 17.325 | E16: =SUM(E5:E14) -> 41 | F16: =SUM(F5:F14) -> 5.4666667

Sheet ECHEANCIER
B1: Echéancier
B3: Echéancier | H3: Vision FAE
B4: N° | C4: Nom Échéance | D4: % | E4: Mois Facturation | F4: Montant à Facturation | H4: Cout Engagé Cumulé | I4: Montant Facturé Cumulé | J4: Montant FAE (€) | K4: Montant FAE (%)
B5: 1 | C5: Commande | D5: 0.2 | F5: =D5*SYNTHESE!$D$8 -> 15485 | H5: =IF(E5<>"",HLOOKUP(E5,PLANNING!$F$4:$U$14,11,FALSE),"") | I5: =IF(E5<>"",F5,"") | J5: =IF(E5<>"",H5-I5,"") | K5: =IF(E5<>"",(-J5/$F$13),"")
B6: 2 | C6: Rédaction DAT | D6: 0.3 | F6: =D6*SYNTHESE!$D$8 -> 23227.5 | H6: =IF(E6<>"",HLOOKUP(E6,PLANNING!$F$4:$U$14,11,FALSE),"") | I6: =IF(E6<>"",F6+I5,"") | J6: =IF(E6<>"",H6-I6,"") | K6: =IF(E6<>"",(-J6/$F$13),"")
B7: 3 | C7: Recette | D7: 0.28 | F7: =D7*SYNTHESE!$D$8 -> 21679 | H7: =IF(E7<>"",HLOOKUP(E7,PLANNING!$F$4:$U$14,11,FALSE),"") | I7: =IF(E7<>"",F7+I6,"") | J7: =IF(E7<>"",H7-I7,"") | K7: =IF(E7<>"",(-J7/$F$13),"")
B8: 4 | C8: 15 sites majeurs accompagnés (PV) | D8: 0.22 | F8: =D8*SYNTHESE!$D$8 -> 17033.5 | H8: =IF(E8<>"",HLOOKUP(E8,PLANNING!$F$4:$U$14,11,FALSE),"") | I8: =IF(E8<>"",F8+I7,"") | J8: =IF(E8<>"",H8-I8,"") | K8: =IF(E8<>"",(-J8/H8),"")
B9: 5 | F9: =D9*SYNTHESE!$D$8 -> 0 | H9: =IF(E9<>"",HLOOKUP(E9,PLANNING!$F$4:$U$14,11,FALSE),"") | I9: =IF(E9<>"",F9+I8,"") | J9: =IF(E9<>"",H9-I9,"") | K9: =IF(E9<>"",(-J9/H9),"")
B10: 6 | F10: =D10*SYNTHESE!$D$8 -> 0 | H10: =IF(E10<>"",HLOOKUP(E10,PLANNING!$F$4:$U$14,11,FALSE),"") | I10: =IF(E10<>"",F10+I9,"") | J10: =IF(E10<>"",H10-I10,"") | K10: =IF(E10<>"",(-J10/H10),"")
B11: 7 | F11: =D11*SYNTHESE!$D$8 -> 0 | H11: =IF(E11<>"",HLOOKUP(E11,PLANNING!$F$4:$U$14,11,FALSE),"") | I11: =IF(E11<>"",F11+I10,"") | J11: =IF(E11<>"",H11-I11,"") | K11: =IF(E11<>"",(-J11/H11),"")
B12: 8 | F12: =D12*SYNTHESE!$D$8 -> 0 | H12: =IF(E12<>"",HLOOKUP(E12,PLANNING!$F$4:$U$14,11,FALSE),"") | I12: =IF(E12<>"",F12+I11,"") | J12: =IF(E12<>"",H12-I12,"") | K12: =IF(E12<>"",(-J12/H12),"")
E13: TOTAL | F13: =SUBTOTAL(9,F5:F12) -> 77425

Sheet PLANNING
B1: Planning
B4: Profil | C4: Charge par profil | D4: CJM | E4: Ecart ? | F4: =REF!H5 -> 45292 | G4: =REF!H6 -> 45323 | H4: =REF!H7 -> 45352 | I4: =REF!H8 -> 45383 | J4: =REF!H9 -> 45413 | K4: =REF!H10 -> 45444 | L4: =REF!H11 -> 45474 | M4: =REF!H12 -> 45505 | N4: =REF!H13 -> 45536 | O4: =REF!H14 -> 45566 | P4: =REF!H15 -> 45597 | Q4: =REF!H16 -> 45627 | R4: =REF!H17 -> 45658 | S4: =REF!H18 -> 45689 | T4: =REF!H19 -> 45717 | U4: =REF!H20 -> 45748
B5: =PROFIL!B6 -> Chef de Projet | C5: =PROFIL!I6 -> 21.5 | D5: =IF(PROFIL!$J$15<>"",PROFIL!D6*(1-PROFIL!$J$15),PROFIL!D6) -> 750 | E5: =SUM(F5:U5)-C5 -> -21.5
B6: =PROFIL!B7 -> Architecte | C6: =PROFIL!I7 -> 10.5 | D6: =IF(PROFIL!$J$15<>"",PROFIL!D7*(1-PROFIL!$J$15),PROFIL!D7) -> 850 | E6: =SUM(F6:U6)-C6 -> -10.5
B7: =PROFIL!B8 -> Consultant Technique | C7: =PROFIL!I8 -> 29.5 | D7: =IF(PROFIL!$J$15<>"",PROFIL!D8*(1-PROFIL!$J$15),PROFIL!D8) -> 750 | E7: =SUM(F7:U7)-C7 -> -29.5
B8: =PROFIL!B9 -> Consultant Change | C8: =PROFIL!I9 -> 37.5 | D8: =IF(PROFIL!$J$15<>"",PROFIL!D9*(1-PROFIL!$J$15),PROFIL!D9) -> 700 | E8: =SUM(F8:U8)-C8 -> -37.5
B9: =PROFIL!B10 -> Consultant Data | C9: =PROFIL!I10 -> 5 | D9: =IF(PROFIL!$J$15<>"",PROFIL!D10*(1-PROFIL!$J$15),PROFIL!D10) -> 800 | E9: =SUM(F9:U9)-C9 -> -5
B10: =PROFIL!B11 -> 0 | C10: =PROFIL!I11 -> 0 | D10: =IF(PROFIL!$J$15<>"",PROFIL!D11*(1-PROFIL!$J$15),PROFIL!D11) -> 0 | E10: =SUM(F10:U10)-C10 -> 0
B11: =PROFIL!B12 -> 0 | C11: =PROFIL!I12 -> 0 | D11: =IF(PROFIL!$J$15<>"",PROFIL!D12*(1-PROFIL!$J$15),PROFIL!D12) -> 0 | E11: =SUM(F11:U11)-C11 -> 0
B12: TOTAL JH | C12: =PROFIL!I13 -> 104 | E12: =SUM(F12:U12)-C12 -> -104 | F12: =IF(SUM(F5:F11)<>0,SUM(F5:F11),"") | G12: =IF(SUM(G5:G11)<>0,SUM(G5:G11),"") | H12: =IF(SUM(H5:H11)<>0,SUM(H5:H11),"") | I12: =IF(SUM(I5:I11)<>0,SUM(I5:I11),"") | J12: =IF(SUM(J5:J11)<>0,SUM(J5:J11),"") | K12: =IF(SUM(K5:K11)<>0,SUM(K5:K11),"") | L12: =IF(SUM(L5:L11)<>0,SUM(L5:L11),"") | M12: =IF(SUM(M5:M11)<>0,SUM(M5:M11),"") | ... U12: =IF(SUM(U5:U11)<>0,SUM(U5:U11),"")
B13: COUT MENSUEL | F13: =F5*$D$5+F6*$D$6+F7*$D$7+F8*$D$8+F9*$D$9+F10*$D$10+F11*$D$11 -> 0 | G13: =G5*$D$5+G6*$D$6+G7*$D$7+G8*$D$8+G9*$D$9+G10*$D$10+G11*$D$11 -> 0 | H13: =H5*$D$5+H6*$D$6+H7*$D$7+H8*$D$8+H9*$D$9+H10*$D$10+H11*$D$11 -> 0 | I13: =I5*$D$5+I6*$D$6+I7*$D$7+I8*$D$8+I9*$D$9+I10*$D$10+I11*$D$11 -> 0 | J13: =J5*$D$5+J6*$D$6+J7*$D$7+J8*$D$8+J9*$D$9+J10*$D$10+J11*$D$11 -> 0 | K13: =K5*$D$5+K6*$D$6+K7*$D$7+K8*$D$8+K9*$D$9+K10*$D$10+K11*$D$11 -> 0 | L13: =L5*$D$5+L6*$D$6+L7*$D$7+L8*$D$8+L9*$D$9+L10*$D$10+L11*$D$11 -> 0 | M13: =M5*$D$5+M6*$D$6+M7*$D$7+M8*$D$8+M9*$D$9+M10*$D$10+M11*$D$11 -> 0 | ... U13: =U5*$D$5+U6*$D$6+U7*$D$7+U8*$D$8+U9*$D$9+U10*$D$10+U11*$D$11 -> 0
B14: COUT MENSUEL CUMULE | F14: =F13 -> 0 | G14: =G13+F14 -> 0 | H14: =H13+G14 -> 0 | I14: =I13+H14 -> 0 | J14: =J13+I14 -> 0 | K14: =K13+J14 -> 0 | L14: =L13+K14 -> 0 | M14: =M13+L14 -> 0 | N14: =N13+M14 -> 0 | ... U14: =U13+T14 -> 0
B18: Phases | C18: Charge par phase | D18: CJM | E18: Ecart ? | F18: =F4 -> 45292 | G18: =G4 -> 45323 | H18: =H4 -> 45352 | I18: =I4 -> 45383 | J18: =J4 -> 45413 | K18: =K4 -> 45444 | L18: =L4 -> 45474 | M18: =M4 -> 45505 | ... U18: =U4 -> 45748
B19: =REF!B5 -> PILOTAGE | C19: ='VENTILATION CHARGE'!K7 -> 22 | D19: 588.33333 | E19: =IFERROR(SUM(F19:U19)-C19,0) -> -22
B20: =REF!B6 -> CONCEPTION | C20: ='VENTILATION CHARGE'!K8 -> 8.5 | D20: 641.66667 | E20: =IFERROR(SUM(F20:U20)-C20,0) -> -8.5
B21: =REF!B7 -> CONSTRUCTION | C21: ='VENTILATION CHARGE'!K9 -> 7.5 | D21: 501.66667 | E21: =IFERROR(SUM(F21:U21)-C21,0) -> -7.5
B22: =REF!B8 -> VALIDATION | C22: ='VENTILATION CHARGE'!K10 -> 56 | D22: 435 | E22: =IFERROR(SUM(F22:U22)-C22,0) -> -56
B23: =REF!B9 -> FINALISATION | C23: ='VENTILATION CHARGE'!K11 -> 6 | D23: 0 | E23: =IFERROR(SUM(F23:U23)-C23,0) -> -6
B24: =REF!B10 -> GARANTIE | C24: ='VENTILATION CHARGE'!K12 | D24: 0 | E24: =IFERROR(SUM(F24:U24)-C24,0) -> 0
B25: =REF!B11 -> TMA | C25: ='VENTILATION CHARGE'!K13 | D25: 0 | E25: =IFERROR(SUM(F25:U25)-C25,0) -> 0
B26: =REF!B12 -> PROVISION | C26: ='VENTILATION CHARGE'!K14 -> 4 | D26: TJM CSV | E26: =IFERROR(SUM(F26:U26)-C26,0) -> -4
B27: TOTAL JH | C27: =SUM(C19:C26) -> 104 | E27: =SUM(E19:E26) -> -104 | F27: =IF(SUM(F19:F26)<>0,SUM(F19:F26),"") | G27: =IF(SUM(G19:G26)<>0,SUM(G19:G26),"") | H27: =IF(SUM(H19:H26)<>0,SUM(H19:H26),"") | I27: =IF(SUM(I19:I26)<>0,SUM(I19:I26),"") | J27: =IF(SUM(J19:J26)<>0,SUM(J19:J26),"") | K27: =IF(SUM(K19:K26)<>0,SUM(K19:K26),"") | L27: =IF(SUM(L19:L26)<>0,SUM(L19:L26),"") | M27: =IF(SUM(M19:M26)<>0,SUM(M19:M26),"") | ... U27: =IF(SUM(U19:U26)<>0,SUM(U19:U26),"")

Sheet VENTILATION CHARGE
B1: Ventilation des charges
B3: Ventilation des charges par phase
B6: PHASE | C6: =WORKLOAD!H4 -> Chef de Projet | D6: =WORKLOAD!I4 -> Architecte | E6: =WORKLOAD!J4 -> Consultant Technique | F6: =WORKLOAD!K4 -> Consultant Change | G6: =WORKLOAD!L4 -> Consultant Data | H6: =WORKLOAD!M4 -> 0 | I6: =WORKLOAD!N4 -> 0 | K6: Total | M6: TJM
B7: =REF!B5 -> PILOTAGE | C7: =IF(SUMIF(WORKLOAD!$C$4:$C$100,'VENTILATION CHARGE'!B7,WORKLOAD!$H$4:$H$100)<>0,SUMIF(WORKLOAD!$C$4:$C$100,'VENTILATION CHARGE'!B7,WORKLOAD!$H$4:$H$100),"") -> 20.5 | D7: =IF(SUMIF(WORKLOAD!$C$4:$C$100,'VENTILATION CHARGE'!B7,WORKLOAD!$I$4:$I$100)<>0,SUMIF(WORKLOAD!$C$4:$C$100,'VENTILATION CHARGE'!B7,WORKLOAD!$I$4:$I$100),"") -> 0.5 | E7: =IF(SUMIF(WORKLOAD!$C$4:$C$100,'VENTILATION CHARGE'!B7,WORKLOAD!$J$4:$J$100)<>0,SUMIF(WORKLOAD!$C$4:$C$100,'VENTILATION CHARGE'!B7,WORKLOAD!$J$4:$J$100),"") | F7: =IF(SUMIF(WORKLOAD!$C$4:$C$100,'VENTILATION CHARGE'!B7,WORKLOAD!$K$4:$K$100)<>0,SUMIF(WORKLOAD!$C$4:$C$100,'VENTILATION CHARGE'!B7,WORKLOAD!$K$4:$K$100),"") -> 1 | G7: =IF(SUMIF(WORKLOAD!$C$4:$C$100,'VENTILATION CHARGE'!B7,WORKLOAD!$L$4:$L$100)<>0,SUMIF(WORKLOAD!$C$4:$C$100,'VENTILATION CHARGE'!B7,WORKLOAD!$L$4:$L$100),"") | H7: =IF(SUMIF(WORKLOAD!$C$4:$C$100,'VENTILATION CHARGE'!B7,WORKLOAD!$M$4:$M$100)<>0,SUMIF(WORKLOAD!$C$4:$C$100,'VENTILATION CHARGE'!B7,WORKLOAD!$M$4:$M$100),"") | I7: =IF(SUMIF(WORKLOAD!$C$4:$C$100,'VENTILATION CHARGE'!B7,WORKLOAD!$N$4:$N$100)<>0,SUMIF(WORKLOAD!$C$4:$C$100,'VENTILATION CHARGE'!B7,WORKLOAD!$N$4:$N$100),"") | K7: =IF(SUM(C7:I7)<>0,SUM(C7:I7),"") -> 22 | M7: =IFERROR(K48/K7,"") -> 750
B8: =REF!B6 -> CONCEPTION | C8: =IF(SUMIF(WORKLOAD!$C$4:$C$100,'VENTILATION CHARGE'!B8,WORKLOAD!$H$4:$H$100)<>0,SUMIF(WORKLOAD!$C$4:$C$100,'VENTILATION CHARGE'!B8,WORKLOAD!$H$4:$H$100),"") | D8: =IF(SUMIF(WORKLOAD!$C$4:$C$100,'VENTILATION CHARGE'!B8,WORKLOAD!$I$4:$I$100)<>0,SUMIF(WORKLOAD!$C$4:$C$100,'VENTILATION CHARGE'!B8,WORKLOAD!$I$4:$I$100),"") -> 7 | E8: =IF(SUMIF(WORKLOAD!$C$4:$C$100,'VENTILATION CHARGE'!B8,WORKLOAD!$J$4:$J$100)<>0,SUMIF(WORKLOAD!$C$4:$C$100,'VENTILATION CHARGE'!B8,WORKLOAD!$J$4:$J$100),"") -> 1.5 | F8: =IF(SUMIF(WORKLOAD!$C$4:$C$100,'VENTILATION CHARGE'!B8,WORKLOAD!$K$4:$K$100)<>0,SUMIF(WORKLOAD!$C$4:$C$100,'VENTILATION CHARGE'!B8,WORKLOAD!$K$4:$K$100),"") | G8: =IF(SUMIF(WORKLOAD!$C$4:$C$100,'VENTILATION CHARGE'!B8,WORKLOAD!$L$4:$L$100)<>0,SUMIF(WORKLOAD!$C$4:$C$100,'VENTILATION CHARGE'!B8,WORKLOAD!$L$4:$L$100),"") | H8: =IF(SUMIF(WORKLOAD!$C$4:$C$100,'VENTILATION CHARGE'!B8,WORKLOAD!$M$4:$M$100)<>0,SUMIF(WORKLOAD!$C$4:$C$100,'VENTILATION CHARGE'!B8,WORKLOAD!$M$4:$M$100),"") | I8: =IF(SUMIF(WORKLOAD!$C$4:$C$100,'VENTILATION CHARGE'!B8,WORKLOAD!$N$4:$N$100)<>0,SUMIF(WORKLOAD!$C$4:$C$100,'VENTILATION CHARGE'!B8,WORKLOAD!$N$4:$N$100),"") | K8: =IF(SUM(C8:I8)<>0,SUM(C8:I8),"") -> 8.5 | M8: =IFERROR(K49/K8,"") -> 832.35294
B9: =REF!B7 -> CONSTRUCTION | C9: =IF(SUMIF(WORKLOAD!$C$4:$C$100,'VENTILATION CHARGE'!B9,WORKLOAD!$H$4:$H$100)<>0,SUMIF(WORKLOAD!$C$4:$C$100,'VENTILATION CHARGE'!B9,WORKLOAD!$H$4:$H$100),"") | D9: =IF(SUMIF(WORKLOAD!$C$4:$C$100,'VENTILATION CHARGE'!B9,WORKLOAD!$I$4:$I$100)<>0,SUMIF(WORKLOAD!$C$4:$C$100,'VENTILATION CHARGE'!B9,WORKLOAD!$I$4:$I$100),"") | E9: =IF(SUMIF(WORKLOAD!$C$4:$C$100,'VENTILATION CHARGE'!B9,WORKLOAD!$J$4:$J$100)<>0,SUMIF(WORKLOAD!$C$4:$C$100,'VENTILATION CHARGE'!B9,WORKLOAD!$J$4:$J$100),"") -> 7.5 | F9: =IF(SUMIF(WORKLOAD!$C$4:$C$100,'VENTILATION CHARGE'!B9,WORKLOAD!$K$4:$K$100)<>0,SUMIF(WORKLOAD!$C$4:$C$100,'VENTILATION CHARGE'!B9,WORKLOAD!$K$4:$K$100),"") | G9: =IF(SUMIF(WORKLOAD!$C$4:$C$100,'VENTILATION CHARGE'!B9,WORKLOAD!$L$4:$L$100)<>0,SUMIF(WORKLOAD!$C$4:$C$100,'VENTILATION CHARGE'!B9,WORKLOAD!$L$4:$L$100),"") | H9: =IF(SUMIF(WORKLOAD!$C$4:$C$100,'VENTILATION CHARGE'!B9,WORKLOAD!$M$4:$M$100)<>0,SUMIF(WORKLOAD!$C$4:$C$100,'VENTILATION CHARGE'!B9,WORKLOAD!$M$4:$M$100),"") | I9: =IF(SUMIF(WORKLOAD!$C$4:$C$100,'VENTILATION CHARGE'!B9,WORKLOAD!$N$4:$N$100)<>0,SUMIF(WORKLOAD!$C$4:$C$100,'VENTILATION CHARGE'!B9,WORKLOAD!$N$4:$N$100),"") | K9: =IF(SUM(C9:I9)<>0,SUM(C9:I9),"") -> 7.5 | M9: =IFERROR(K50/K9,"") -> 750
B10: =REF!B8 -> VALIDATION | C10: =IF(SUMIF(WORKLOAD!$C$4:$C$100,'VENTILATION CHARGE'!B10,WORKLOAD!$H$4:$H$100)<>0,SUMIF(WORKLOAD!$C$4:$C$100,'VENTILATION CHARGE'!B10,WORKLOAD!$H$4:$H$100),"") -> 0.5 | D10: =IF(SUMIF(WORKLOAD!$C$4:$C$100,'VENTILATION CHARGE'!B10,WORKLOAD!$I$4:$I$100)<>0,SUMIF(WORKLOAD!$C$4:$C$100,'VENTILATION CHARGE'!B10,WORKLOAD!$I$4:$I$100),"") | E10: =IF(SUMIF(WORKLOAD!$C$4:$C$100,'VENTILATION CHARGE'!B10,WORKLOAD!$J$4:$J$100)<>0,SUMIF(WORKLOAD!$C$4:$C$100,'VENTILATION CHARGE'!B10,WORKLOAD!$J$4:$J$100),"") -> 16.5 | F10: =IF(SUMIF(WORKLOAD!$C$4:$C$100,'VENTILATION CHARGE'!B10,WORKLOAD!$K$4:$K$100)<>0,SUMIF(WORKLOAD!$C$4:$C$100,'VENTILATION CHARGE'!B10,WORKLOAD!$K$4:$K$100),"") -> 34 | G10: =IF(SUMIF(WORKLOAD!$C$4:$C$100,'VENTILATION CHARGE'!B10,WORKLOAD!$L$4:$L$100)<>0,SUMIF(WORKLOAD!$C$4:$C$100,'VENTILATION CHARGE'!B10,WORKLOAD!$L$4:$L$100),"") -> 5 | H10: =IF(SUMIF(WORKLOAD!$C$4:$C$100,'VENTILATION CHARGE'!B10,WORKLOAD!$M$4:$M$100)<>0,SUMIF(WORKLOAD!$C$4:$C$100,'VENTILATION CHARGE'!B10,WORKLOAD!$M$4:$M$100),"") | I10: =IF(SUMIF(WORKLOAD!$C$4:$C$100,'VENTILATION CHARGE'!B10,WORKLOAD!$N$4:$N$100)<>0,SUMIF(WORKLOAD!$C$4:$C$100,'VENTILATION CHARGE'!B10,WORKLOAD!$N$4:$N$100),"") | K10: =IF(SUM(C10:I10)<>0,SUM(C10:I10),"") -> 56 | M10: =IFERROR(K51/K10,"") -> 724.10714
B11: =REF!B9 -> FINALISATION | C11: =IF(SUMIF(WORKLOAD!$C$4:$C$100,'VENTILATION CHARGE'!B11,WORKLOAD!$H$4:$H$100)<>0,SUMIF(WORKLOAD!$C$4:$C$100,'VENTILATION CHARGE'!B11,WORKLOAD!$H$4:$H$100),"") | D11: =IF(SUMIF(WORKLOAD!$C$4:$C$100,'VENTILATION CHARGE'!B11,WORKLOAD!$I$4:$I$100)<>0,SUMIF(WORKLOAD!$C$4:$C$100,'VENTILATION CHARGE'!B11,WORKLOAD!$I$4:$I$100),"") -> 2 | E11: =IF(SUMIF(WORKLOAD!$C$4:$C$100,'VENTILATION CHARGE'!B11,WORKLOAD!$J$4:$J$100)<>0,SUMIF(WORKLOAD!$C$4:$C$100,'VENTILATION CHARGE'!B11,WORKLOAD!$J$4:$J$100),"") -> 3 | F11: =IF(SUMIF(WORKLOAD!$C$4:$C$100,'VENTILATION CHARGE'!B11,WORKLOAD!$K$4:$K$100)<>0,SUMIF(WORKLOAD!$C$4:$C$100,'VENTILATION CHARGE'!B11,WORKLOAD!$K$4:$K$100),"") -> 1 | G11: =IF(SUMIF(WORKLOAD!$C$4:$C$100,'VENTILATION CHARGE'!B11,WORKLOAD!$L$4:$L$100)<>0,SUMIF(WORKLOAD!$C$4:$C$100,'VENTILATION CHARGE'!B11,WORKLOAD!$L$4:$L$100),"") | H11: =IF(SUMIF(WORKLOAD!$C$4:$C$100,'VENTILATION CHARGE'!B11,WORKLOAD!$M$4:$M$100)<>0,SUMIF(WORKLOAD!$C$4:$C$100,'VENTILATION CHARGE'!B11,WORKLOAD!$M$4:$M$100),"") | I11: =IF(SUMIF(WORKLOAD!$C$4:$C$100,'VENTILATION CHARGE'!B11,WORKLOAD!$N$4:$N$100)<>0,SUMIF(WORKLOAD!$C$4:$C$100,'VENTILATION CHARGE'!B11,WORKLOAD!$N$4:$N$100),"") | K11: =IF(SUM(C11:I11)<>0,SUM(C11:I11),"") -> 6 | M11: =IFERROR(K52/K11,"") -> 775
B12: =REF!B10 -> GARANTIE | C12: =IF(SUMIF(WORKLOAD!$C$4:$C$100,'VENTILATION CHARGE'!B12,WORKLOAD!$H$4:$H$100)<>0,SUMIF(WORKLOAD!$C$4:$C$100,'VENTILATION CHARGE'!B12,WORKLOAD!$H$4:$H$100),"") | D12: =IF(SUMIF(WORKLOAD!$C$4:$C$100,'VENTILATION CHARGE'!B12,WORKLOAD!$I$4:$I$100)<>0,SUMIF(WORKLOAD!$C$4:$C$100,'VENTILATION CHARGE'!B12,WORKLOAD!$I$4:$I$100),"") | E12: =IF(SUMIF(WORKLOAD!$C$4:$C$100,'VENTILATION CHARGE'!B12,WORKLOAD!$J$4:$J$100)<>0,SUMIF(WORKLOAD!$C$4:$C$100,'VENTILATION CHARGE'!B12,WORKLOAD!$J$4:$J$100),"") | F12: =IF(SUMIF(WORKLOAD!$C$4:$C$100,'VENTILATION CHARGE'!B12,WORKLOAD!$K$4:$K$100)<>0,SUMIF(WORKLOAD!$C$4:$C$100,'VENTILATION CHARGE'!B12,WORKLOAD!$K$4:$K$100),"") | G12: =IF(SUMIF(WORKLOAD!$C$4:$C$100,'VENTILATION CHARGE'!B12,WORKLOAD!$L$4:$L$100)<>0,SUMIF(WORKLOAD!$C$4:$C$100,'VENTILATION CHARGE'!B12,WORKLOAD!$L$4:$L$100),"") | H12: =IF(SUMIF(WORKLOAD!$C$4:$C$100,'VENTILATION CHARGE'!B12,WORKLOAD!$M$4:$M$100)<>0,SUMIF(WORKLOAD!$C$4:$C$100,'VENTILATION CHARGE'!B12,WORKLOAD!$M$4:$M$100),"") | I12: =IF(SUMIF(WORKLOAD!$C$4:$C$100,'VENTILATION CHARGE'!B12,WORKLOAD!$N$4:$N$100)<>0,SUMIF(WORKLOAD!$C$4:$C$100,'VENTILATION CHARGE'!B12,WORKLOAD!$N$4:$N$100),"") | K12: =IF(SUM(C12:I12)<>0,SUM(C12:I12),"") | M12: =IFERROR(K52/K12,"")
B13: =REF!B11 -> TMA | C13: =IF(SUMIF(WORKLOAD!$C$4:$C$100,'VENTILATION CHARGE'!B13,WORKLOAD!$H$4:$H$100)<>0,SUMIF(WORKLOAD!$C$4:$C$100,'VENTILATION CHARGE'!B13,WORKLOAD!$H$4:$H$100),"") | D13: =IF(SUMIF(WORKLOAD!$C$4:$C$100,'VENTILATION CHARGE'!B13,WORKLOAD!$I$4:$I$100)<>0,SUMIF(WORKLOAD!$C$4:$C$100,'VENTILATION CHARGE'!B13,WORKLOAD!$I$4:$I$100),"") | E13: =IF(SUMIF(WORKLOAD!$C$4:$C$100,'VENTILATION CHARGE'!B13,WORKLOAD!$J$4:$J$100)<>0,SUMIF(WORKLOAD!$C$4:$C$100,'VENTILATION CHARGE'!B13,WORKLOAD!$J$4:$J$100),"") | F13: =IF(SUMIF(WORKLOAD!$C$4:$C$100,'VENTILATION CHARGE'!B13,WORKLOAD!$K$4:$K$100)<>0,SUMIF(WORKLOAD!$C$4:$C$100,'VENTILATION CHARGE'!B13,WORKLOAD!$K$4:$K$100),"") | G13: =IF(SUMIF(WORKLOAD!$C$4:$C$100,'VENTILATION CHARGE'!B13,WORKLOAD!$L$4:$L$100)<>0,SUMIF(WORKLOAD!$C$4:$C$100,'VENTILATION CHARGE'!B13,WORKLOAD!$L$4:$L$100),"") | H13: =IF(SUMIF(WORKLOAD!$C$4:$C$100,'VENTILATION CHARGE'!B13,WORKLOAD!$M$4:$M$100)<>0,SUMIF(WORKLOAD!$C$4:$C$100,'VENTILATION CHARGE'!B13,WORKLOAD!$M$4:$M$100),"") | I13: =IF(SUMIF(WORKLOAD!$C$4:$C$100,'VENTILATION CHARGE'!B13,WORKLOAD!$N$4:$N$100)<>0,SUMIF(WORKLOAD!$C$4:$C$100,'VENTILATION CHARGE'!B13,WORKLOAD!$N$4:$N$100),"") | K13: =IF(SUM(C13:I13)<>0,SUM(C13:I13),"") | M13: =IFERROR(K54/K13,"")
B14: =REF!B12 -> PROVISION | C14: =IF(SUMIF(WORKLOAD!$C$4:$C$100,'VENTILATION CHARGE'!B14,WORKLOAD!$H$4:$H$100)<>0,SUMIF(WORKLOAD!$C$4:$C$100,'VENTILATION CHARGE'!B14,WORKLOAD!$H$4:$H$100),"") -> 0.5 | D14: =IF(SUMIF(WORKLOAD!$C$4:$C$100,'VENTILATION CHARGE'!B14,WORKLOAD!$I$4:$I$100)<>0,SUMIF(WORKLOAD!$C$4:$C$100,'VENTILATION CHARGE'!B14,WORKLOAD!$I$4:$I$100),"") -> 1 | E14: =IF(SUMIF(WORKLOAD!$C$4:$C$100,'VENTILATION CHARGE'!B14,WORKLOAD!$J$4:$J$100)<>0,SUMIF(WORKLOAD!$C$4:$C$100,'VENTILATION CHARGE'!B14,WORKLOAD!$J$4:$J$100),"") -> 1 | F14: =IF(SUMIF(WORKLOAD!$C$4:$C$100,'VENTILATION CHARGE'!B14,WORKLOAD!$K$4:$K$100)<>0,SUMIF(WORKLOAD!$C$4:$C$100,'VENTILATION CHARGE'!B14,WORKLOAD!$K$4:$K$100),"") -> 1.5 | G14: =IF(SUMIF(WORKLOAD!$C$4:$C$100,'VENTILATION CHARGE'!B14,WORKLOAD!$L$4:$L$100)<>0,SUMIF(WORKLOAD!$C$4:$C$100,'VENTILATION CHARGE'!B14,WORKLOAD!$L$4:$L$100),"") | H14: =IF(SUMIF(WORKLOAD!$C$4:$C$100,'VENTILATION CHARGE'!B14,WORKLOAD!$M$4:$M$100)<>0,SUMIF(WORKLOAD!$C$4:$C$100,'VENTILATION CHARGE'!B14,WORKLOAD!$M$4:$M$100),"") | I14: =IF(SUMIF(WORKLOAD!$C$4:$C$100,'VENTILATION CHARGE'!B14,WORKLOAD!$N$4:$N$100)<>0,SUMIF(WORKLOAD!$C$4:$C$100,'VENTILATION CHARGE'!B14,WORKLOAD!$N$4:$N$100),"") | K14: =IF(SUM(C14:I14)<>0,SUM(C14:I14),"") -> 4 | M14: =IFERROR(K55/K14,"") -> 756.25
B16: Charges | C16: =IF(SUM(C7:C14)<>0,SUM(C7:C14),"") -> 21.5 | D16: =IF(SUM(D7:D14)<>0,SUM(D7:D14),"") -> 10.5 | E16: =IF(SUM(E7:E14)<>0,SUM(E7:E14),"") -> 29.5 | F16: =IF(SUM(F7:F14)<>0,SUM(F7:F14),"") -> 37.5 | G16: =IF(SUM(G7:G14)<>0,SUM(G7:G14),"") -> 5 | H16: =IF(SUM(H7:H14)<>0,SUM(H7:H14),"") | I16: =IF(SUM(I7:I14)<>0,SUM(I7:I14),"") | K16: =SUM(K7:K14) -> 104 | M16: =IFERROR(K57/K16,"") -> 744.47115
B18: Montants | C18: =C57 -> 16125 | D18: =D57 -> 8925 | E18: =E57 -> 22125 | F18: =F57 -> 26250 | G18: =G57 -> 4000 | H18: =H57 | I18: =I57 | K18: =K57 -> 77425
B20: Ventilation des charges par étape
B23: ETAPE | C23: =WORKLOAD!H4 -> Chef de Projet | D23: =WORKLOAD!I4 -> Architecte | E23: =WORKLOAD!J4 -> Consultant Technique | F23: =WORKLOAD!K4 -> Consultant Change | G23: =WORKLOAD!L4 -> Consultant Data | H23: =WORKLOAD!M4 -> 0 | I23: =WORKLOAD!N4 -> 0 | K23: Charges
B24: =REF!D5 -> Pilotage projet | C24: =IF(SUMIF(WORKLOAD!$D$4:$D$100,B24,WORKLOAD!$H$4:$H$100)<>0,SUMIF(WORKLOAD!$D$4:$D$100,B24,WORKLOAD!$H$4:$H$100),"") -> 20.5 | D24: =IF(SUMIF(WORKLOAD!$D$4:$D$100,'VENTILATION CHARGE'!B24,WORKLOAD!$I$4:$I$100)<>0,SUMIF(WORKLOAD!$D$4:$D$100,'VENTILATION CHARGE'!B24,WORKLOAD!$I$4:$I$100),"") -> 0.5 | E24: =IF(SUMIF(WORKLOAD!$D$4:$D$100,B24,WORKLOAD!$J$4:$J$100)<>0,SUMIF(WORKLOAD!$D$4:$D$100,B24,WORKLOAD!$J$4:$J$100),"") | F24: =IF(SUMIF(WORKLOAD!$D$4:$D$100,B24,WORKLOAD!$K$4:$K$100)<>0,SUMIF(WORKLOAD!$D$4:$D$100,B24,WORKLOAD!$K$4:$K$100),"") -> 1 | G24: =IF(SUMIF(WORKLOAD!$D$4:$D$100,B24,WORKLOAD!$L$4:$L$100)<>0,SUMIF(WORKLOAD!$D$4:$D$100,B24,WORKLOAD!$L$4:$L$100),"") | H24: =IF(SUMIF(WORKLOAD!$D$4:$D$100,B24,WORKLOAD!$M$4:$M$100)<>0,SUMIF(WORKLOAD!$D$4:$D$100,B24,WORKLOAD!$M$4:$M$100),"") | I24: =IF(SUMIF(WORKLOAD!$D$4:$D$100,B24,WORKLOAD!$N$4:$N$100)<>0,SUMIF(WORKLOAD!$D$4:$D$100,B24,WORKLOAD!$N$4:$N$100),"") | K24: =IF(SUM(C24:I24)<>0,SUM(C24:I24),"") -> 22
B25: =REF!D6 -> Analyse de l'existant | C25: =IF(SUMIF(WORKLOAD!$D$4:$D$100,B25,WORKLOAD!$H$4:$H$100)<>0,SUMIF(WORKLOAD!$D$4:$D$100,B25,WORKLOAD!$H$4:$H$100),"") | D25: =IF(SUMIF(WORKLOAD!$D$4:$D$100,'VENTILATION CHARGE'!B25,WORKLOAD!$I$4:$I$100)<>0,SUMIF(WORKLOAD!$D$4:$D$100,'VENTILATION CHARGE'!B25,WORKLOAD!$I$4:$I$100),"") | E25: =IF(SUMIF(WORKLOAD!$D$4:$D$100,B25,WORKLOAD!$J$4:$J$100)<>0,SUMIF(WORKLOAD!$D$4:$D$100,B25,WORKLOAD!$J$4:$J$100),"") | F25: =IF(SUMIF(WORKLOAD!$D$4:$D$100,B25,WORKLOAD!$K$4:$K$100)<>0,SUMIF(WORKLOAD!$D$4:$D$100,B25,WORKLOAD!$K$4:$K$100),"") | G25: =IF(SUMIF(WORKLOAD!$D$4:$D$100,B25,WORKLOAD!$L$4:$L$100)<>0,SUMIF(WORKLOAD!$D$4:$D$100,B25,WORKLOAD!$L$4:$L$100),"") | H25: =IF(SUMIF(WORKLOAD!$D$4:$D$100,B25,WORKLOAD!$M$4:$M$100)<>0,SUMIF(WORKLOAD!$D$4:$D$100,B25,WORKLOAD!$M$4:$M$100),"") | I25: =IF(SUMIF(WORKLOAD!$D$4:$D$100,B25,WORKLOAD!$N$4:$N$100)<>0,SUMIF(WORKLOAD!$D$4:$D$100,B25,WORKLOAD!$N$4:$N$100),"") | K25: =IF(SUM(C25:I25)<>0,SUM(C25:I25),"")
B26: =REF!D7 -> Conception générale | C26: =IF(SUMIF(WORKLOAD!$D$4:$D$100,B26,WORKLOAD!$H$4:$H$100)<>0,SUMIF(WORKLOAD!$D$4:$D$100,B26,WORKLOAD!$H$4:$H$100),"") | D26: =IF(SUMIF(WORKLOAD!$D$4:$D$100,'VENTILATION CHARGE'!B26,WORKLOAD!$I$4:$I$100)<>0,SUMIF(WORKLOAD!$D$4:$D$100,'VENTILATION CHARGE'!B26,WORKLOAD!$I$4:$I$100),"") -> 1 | E26: =IF(SUMIF(WORKLOAD!$D$4:$D$100,B26,WORKLOAD!$J$4:$J$100)<>0,SUMIF(WORKLOAD!$D$4:$D$100,B26,WORKLOAD!$J$4:$J$100),"") -> 0.5 | F26: =IF(SUMIF(WORKLOAD!$D$4:$D$100,B26,WORKLOAD!$K$4:$K$100)<>0,SUMIF(WORKLOAD!$D$4:$D$100,B26,WORKLOAD!$K$4:$K$100),"") | G26: =IF(SUMIF(WORKLOAD!$D$4:$D$100,B26,WORKLOAD!$L$4:$L$100)<>0,SUMIF(WORKLOAD!$D$4:$D$100,B26,WORKLOAD!$L$4:$L$100),"") | H26: =IF(SUMIF(WORKLOAD!$D$4:$D$100,B26,WORKLOAD!$M$4:$M$100)<>0,SUMIF(WORKLOAD!$D$4:$D$100,B26,WORKLOAD!$M$4:$M$100),"") | I26: =IF(SUMIF(WORKLOAD!$D$4:$D$100,B26,WORKLOAD!$N$4:$N$100)<>0,SUMIF(WORKLOAD!$D$4:$D$100,B26,WORKLOAD!$N$4:$N$100),"") | K26: =IF(SUM(C26:I26)<>0,SUM(C26:I26),"") -> 1.5
B27: =REF!D8 -> Conception technique détaillée | C27: =IF(SUMIF(WORKLOAD!$D$4:$D$100,B27,WORKLOAD!$H$4:$H$100)<>0,SUMIF(WORKLOAD!$D$4:$D$100,B27,WORKLOAD!$H$4:$H$100),"") | D27: =IF(SUMIF(WORKLOAD!$D$4:$D$100,'VENTILATION CHARGE'!B27,WORKLOAD!$I$4:$I$100)<>0,SUMIF(WORKLOAD!$D$4:$D$100,'VENTILATION CHARGE'!B27,WORKLOAD!$I$4:$I$100),"") | E27: =IF(SUMIF(WORKLOAD!$D$4:$D$100,B27,WORKLOAD!$J$4:$J$100)<>0,SUMIF(WORKLOAD!$D$4:$D$100,B27,WORKLOAD!$J$4:$J$100),"") | F27: =IF(SUMIF(WORKLOAD!$D$4:$D$100,B27,WORKLOAD!$K$4:$K$100)<>0,SUMIF(WORKLOAD!$D$4:$D$100,B27,WORKLOAD!$K$4:$K$100),"") | G27: =IF(SUMIF(WORKLOAD!$D$4:$D$100,B27,WORKLOAD!$L$4:$L$100)<>0,SUMIF(WORKLOAD!$D$4:$D$100,B27,WORKLOAD!$L$4:$L$100),"") | H27: =IF(SUMIF(WORKLOAD!$D$4:$D$100,B27,WORKLOAD!$M$4:$M$100)<>0,SUMIF(WORKLOAD!$D$4:$D$100,B27,WORKLOAD!$M$4:$M$100),"") | I27: =IF(SUMIF(WORKLOAD!$D$4:$D$100,B27,WORKLOAD!$N$4:$N$100)<>0,SUMIF(WORKLOAD!$D$4:$D$100,B27,WORKLOAD!$N$4:$N$100),"") | K27: =IF(SUM(C27:I27)<>0,SUM(C27:I27),"")
B28: =REF!D9 -> Conception fonctionnelle détaillée | C28: =IF(SUMIF(WORKLOAD!$D$4:$D$100,B28,WORKLOAD!$H$4:$H$100)<>0,SUMIF(WORKLOAD!$D$4:$D$100,B28,WORKLOAD!$H$4:$H$100),"") | D28: =IF(SUMIF(WORKLOAD!$D$4:$D$100,'VENTILATION CHARGE'!B28,WORKLOAD!$I$4:$I$100)<>0,SUMIF(WORKLOAD!$D$4:$D$100,'VENTILATION CHARGE'!B28,WORKLOAD!$I$4:$I$100),"") -> 3 | E28: =IF(SUMIF(WORKLOAD!$D$4:$D$100,B28,WORKLOAD!$J$4:$J$100)<>0,SUMIF(WORKLOAD!$D$4:$D$100,B28,WORKLOAD!$J$4:$J$100),"") -> 1 | F28: =IF(SUMIF(WORKLOAD!$D$4:$D$100,B28,WORKLOAD!$K$4:$K$100)<>0,SUMIF(WORKLOAD!$D$4:$D$100,B28,WORKLOAD!$K$4:$K$100),"") | G28: =IF(SUMIF(WORKLOAD!$D$4:$D$100,B28,WORKLOAD!$L$4:$L$100)<>0,SUMIF(WORKLOAD!$D$4:$D$100,B28,WORKLOAD!$L$4:$L$100),"") | H28: =IF(SUMIF(WORKLOAD!$D$4:$D$100,B28,WORKLOAD!$M$4:$M$100)<>0,SUMIF(WORKLOAD!$D$4:$D$100,B28,WORKLOAD!$M$4:$M$100),"") | I28: =IF(SUMIF(WORKLOAD!$D$4:$D$100,B28,WORKLOAD!$N$4:$N$100)<>0,SUMIF(WORKLOAD!$D$4:$D$100,B28,WORKLOAD!$N$4:$N$100),"") | K28: =IF(SUM(C28:I28)<>0,SUM(C28:I28),"") -> 4
B29: =REF!D10 -> Ergonomie/Graphisme | C29: =IF(SUMIF(WORKLOAD!$D$4:$D$100,B29,WORKLOAD!$H$4:$H$100)<>0,SUMIF(WORKLOAD!$D$4:$D$100,B29,WORKLOAD!$H$4:$H$100),"") | D29: =IF(SUMIF(WORKLOAD!$D$4:$D$100,'VENTILATION CHARGE'!B29,WORKLOAD!$I$4:$I$100)<>0,SUMIF(WORKLOAD!$D$4:$D$100,'VENTILATION CHARGE'!B29,WORKLOAD!$I$4:$I$100),"") | E29: =IF(SUMIF(WORKLOAD!$D$4:$D$100,B29,WORKLOAD!$J$4:$J$100)<>0,SUMIF(WORKLOAD!$D$4:$D$100,B29,WORKLOAD!$J$4:$J$100),"") | F29: =IF(SUMIF(WORKLOAD!$D$4:$D$100,B29,WORKLOAD!$K$4:$K$100)<>0,SUMIF(WORKLOAD!$D$4:$D$100,B29,WORKLOAD!$K$4:$K$100),"") | G29: =IF(SUMIF(WORKLOAD!$D$4:$D$100,B29,WORKLOAD!$L$4:$L$100)<>0,SUMIF(WORKLOAD!$D$4:$D$100,B29,WORKLOAD!$L$4:$L$100),"") | H29: =IF(SUMIF(WORKLOAD!$D$4:$D$100,B29,WORKLOAD!$M$4:$M$100)<>0,SUMIF(WORKLOAD!$D$4:$D$100,B29,WORKLOAD!$M$4:$M$100),"") | I29: =IF(SUMIF(WORKLOAD!$D$4:$D$100,B29,WORKLOAD!$N$4:$N$100)<>0,SUMIF(WORKLOAD!$D$4:$D$100,B29,WORKLOAD!$N$4:$N$100),"") | K29: =IF(SUM(C29:I29)<>0,SUM(C29:I29),"")
B30: =REF!D11 -> Cahier de recette | C30: =IF(SUMIF(WORKLOAD!$D$4:$D$100,B30,WORKLOAD!$H$4:$H$100)<>0,SUMIF(WORKLOAD!$D$4:$D$100,B30,WORKLOAD!$H$4:$H$100),"") | D30: =IF(SUMIF(WORKLOAD!$D$4:$D$100,'VENTILATION CHARGE'!B30,WORKLOAD!$I$4:$I$100)<>0,SUMIF(WORKLOAD!$D$4:$D$100,'VENTILATION CHARGE'!B30,WORKLOAD!$I$4:$I$100),"") | E30: =IF(SUMIF(WORKLOAD!$D$4:$D$100,B30,WORKLOAD!$J$4:$J$100)<>0,SUMIF(WORKLOAD!$D$4:$D$100,B30,WORKLOAD!$J$4:$J$100),"") | F30: =IF(SUMIF(WORKLOAD!$D$4:$D$100,B30,WORKLOAD!$K$4:$K$100)<>0,SUMIF(WORKLOAD!$D$4:$D$100,B30,WORKLOAD!$K$4:$K$100),"") | G30: =IF(SUMIF(WORKLOAD!$D$4:$D$100,B30,WORKLOAD!$L$4:$L$100)<>0,SUMIF(WORKLOAD!$D$4:$D$100,B30,WORKLOAD!$L$4:$L$100),"") | H30: =IF(SUMIF(WORKLOAD!$D$4:$D$100,B30,WORKLOAD!$M$4:$M$100)<>0,SUMIF(WORKLOAD!$D$4:$D$100,B30,WORKLOAD!$M$4:$M$100),"") | I30: =IF(SUMIF(WORKLOAD!$D$4:$D$100,B30,WORKLOAD!$N$4:$N$100)<>0,SUMIF(WORKLOAD!$D$4:$D$100,B30,WORKLOAD!$N$4:$N$100),"") | K30: =IF(SUM(C30:I30)<>0,SUM(C30:I30),"")
B31: =REF!D12 -> Développement et tests unitaires | C31: =IF(SUMIF(WORKLOAD!$D$4:$D$100,B31,WORKLOAD!$H$4:$H$100)<>0,SUMIF(WORKLOAD!$D$4:$D$100,B31,WORKLOAD!$H$4:$H$100),"") | D31: =IF(SUMIF(WORKLOAD!$D$4:$D$100,'VENTILATION CHARGE'!B31,WORKLOAD!$I$4:$I$100)<>0,SUMIF(WORKLOAD!$D$4:$D$100,'VENTILATION CHARGE'!B31,WORKLOAD!$I$4:$I$100),"") | E31: =IF(SUMIF(WORKLOAD!$D$4:$D$100,B31,WORKLOAD!$J$4:$J$100)<>0,SUMIF(WORKLOAD!$D$4:$D$100,B31,WORKLOAD!$J$4:$J$100),"") -> 7.5 | F31: =IF(SUMIF(WORKLOAD!$D$4:$D$100,B31,WORKLOAD!$K$4:$K$100)<>0,SUMIF(WORKLOAD!$D$4:$D$100,B31,WORKLOAD!$K$4:$K$100),"") | G31: =IF(SUMIF(WORKLOAD!$D$4:$D$100,B31,WORKLOAD!$L$4:$L$100)<>0,SUMIF(WORKLOAD!$D$4:$D$100,B31,WORKLOAD!$L$4:$L$100),"") | H31: =IF(SUMIF(WORKLOAD!$D$4:$D$100,B31,WORKLOAD!$M$4:$M$100)<>0,SUMIF(WORKLOAD!$D$4:$D$100,B31,WORKLOAD!$M$4:$M$100),"") | I31: =IF(SUMIF(WORKLOAD!$D$4:$D$100,B31,WORKLOAD!$N$4:$N$100)<>0,SUMIF(WORKLOAD!$D$4:$D$100,B31,WORKLOAD!$N$4:$N$100),"") | K31: =IF(SUM(C31:I31)<>0,SUM(C31:I31),"") -> 7.5
B32: =REF!D13 -> Tests d'intégration / Recette interne | C32: =IF(SUMIF(WORKLOAD!$D$4:$D$100,B32,WORKLOAD!$H$4:$H$100)<>0,SUMIF(WORKLOAD!$D$4:$D$100,B32,WORKLOAD!$H$4:$H$100),"") | D32: =IF(SUMIF(WORKLOAD!$D$4:$D$100,'VENTILATION CHARGE'!B32,WORKLOAD!$I$4:$I$100)<>0,SUMIF(WORKLOAD!$D$4:$D$100,'VENTILATION CHARGE'!B32,WORKLOAD!$I$4:$I$100),"") | E32: =IF(SUMIF(WORKLOAD!$D$4:$D$100,B32,WORKLOAD!$J$4:$J$100)<>0,SUMIF(WORKLOAD!$D$4:$D$100,B32,WORKLOAD!$J$4:$J$100),"") | F32: =IF(SUMIF(WORKLOAD!$D$4:$D$100,B32,WORKLOAD!$K$4:$K$100)<>0,SUMIF(WORKLOAD!$D$4:$D$100,B32,WORKLOAD!$K$4:$K$100),"") | G32: =IF(SUMIF(WORKLOAD!$D$4:$D$100,B32,WORKLOAD!$L$4:$L$100)<>0,SUMIF(WORKLOAD!$D$4:$D$100,B32,WORKLOAD!$L$4:$L$100),"") | H32: =IF(SUMIF(WORKLOAD!$D$4:$D$100,B32,WORKLOAD!$M$4:$M$100)<>0,SUMIF(WORKLOAD!$D$4:$D$100,B32,WORKLOAD!$M$4:$M$100),"") | I32: =IF(SUMIF(WORKLOAD!$D$4:$D$100,B32,WORKLOAD!$N$4:$N$100)<>0,SUMIF(WORKLOAD!$D$4:$D$100,B32,WORKLOAD!$N$4:$N$100),"") | K32: =IF(SUM(C32:I32)<>0,SUM(C32:I32),"")
B33: =REF!D14 -> Livraison / installation / Mise en œuvre | C33: =IF(SUMIF(WORKLOAD!$D$4:$D$100,B33,WORKLOAD!$H$4:$H$100)<>0,SUMIF(WORKLOAD!$D$4:$D$100,B33,WORKLOAD!$H$4:$H$100),"") | D33: =IF(SUMIF(WORKLOAD!$D$4:$D$100,'VENTILATION CHARGE'!B33,WORKLOAD!$I$4:$I$100)<>0,SUMIF(WORKLOAD!$D$4:$D$100,'VENTILATION CHARGE'!B33,WORKLOAD!$I$4:$I$100),"") | E33: =IF(SUMIF(WORKLOAD!$D$4:$D$100,B33,WORKLOAD!$J$4:$J$100)<>0,SUMIF(WORKLOAD!$D$4:$D$100,B33,WORKLOAD!$J$4:$J$100),"") -> 3 | F33: =IF(SUMIF(WORKLOAD!$D$4:$D$100,B33,WORKLOAD!$K$4:$K$100)<>0,SUMIF(WORKLOAD!$D$4:$D$100,B33,WORKLOAD!$K$4:$K$100),"") -> 3 | G33: =IF(SUMIF(WORKLOAD!$D$4:$D$100,B33,WORKLOAD!$L$4:$L$100)<>0,SUMIF(WORKLOAD!$D$4:$D$100,B33,WORKLOAD!$L$4:$L$100),"") | H33: =IF(SUMIF(WORKLOAD!$D$4:$D$100,B33,WORKLOAD!$M$4:$M$100)<>0,SUMIF(WORKLOAD!$D$4:$D$100,B33,WORKLOAD!$M$4:$M$100),"") | I33: =IF(SUMIF(WORKLOAD!$D$4:$D$100,B33,WORKLOAD!$N$4:$N$100)<>0,SUMIF(WORKLOAD!$D$4:$D$100,B33,WORKLOAD!$N$4:$N$100),"") | K33: =IF(SUM(C33:I33)<>0,SUM(C33:I33),"") -> 6
B34: =REF!D15 -> Pilote | C34: =IF(SUMIF(WORKLOAD!$D$4:$D$100,B34,WORKLOAD!$H$4:$H$100)<>0,SUMIF(WORKLOAD!$D$4:$D$100,B34,WORKLOAD!$H$4:$H$100),"") | D34: =IF(SUMIF(WORKLOAD!$D$4:$D$100,'VENTILATION CHARGE'!B34,WORKLOAD!$I$4:$I$100)<>0,SUMIF(WORKLOAD!$D$4:$D$100,'VENTILATION CHARGE'!B34,WORKLOAD!$I$4:$I$100),"") | E34: =IF(SUMIF(WORKLOAD!$D$4:$D$100,B34,WORKLOAD!$J$4:$J$100)<>0,SUMIF(WORKLOAD!$D$4:$D$100,B34,WORKLOAD!$J$4:$J$100),"") | F34: =IF(SUMIF(WORKLOAD!$D$4:$D$100,B34,WORKLOAD!$K$4:$K$100)<>0,SUMIF(WORKLOAD!$D$4:$D$100,B34,WORKLOAD!$K$4:$K$100),"") | G34: =IF(SUMIF(WORKLOAD!$D$4:$D$100,B34,WORKLOAD!$L$4:$L$100)<>0,SUMIF(WORKLOAD!$D$4:$D$100,B34,WORKLOAD!$L$4:$L$100),"") | H34: =IF(SUMIF(WORKLOAD!$D$4:$D$100,B34,WORKLOAD!$M$4:$M$100)<>0,SUMIF(WORKLOAD!$D$4:$D$100,B34,WORKLOAD!$M$4:$M$100),"") | I34: =IF(SUMIF(WORKLOAD!$D$4:$D$100,B34,WORKLOAD!$N$4:$N$100)<>0,SUMIF(WORKLOAD!$D$4:$D$100,B34,WORKLOAD!$N$4:$N$100),"") | K34: =IF(SUM(C34:I34)<>0,SUM(C34:I34),"")
B35: =REF!D16 -> Généralisation | C35: =IF(SUMIF(WORKLOAD!$D$4:$D$100,B35,WORKLOAD!$H$4:$H$100)<>0,SUMIF(WORKLOAD!$D$4:$D$100,B35,WORKLOAD!$H$4:$H$100),"") | D35: =IF(SUMIF(WORKLOAD!$D$4:$D$100,'VENTILATION CHARGE'!B35,WORKLOAD!$I$4:$I$100)<>0,SUMIF(WORKLOAD!$D$4:$D$100,'VENTILATION CHARGE'!B35,WORKLOAD!$I$4:$I$100),"") | E35: =IF(SUMIF(WORKLOAD!$D$4:$D$100,B35,WORKLOAD!$J$4:$J$100)<>0,SUMIF(WORKLOAD!$D$4:$D$100,B35,WORKLOAD!$J$4:$J$100),"") | F35: =IF(SUMIF(WORKLOAD!$D$4:$D$100,B35,WORKLOAD!$K$4:$K$100)<>0,SUMIF(WORKLOAD!$D$4:$D$100,B35,WORKLOAD!$K$4:$K$100),"") | G35: =IF(SUMIF(WORKLOAD!$D$4:$D$100,B35,WORKLOAD!$L$4:$L$100)<>0,SUMIF(WORKLOAD!$D$4:$D$100,B35,WORKLOAD!$L$4:$L$100),"") | H35: =IF(SUMIF(WORKLOAD!$D$4:$D$100,B35,WORKLOAD!$M$4:$M$100)<>0,SUMIF(WORKLOAD!$D$4:$D$100,B35,WORKLOAD!$M$4:$M$100),"") | I35: =IF(SUMIF(WORKLOAD!$D$4:$D$100,B35,WORKLOAD!$N$4:$N$100)<>0,SUMIF(WORKLOAD!$D$4:$D$100,B35,WORKLOAD!$N$4:$N$100),"") | K35: =IF(SUM(C35:I35)<>0,SUM(C35:I35),"")
... B42: =REF!D23 -> Hors abaques | C42: =IF(SUMIF(WORKLOAD!$D$4:$D$100,B42,WORKLOAD!$H$4:$H$100)<>0,SUMIF(WORKLOAD!$D$4:$D$100,B42,WORKLOAD!$H$4:$H$100),"") | D42: =IF(SUMIF(WORKLOAD!$D$4:$D$100,'VENTILATION CHARGE'!B42,WORKLOAD!$I$4:$I$100)<>0,SUMIF(WORKLOAD!$D$4:$D$100,'VENTILATION CHARGE'!B42,WORKLOAD!$I$4:$I$100),"") | E42: =IF(SUMIF(WORKLOAD!$D$4:$D$100,B42,WORKLOAD!$J$4:$J$100)<>0,SUMIF(WORKLOAD!$D$4:$D$100,B42,WORKLOAD!$J$4:$J$100),"") | F42: =IF(SUMIF(WORKLOAD!$D$4:$D$100,B42,WORKLOAD!$K$4:$K$100)<>0,SUMIF(WORKLOAD!$D$4:$D$100,B42,WORKLOAD!$K$4:$K$100),"") | G42: =IF(SUMIF(WORKLOAD!$D$4:$D$100,B42,WORKLOAD!$L$4:$L$100)<>0,SUMIF(WORKLOAD!$D$4:$D$100,B42,WORKLOAD!$L$4:$L$100),"") | H42: =IF(SUMIF(WORKLOAD!$D$4:$D$100,B42,WORKLOAD!$M$4:$M$100)<>0,SUMIF(WORKLOAD!$D$4:$D$100,B42,WORKLOAD!$M$4:$M$100),"") | I42: =IF(SUMIF(WORKLOAD!$D$4:$D$100,B42,WORKLOAD!$N$4:$N$100)<>0,SUMIF(WORKLOAD!$D$4:$D$100,B42,WORKLOAD!$N$4:$N$100),"") | K42: =IF(SUM(C42:I42)<>0,SUM(C42:I42),"")
B44: TOTAL | C44: =IF(SUM(C24:C42)<>0,SUM(C24:C42),"") -> 21 | D44: =IF(SUM(D24:D42)<>0,SUM(D24:D42),"") -> 6.5 | E44: =IF(SUM(E24:E42)<>0,SUM(E24:E42),"") -> 26.5 | F44: =IF(SUM(F24:F42)<>0,SUM(F24:F42),"") -> 36 | G44: =IF(SUM(G24:G42)<>0,SUM(G24:G42),"") -> 5 | H44: =IF(SUM(H24:H42)<>0,SUM(H24:H42),"") | I44: =IF(SUM(I24:I42)<>0,SUM(I24:I42),"") | K44: =SUM(K24:K42) -> 95
B46: Ventilation des couts par profil
B47: PHASE | C47: =WORKLOAD!H4 -> Chef de Projet | D47: =WORKLOAD!I4 -> Architecte | E47: =WORKLOAD!J4 -> Consultant Technique | F47: =WORKLOAD!K4 -> Consultant Change | G47: =WORKLOAD!L4 -> Consultant Data | H47: =WORKLOAD!M4 -> 0 | I47: =WORKLOAD!N4 -> 0 | K47: Montants
B48: =REF!B5 -> PILOTAGE | C48: =IF(SUMIF(WORKLOAD!$C$4:$C$100,'VENTILATION CHARGE'!B48,WORKLOAD!$O$4:$O$100)<>0,SUMIF(WORKLOAD!$C$4:$C$100,'VENTILATION CHARGE'!B48,WORKLOAD!$O$4:$O$100),"") -> 15375 | D48: =IF(SUMIF(WORKLOAD!$C$4:$C$100,'VENTILATION CHARGE'!B48,WORKLOAD!$P$4:$P$100)<>0,SUMIF(WORKLOAD!$C$4:$C$100,'VENTILATION CHARGE'!B48,WORKLOAD!$P$4:$P$100),"") -> 425 | E48: =IF(SUMIF(WORKLOAD!$C$4:$C$100,'VENTILATION CHARGE'!B48,WORKLOAD!$Q$4:$Q$100)<>0,SUMIF(WORKLOAD!$C$4:$C$100,'VENTILATION CHARGE'!B48,WORKLOAD!$Q$4:$Q$100),"") | F48: =IF(SUMIF(WORKLOAD!$C$4:$C$100,'VENTILATION CHARGE'!B48,WORKLOAD!$R$4:$R$100)<>0,SUMIF(WORKLOAD!$C$4:$C$100,'VENTILATION CHARGE'!B48,WORKLOAD!$R$4:$R$100),"") -> 700 | G48: =IF(SUMIF(WORKLOAD!$C$4:$C$100,'VENTILATION CHARGE'!B48,WORKLOAD!$S$4:$S$100)<>0,SUMIF(WORKLOAD!$C$4:$C$100,'VENTILATION CHARGE'!B48,WORKLOAD!$S$4:$S$100),"") | H48: =IF(SUMIF(WORKLOAD!$C$4:$C$100,'VENTILATION CHARGE'!B48,WORKLOAD!$T$4:$T$100)<>0,SUMIF(WORKLOAD!$C$4:$C$100,'VENTILATION CHARGE'!B48,WORKLOAD!$T$4:$T$100),"") | I48: =IF(SUMIF(WORKLOAD!$C$4:$C$100,'VENTILATION CHARGE'!B48,WORKLOAD!$U$4:$U$100)<>0,SUMIF(WORKLOAD!$C$4:$C$100,'VENTILATION CHARGE'!B48,WORKLOAD!$U$4:$U$100),"") | K48: =IF(SUM(C48:I48)<>0,SUM(C48:I48),"") -> 16500
B49: =REF!B6 -> CONCEPTION | C49: =IF(SUMIF(WORKLOAD!$C$4:$C$100,'VENTILATION CHARGE'!B49,WORKLOAD!$O$4:$O$100)<>0,SUMIF(WORKLOAD!$C$4:$C$100,'VENTILATION CHARGE'!B49,WORKLOAD!$O$4:$O$100),"") | D49: =IF(SUMIF(WORKLOAD!$C$4:$C$100,'VENTILATION CHARGE'!B49,WORKLOAD!$P$4:$P$100)<>0,SUMIF(WORKLOAD!$C$4:$C$100,'VENTILATION CHARGE'!B49,WORKLOAD!$P$4:$P$100),"") -> 5950 | E49: =IF(SUMIF(WORKLOAD!$C$4:$C$100,'VENTILATION CHARGE'!B49,WORKLOAD!$Q$4:$Q$100)<>0,SUMIF(WORKLOAD!$C$4:$C$100,'VENTILATION CHARGE'!B49,WORKLOAD!$Q$4:$Q$100),"") -> 1125 | F49: =IF(SUMIF(WORKLOAD!$C$4:$C$100,'VENTILATION CHARGE'!B49,WORKLOAD!$R$4:$R$100)<>0,SUMIF(WORKLOAD!$C$4:$C$100,'VENTILATION CHARGE'!B49,WORKLOAD!$R$4:$R$100),"") | G49: =IF(SUMIF(WORKLOAD!$C$4:$C$100,'VENTILATION CHARGE'!B49,WORKLOAD!$S$4:$S$100)<>0,SUMIF(WORKLOAD!$C$4:$C$100,'VENTILATION CHARGE'!B49,WORKLOAD!$S$4:$S$100),"") | H49: =IF(SUMIF(WORKLOAD!$C$4:$C$100,'VENTILATION CHARGE'!B49,WORKLOAD!$T$4:$T$100)<>0,SUMIF(WORKLOAD!$C$4:$C$100,'VENTILATION CHARGE'!B49,WORKLOAD!$T$4:$T$100),"") | I49: =IF(SUMIF(WORKLOAD!$C$4:$C$100,'VENTILATION CHARGE'!B49,WORKLOAD!$U$4:$U$100)<>0,SUMIF(WORKLOAD!$C$4:$C$100,'VENTILATION CHARGE'!B49,WORKLOAD!$U$4:$U$100),"") | K49: =IF(SUM(C49:I49)<>0,SUM(C49:I49),"") -> 7075
B50: =REF!B7 -> CONSTRUCTION | C50: =IF(SUMIF(WORKLOAD!$C$4:$C$100,'VENTILATION CHARGE'!B50,WORKLOAD!$O$4:$O$100)<>0,SUMIF(WORKLOAD!$C$4:$C$100,'VENTILATION CHARGE'!B50,WORKLOAD!$O$4:$O$100),"") | D50: =IF(SUMIF(WORKLOAD!$C$4:$C$100,'VENTILATION CHARGE'!B50,WORKLOAD!$P$4:$P$100)<>0,SUMIF(WORKLOAD!$C$4:$C$100,'VENTILATION CHARGE'!B50,WORKLOAD!$P$4:$P$100),"") | E50: =IF(SUMIF(WORKLOAD!$C$4:$C$100,'VENTILATION CHARGE'!B50,WORKLOAD!$Q$4:$Q$100)<>0,SUMIF(WORKLOAD!$C$4:$C$100,'VENTILATION CHARGE'!B50,WORKLOAD!$Q$4:$Q$100),"") -> 5625 | F50: =IF(SUMIF(WORKLOAD!$C$4:$C$100,'VENTILATION CHARGE'!B50,WORKLOAD!$R$4:$R$100)<>0,SUMIF(WORKLOAD!$C$4:$C$100,'VENTILATION CHARGE'!B50,WORKLOAD!$R$4:$R$100),"") | G50: =IF(SUMIF(WORKLOAD!$C$4:$C$100,'VENTILATION CHARGE'!B50,WORKLOAD!$S$4:$S$100)<>0,SUMIF(WORKLOAD!$C$4:$C$100,'VENTILATION CHARGE'!B50,WORKLOAD!$S$4:$S$100),"") | H50: =IF(SUMIF(WORKLOAD!$C$4:$C$100,'VENTILATION CHARGE'!B50,WORKLOAD!$T$4:$T$100)<>0,SUMIF(WORKLOAD!$C$4:$C$100,'VENTILATION CHARGE'!B50,WORKLOAD!$T$4:$T$100),"") | I50: =IF(SUMIF(WORKLOAD!$C$4:$C$100,'VENTILATION CHARGE'!B50,WORKLOAD!$U$4:$U$100)<>0,SUMIF(WORKLOAD!$C$4:$C$100,'VENTILATION CHARGE'!B50,WORKLOAD!$U$4:$U$100),"") | K50: =IF(SUM(C50:I50)<>0,SUM(C50:I50),"") -> 5625
B51: =REF!B8 -> VALIDATION | C51: =IF(SUMIF(WORKLOAD!$C$4:$C$100,'VENTILATION CHARGE'!B51,WORKLOAD!$O$4:$O$100)<>0,SUMIF(WORKLOAD!$C$4:$C$100,'VENTILATION CHARGE'!B51,WORKLOAD!$O$4:$O$100),"") -> 375 | D51: =IF(SUMIF(WORKLOAD!$C$4:$C$100,'VENTILATION CHARGE'!B51,WORKLOAD!$P$4:$P$100)<>0,SUMIF(WORKLOAD!$C$4:$C$100,'VENTILATION CHARGE'!B51,WORKLOAD!$P$4:$P$100),"") | E51: =IF(SUMIF(WORKLOAD!$C$4:$C$100,'VENTILATION CHARGE'!B51,WORKLOAD!$Q$4:$Q$100)<>0,SUMIF(WORKLOAD!$C$4:$C$100,'VENTILATION CHARGE'!B51,WORKLOAD!$Q$4:$Q$100),"") -> 12375 | F51: =IF(SUMIF(WORKLOAD!$C$4:$C$100,'VENTILATION CHARGE'!B51,WORKLOAD!$R$4:$R$100)<>0,SUMIF(WORKLOAD!$C$4:$C$100,'VENTILATION CHARGE'!B51,WORKLOAD!$R$4:$R$100),"") -> 23800 | G51: =IF(SUMIF(WORKLOAD!$C$4:$C$100,'VENTILATION CHARGE'!B51,WORKLOAD!$S$4:$S$100)<>0,SUMIF(WORKLOAD!$C$4:$C$100,'VENTILATION CHARGE'!B51,WORKLOAD!$S$4:$S$100),"") -> 4000 | H51: =IF(SUMIF(WORKLOAD!$C$4:$C$100,'VENTILATION CHARGE'!B51,WORKLOAD!$T$4:$T$100)<>0,SUMIF(WORKLOAD!$C$4:$C$100,'VENTILATION CHARGE'!B51,WORKLOAD!$T$4:$T$100),"") | I51: =IF(SUMIF(WORKLOAD!$C$4:$C$100,'VENTILATION CHARGE'!B51,WORKLOAD!$U$4:$U$100)<>0,SUMIF(WORKLOAD!$C$4:$C$100,'VENTILATION CHARGE'!B51,WORKLOAD!$U$4:$U$100),"") | K51: =IF(SUM(C51:I51)<>0,SUM(C51:I51),"") -> 40550
B52: =REF!B9 -> FINALISATION | C52: =IF(SUMIF(WORKLOAD!$C$4:$C$100,'VENTILATION CHARGE'!B52,WORKLOAD!$O$4:$O$100)<>0,SUMIF(WORKLOAD!$C$4:$C$100,'VENTILATION CHARGE'!B52,WORKLOAD!$O$4:$O$100),"") | D52: =IF(SUMIF(WORKLOAD!$C$4:$C$100,'VENTILATION CHARGE'!B52,WORKLOAD!$P$4:$P$100)<>0,SUMIF(WORKLOAD!$C$4:$C$100,'VENTILATION CHARGE'!B52,WORKLOAD!$P$4:$P$100),"") -> 1700 | E52: =IF(SUMIF(WORKLOAD!$C$4:$C$100,'VENTILATION CHARGE'!B52,WORKLOAD!$Q$4:$Q$100)<>0,SUMIF(WORKLOAD!$C$4:$C$100,'VENTILATION CHARGE'!B52,WORKLOAD!$Q$4:$Q$100),"") -> 2250 | F52: =IF(SUMIF(WORKLOAD!$C$4:$C$100,'VENTILATION CHARGE'!B52,WORKLOAD!$R$4:$R$100)<>0,SUMIF(WORKLOAD!$C$4:$C$100,'VENTILATION CHARGE'!B52,WORKLOAD!$R$4:$R$100),"") -> 700 | G52: =IF(SUMIF(WORKLOAD!$C$4:$C$100,'VENTILATION CHARGE'!B52,WORKLOAD!$S$4:$S$100)<>0,SUMIF(WORKLOAD!$C$4:$C$100,'VENTILATION CHARGE'!B52,WORKLOAD!$S$4:$S$100),"") | H52: =IF(SUMIF(WORKLOAD!$C$4:$C$100,'VENTILATION CHARGE'!B52,WORKLOAD!$T$4:$T$100)<>0,SUMIF(WORKLOAD!$C$4:$C$100,'VENTILATION CHARGE'!B52,WORKLOAD!$T$4:$T$100),"") | I52: =IF(SUMIF(WORKLOAD!$C$4:$C$100,'VENTILATION CHARGE'!B52,WORKLOAD!$U$4:$U$100)<>0,SUMIF(WORKLOAD!$C$4:$C$100,'VENTILATION CHARGE'!B52,WORKLOAD!$U$4:$U$100),"") | K52: =IF(SUM(C52:I52)<>0,SUM(C52:I52),"") -> 4650
B53: =REF!B10 -> GARANTIE | C53: =IF(SUMIF(WORKLOAD!$C$4:$C$100,'VENTILATION CHARGE'!B53,WORKLOAD!$O$4:$O$100)<>0,SUMIF(WORKLOAD!$C$4:$C$100,'VENTILATION CHARGE'!B53,WORKLOAD!$O$4:$O$100),"") | D53: =IF(SUMIF(WORKLOAD!$C$4:$C$100,'VENTILATION CHARGE'!B53,WORKLOAD!$P$4:$P$100)<>0,SUMIF(WORKLOAD!$C$4:$C$100,'VENTILATION CHARGE'!B53,WORKLOAD!$P$4:$P$100),"") | E53: =IF(SUMIF(WORKLOAD!$C$4:$C$100,'VENTILATION CHARGE'!B53,WORKLOAD!$Q$4:$Q$100)<>0,SUMIF(WORKLOAD!$C$4:$C$100,'VENTILATION CHARGE'!B53,WORKLOAD!$Q$4:$Q$100),"") | F53: =IF(SUMIF(WORKLOAD!$C$4:$C$100,'VENTILATION CHARGE'!B53,WORKLOAD!$R$4:$R$100)<>0,SUMIF(WORKLOAD!$C$4:$C$100,'VENTILATION CHARGE'!B53,WORKLOAD!$R$4:$R$100),"") | G53: =IF(SUMIF(WORKLOAD!$C$4:$C$100,'VENTILATION CHARGE'!B53,WORKLOAD!$S$4:$S$100)<>0,SUMIF(WORKLOAD!$C$4:$C$100,'VENTILATION CHARGE'!B53,WORKLOAD!$S$4:$S$100),"") | H53: =IF(SUMIF(WORKLOAD!$C$4:$C$100,'VENTILATION CHARGE'!B53,WORKLOAD!$T$4:$T$100)<>0,SUMIF(WORKLOAD!$C$4:$C$100,'VENTILATION CHARGE'!B53,WORKLOAD!$T$4:$T$100),"") | I53: =IF(SUMIF(WORKLOAD!$C$4:$C$100,'VENTILATION CHARGE'!B53,WORKLOAD!$U$4:$U$100)<>0,SUMIF(WORKLOAD!$C$4:$C$100,'VENTILATION CHARGE'!B53,WORKLOAD!$U$4:$U$100),"") | K53: =IF(SUM(C53:I53)<>0,SUM(C53:I53),"")
B54: =REF!B11 -> TMA | C54: =IF(SUMIF(WORKLOAD!$C$4:$C$100,'VENTILATION CHARGE'!B54,WORKLOAD!$O$4:$O$100)<>0,SUMIF(WORKLOAD!$C$4:$C$100,'VENTILATION CHARGE'!B54,WORKLOAD!$O$4:$O$100),"") | D54: =IF(SUMIF(WORKLOAD!$C$4:$C$100,'VENTILATION CHARGE'!B54,WORKLOAD!$P$4:$P$100)<>0,SUMIF(WORKLOAD!$C$4:$C$100,'VENTILATION CHARGE'!B54,WORKLOAD!$P$4:$P$100),"") | E54: =IF(SUMIF(WORKLOAD!$C$4:$C$100,'VENTILATION CHARGE'!B54,WORKLOAD!$Q$4:$Q$100)<>0,SUMIF(WORKLOAD!$C$4:$C$100,'VENTILATION CHARGE'!B54,WORKLOAD!$Q$4:$Q$100),"") | F54: =IF(SUMIF(WORKLOAD!$C$4:$C$100,'VENTILATION CHARGE'!B54,WORKLOAD!$R$4:$R$100)<>0,SUMIF(WORKLOAD!$C$4:$C$100,'VENTILATION CHARGE'!B54,WORKLOAD!$R$4:$R$100),"") | G54: =IF(SUMIF(WORKLOAD!$C$4:$C$100,'VENTILATION CHARGE'!B54,WORKLOAD!$S$4:$S$100)<>0,SUMIF(WORKLOAD!$C$4:$C$100,'VENTILATION CHARGE'!B54,WORKLOAD!$S$4:$S$100),"") | H54: =IF(SUMIF(WORKLOAD!$C$4:$C$100,'VENTILATION CHARGE'!B54,WORKLOAD!$T$4:$T$100)<>0,SUMIF(WORKLOAD!$C$4:$C$100,'VENTILATION CHARGE'!B54,WORKLOAD!$T$4:$T$100),"") | I54: =IF(SUMIF(WORKLOAD!$C$4:$C$100,'VENTILATION CHARGE'!B54,WORKLOAD!$U$4:$U$100)<>0,SUMIF(WORKLOAD!$C$4:$C$100,'VENTILATION CHARGE'!B54,WORKLOAD!$U$4:$U$100),"") | K54: =IF(SUM(C54:I54)<>0,SUM(C54:I54),"")
B55: =REF!B12 -> PROVISION | C55: =IF(SUMIF(WORKLOAD!$C$4:$C$100,'VENTILATION CHARGE'!B55,WORKLOAD!$O$4:$O$100)<>0,SUMIF(WORKLOAD!$C$4:$C$100,'VENTILATION CHARGE'!B55,WORKLOAD!$O$4:$O$100),"") -> 375 | D55: =IF(SUMIF(WORKLOAD!$C$4:$C$100,'VENTILATION CHARGE'!B55,WORKLOAD!$P$4:$P$100)<>0,SUMIF(WORKLOAD!$C$4:$C$100,'VENTILATION CHARGE'!B55,WORKLOAD!$P$4:$P$100),"") -> 850 | E55: =IF(SUMIF(WORKLOAD!$C$4:$C$100,'VENTILATION CHARGE'!B55,WORKLOAD!$Q$4:$Q$100)<>0,SUMIF(WORKLOAD!$C$4:$C$100,'VENTILATION CHARGE'!B55,WORKLOAD!$Q$4:$Q$100),"") -> 750 | F55: =IF(SUMIF(WORKLOAD!$C$4:$C$100,'VENTILATION CHARGE'!B55,WORKLOAD!$R$4:$R$100)<>0,SUMIF(WORKLOAD!$C$4:$C$100,'VENTILATION CHARGE'!B55,WORKLOAD!$R$4:$R$100),"") -> 1050 | G55: =IF(SUMIF(WORKLOAD!$C$4:$C$100,'VENTILATION CHARGE'!B55,WORKLOAD!$S$4:$S$100)<>0,SUMIF(WORKLOAD!$C$4:$C$100,'VENTILATION CHARGE'!B55,WORKLOAD!$S$4:$S$100),"") | H55: =IF(SUMIF(WORKLOAD!$C$4:$C$100,'VENTILATION CHARGE'!B55,WORKLOAD!$T$4:$T$100)<>0,SUMIF(WORKLOAD!$C$4:$C$100,'VENTILATION CHARGE'!B55,WORKLOAD!$T$4:$T$100),"") | I55: =IF(SUMIF(WORKLOAD!$C$4:$C$100,'VENTILATION CHARGE'!B55,WORKLOAD!$U$4:$U$100)<>0,SUMIF(WORKLOAD!$C$4:$C$100,'VENTILATION CHARGE'!B55,WORKLOAD!$U$4:$U$100),"") | K55: =IF(SUM(C55:I55)<>0,SUM(C55:I55),"") -> 3025
B57: TOTAL | C57: =IF(SUM(C48:C55)<>0,SUM(C48:C55),"") -> 16125 | D57: =IF(SUM(D48:D55)<>0,SUM(D48:D55),"") -> 8925 | E57: =IF(SUM(E48:E55)<>0,SUM(E48:E55),"") -> 22125 | F57: =IF(SUM(F48:F55)<>0,SUM(F48:F55),"") -> 26250 | G57: =IF(SUM(G48:G55)<>0,SUM(G48:G55),"") -> 4000 | H57: =IF(SUM(H48:H55)<>0,SUM(H48:H55),"") | I57: =IF(SUM(I48:I55)<>0,SUM(I48:I55),"") | K57: =SUM(K48:K55) -> 77425

Sheet VERSION

Sheet REF
B1: Référence
B4: PHASE | D4: ETAPE | F4: PROFIL | H4: MOIS | J4: TYPE ACHAT | L4: ACTIVITE | N4: AGENCE
B5: PILOTAGE | D5: Pilotage projet | F5: Consultant Junior | H5: 45292 | J5: CSP Microsoft | L5: Apps & Infrastructure | N5: AgilityCenter
B6: CONCEPTION | D6: Analyse de l'existant | F6: Consultant Change | H6: 45323 | J6: JetBrains | L6: Apps & Infrastructure & Data | N6: Aix
B7: CONSTRUCTION | D7: Conception générale | F7: Consultant Technique | H7: 45352 | J7: Logiciel | L7: Business Intelligence | N7: Nice
B8: VALIDATION | D8: Conception technique détaillée | F8: Consultant Data | H8: 45383 | J8: ManageEngine | L8: Change Management & Motion Design | N8: Lyon
B9: FINALISATION | D9: Conception fonctionnelle détaillée | F9: Expert senior | H9: 45413 | J9: Matériel | L9: Data BI & IA | N9: Clermont
B10: GARANTIE | D10: Ergonomie/Graphisme | F10: Architecte | H10: 45444 | J10: Skillisy | L10: Enterprise Solution Center | N10: Grenoble
B11: TMA | D11: Cahier de recette | F11: Architecte Senior | H11: 45474 | J11: Rescue | L11: Intelligence Artificielle | N11: Toulouse
B12: PROVISION | D12: Développement et tests unitaires | F12: Chef de Projet | H12: 45505 | J12: Run2C | L12: Modern Apps | N12: Agence Ouest
D13: Tests d'intégration / Recette interne | F13: Chef de Projet Senior | H13: 45536 | J13: Support - MCO | L13: Modern Desktop | N13: Nord
D14: Livraison / installation / Mise en œuvre | F14: Directeur de projet | H14: 45566 | L14: Modern Workplace | N14: Paris
D15: Pilote | F15: Consultant Fonctionnel | H15: 45597 | L15: Modern Data Center | N15: CSV Infra
D16: Généralisation | F16: Consultant Fonctionnel Senior | H16: 45627 | L16: Desktop & Trust | N16: CSV Log
D17: Support | F17: Expert fonctionnel | H17: 45658 | L17: Identity & Trust | N17: Maroc
D18: Reprise de contenu | F18: Référent | H18: 45689 | L18: Productivity & Mobility | N18: EMS
D19: Assistance recette | F19: Manager | H19: 45717 | L19: Support | N19: Magellan
D20: Formation | F20: Dev Confirmé | H20: 45748 | L20: Non Applicable | N20: Structure
D21: Garantie (suite recette - 3 mois) | F21: Dev Junior
D22: Provision pour risque | F22: Testeur
D23: Hors abaques
